Workbook

Sheet 안내
A1: M&A 188건 수집 시트
A3: 원본 | B3: meeting/20261102/MA188_수집시트.csv, MA188_근거.csv (이 파일은 그 CSV를 nbs/ma188_export_xlsx.py로 옮긴 것)
A4: 내용 | B4: CJ ENM 30·Kakao 74·Naver 84, 거래 188건과 근거 4371행. 설계와 결과 해석은 meeting/20261102/주차연구정리_20261102.md
A5: 시트
A6: 요약 | B6: 기업별 수집 상태, 분류 대조표, 손상·편입 시점·금액 대조 집계. 모두 '거래' 시트를 세는 수식
A7: 거래 | B7: 한 행이 한 거래. 1행은 열 묶음, 2행은 열 이름, 3행은 CSV 열 이름이며 3행에 필터가 있다. 거래·기업·날짜·대상회사 열은 고정
A8: 근거 | B8: 한 행이 근거 하나. URL을 누르면 원문이 열린다. '뒷받침하는 열'은 그 근거가 '거래' 시트의 어느 열 값을 뒷받침하는지 적은 것
A9: 열 묶음
A10: 식별 | B10: 거래 번호(C=CJ ENM, K=Kakao, N=Naver), 날짜, 대상회사, 원자료 금액 순위
A11: 분류 요약 (파생) | B11: 원래 열에서 뽑은 값. 거래 형태 (설명란 판정)·거래 형태 (공시 확인)(MA①~⑦ 코드), 형태 변경(변경/같음), 손상 구분(있음 / 없음 (확인) / 식별 불가 / 미확인 / 해당 없음, 근거는 '손상 구분 근거' 열), 금액 대조(일치/불일치/기타), 편입 시점
A12: 원자료 (Capital IQ) | B12: Capital IQ에서 추출한 그대로의 값: 상태, 금액, 매수자, 매도자, 설명란
A13: v4 분야 | B13: v4 파일에서 추가된 12개 분야. Capital IQ 원본에는 없고, 이번 수집에서 확인하지 않았다
A14: 10-19 설명란 판정 | B14: 10-19 분석(nbs/pp_ma_record_audit.py)이 설명란·매수자·매도자 칸을 규칙으로 읽어 붙인 값. 편입 전 표시는 작성자의 배경지식(경영통합 연도 등)에 기댄다
A15: 공시 확인 | B15: 공시·감사보고서로 확인한 거래 형태, 편입 시점, 상태, 금액, 발표일과 메모
A16: 인수 목적·핵심 / 규모 / 주가 이벤트 | B16: 발표 당시 목적, 핵심 여부, 인수 주체·그룹 정점의 규모와 비율, 종목과 처음 알려진 날
A17: 전후 이벤트 / 성과 | B17: 인수 전후 사건, 손상, 대상회사 인수 전후 매출·영업이익, 어닝콜 언급
A18: 수집 | B18: 수집 상태(완료 = 모든 항목을 채움, 부분 = 공개 자료가 없어 비어 있는 항목이 있음)와 수집 일시
A19: 값 표기 | B19: 미확인 = 찾았지만 근거가 없음 · 해당 없음 = 그 거래에 해당하지 않음 · 추정: = 추정한 값
A20: 색 | B20: 거래 형태 (공시 확인)·형태 변경 칸 청록 = 설명란 판정과 거래 형태가 다름 · 손상 구분 빨강 = 있음, 초록 = 없음 (확인), 주황 = 식별 불가·미확인 · 금액 대조 빨강 = 불일치 · 수집 상태 초록 = 완료
A21: 손상 구분 | B21: 있음 = 인수 뒤 손상 확인 · 없음 (확인) = 인수 뒤 영업권·투자주식이 손상 없이 유지됨을 확인 · 식별 불가 = 영업권이 부문 단위로 묶여 이 거래 몫을 알 수 없음 · 미확인 = 확인 기간이 짧거나 비어 판단 자료 부족 · 해당 없음 = 그룹 밖 매수자, 그룹의 매각, 동일지배 합병, 공정가치 금융자산 등 구조상 손상을 따지지 않는 거래
... A23: 행 높이 | B23: 긴 글은 칸 안에서 줄바꿈되고 행 높이는 고정이다. 전체 내용은 셀을 선택해 수식 입력줄에서 보거나 행 높이를 늘려 본다

Sheet 요약
A1: M&A 188건 수집 결과 요약
A2: 모든 수치는 '거래' 시트를 세는 수식이다. '거래' 시트를 고치면 함께 바뀐다.
A4: 기업별 수집 상태
A5: 기업 | B5: 완료 | C5: 부분 | D5: 합계
A6: CJ ENM | B6: =COUNTIFS(거래!$B$4:$B$191,$A6,거래!$BF$4:$BF$191,"완료") | C6: =COUNTIFS(거래!$B$4:$B$191,$A6,거래!$BF$4:$BF$191,"부분") | D6: =SUM(B6:C6)
A7: Kakao | B7: =COUNTIFS(거래!$B$4:$B$191,$A7,거래!$BF$4:$BF$191,"완료") | C7: =COUNTIFS(거래!$B$4:$B$191,$A7,거래!$BF$4:$BF$191,"부분") | D7: =SUM(B7:C7)
A8: Naver | B8: =COUNTIFS(거래!$B$4:$B$191,$A8,거래!$BF$4:$BF$191,"완료") | C8: =COUNTIFS(거래!$B$4:$B$191,$A8,거래!$BF$4:$BF$191,"부분") | D8: =SUM(B8:C8)
A9: 합계 | B9: =SUM(B6:B8) | C9: =SUM(C6:C8) | D9: =SUM(D6:D8)
A11: 거래 형태: 설명란 판정(행) → 공시 확인(열)
A12: 설명란 판정 | B12: MA① 경영권 인수 | C12: MA② 기존 지분 확대 | D12: MA③ 소수지분 매입 | E12: MA④ 그룹 내부 재편 | F12: MA⑤ 그룹의 지분 매각 | G12: MA⑥ 외부자 간 거래 | H12: 합계
A13: MA① 경영권 인수 | B13: =COUNTIFS(거래!$H$4:$H$191,"MA①",거래!$I$4:$I$191,"MA①") | C13: =COUNTIFS(거래!$H$4:$H$191,"MA①",거래!$I$4:$I$191,"MA②") | D13: =COUNTIFS(거래!$H$4:$H$191,"MA①",거래!$I$4:$I$191,"MA③") | E13: =COUNTIFS(거래!$H$4:$H$191,"MA①",거래!$I$4:$I$191,"MA④") | F13: =COUNTIFS(거래!$H$4:$H$191,"MA①",거래!$I$4:$I$191,"MA⑤") | G13: =COUNTIFS(거래!$H$4:$H$191,"MA①",거래!$I$4:$I$191,"MA⑥") | H13: =SUM(B13:G13)
A14: MA② 기존 지분 확대 | B14: =COUNTIFS(거래!$H$4:$H$191,"MA②",거래!$I$4:$I$191,"MA①") | C14: =COUNTIFS(거래!$H$4:$H$191,"MA②",거래!$I$4:$I$191,"MA②") | D14: =COUNTIFS(거래!$H$4:$H$191,"MA②",거래!$I$4:$I$191,"MA③") | E14: =COUNTIFS(거래!$H$4:$H$191,"MA②",거래!$I$4:$I$191,"MA④") | F14: =COUNTIFS(거래!$H$4:$H$191,"MA②",거래!$I$4:$I$191,"MA⑤") | G14: =COUNTIFS(거래!$H$4:$H$191,"MA②",거래!$I$4:$I$191,"MA⑥") | H14: =SUM(B14:G14)
A15: MA③ 소수지분 매입 | B15: =COUNTIFS(거래!$H$4:$H$191,"MA③",거래!$I$4:$I$191,"MA①") | C15: =COUNTIFS(거래!$H$4:$H$191,"MA③",거래!$I$4:$I$191,"MA②") | D15: =COUNTIFS(거래!$H$4:$H$191,"MA③",거래!$I$4:$I$191,"MA③") | E15: =COUNTIFS(거래!$H$4:$H$191,"MA③",거래!$I$4:$I$191,"MA④") | F15: =COUNTIFS(거래!$H$4:$H$191,"MA③",거래!$I$4:$I$191,"MA⑤") | G15: =COUNTIFS(거래!$H$4:$H$191,"MA③",거래!$I$4:$I$191,"MA⑥") | H15: =SUM(B15:G15)
A16: MA④ 그룹 내부 재편 | B16: =COUNTIFS(거래!$H$4:$H$191,"MA④",거래!$I$4:$I$191,"MA①") | C16: =COUNTIFS(거래!$H$4:$H$191,"MA④",거래!$I$4:$I$191,"MA②") | D16: =COUNTIFS(거래!$H$4:$H$191,"MA④",거래!$I$4:$I$191,"MA③") | E16: =COUNTIFS(거래!$H$4:$H$191,"MA④",거래!$I$4:$I$191,"MA④") | F16: =COUNTIFS(거래!$H$4:$H$191,"MA④",거래!$I$4:$I$191,"MA⑤") | G16: =COUNTIFS(거래!$H$4:$H$191,"MA④",거래!$I$4:$I$191,"MA⑥") | H16: =SUM(B16:G16)
A17: MA⑤ 그룹의 지분 매각 | B17: =COUNTIFS(거래!$H$4:$H$191,"MA⑤",거래!$I$4:$I$191,"MA①") | C17: =COUNTIFS(거래!$H$4:$H$191,"MA⑤",거래!$I$4:$I$191,"MA②") | D17: =COUNTIFS(거래!$H$4:$H$191,"MA⑤",거래!$I$4:$I$191,"MA③") | E17: =COUNTIFS(거래!$H$4:$H$191,"MA⑤",거래!$I$4:$I$191,"MA④") | F17: =COUNTIFS(거래!$H$4:$H$191,"MA⑤",거래!$I$4:$I$191,"MA⑤") | G17: =COUNTIFS(거래!$H$4:$H$191,"MA⑤",거래!$I$4:$I$191,"MA⑥") | H17: =SUM(B17:G17)
A18: MA⑥ 외부자 간 거래 | B18: =COUNTIFS(거래!$H$4:$H$191,"MA⑥",거래!$I$4:$I$191,"MA①") | C18: =COUNTIFS(거래!$H$4:$H$191,"MA⑥",거래!$I$4:$I$191,"MA②") | D18: =COUNTIFS(거래!$H$4:$H$191,"MA⑥",거래!$I$4:$I$191,"MA③") | E18: =COUNTIFS(거래!$H$4:$H$191,"MA⑥",거래!$I$4:$I$191,"MA④") | F18: =COUNTIFS(거래!$H$4:$H$191,"MA⑥",거래!$I$4:$I$191,"MA⑤") | G18: =COUNTIFS(거래!$H$4:$H$191,"MA⑥",거래!$I$4:$I$191,"MA⑥") | H18: =SUM(B18:G18)
A19: MA⑦ 매수자 미기재 | B19: =COUNTIFS(거래!$H$4:$H$191,"MA⑦",거래!$I$4:$I$191,"MA①") | C19: =COUNTIFS(거래!$H$4:$H$191,"MA⑦",거래!$I$4:$I$191,"MA②") | D19: =COUNTIFS(거래!$H$4:$H$191,"MA⑦",거래!$I$4:$I$191,"MA③") | E19: =COUNTIFS(거래!$H$4:$H$191,"MA⑦",거래!$I$4:$I$191,"MA④") | F19: =COUNTIFS(거래!$H$4:$H$191,"MA⑦",거래!$I$4:$I$191,"MA⑤") | G19: =COUNTIFS(거래!$H$4:$H$191,"MA⑦",거래!$I$4:$I$191,"MA⑥") | H19: =SUM(B19:G19)
A20: 합계 | B20: =SUM(B13:B19) | C20: =SUM(C13:C19) | D20: =SUM(D13:D19) | E20: =SUM(E13:E19) | F20: =SUM(F13:F19) | G20: =SUM(G13:G19) | H20: =SUM(H13:H19)
A22: 기업별 손상 구분 (188건 전체)
A23: 기업 | B23: 있음 | C23: 없음 (확인) | D23: 식별 불가 | E23: 미확인 | F23: 해당 없음 | G23: 합계
A24: CJ ENM | B24: =COUNTIFS(거래!$B$4:$B$191,$A24,거래!$K$4:$K$191,"있음") | C24: =COUNTIFS(거래!$B$4:$B$191,$A24,거래!$K$4:$K$191,"없음 (확인)") | D24: =COUNTIFS(거래!$B$4:$B$191,$A24,거래!$K$4:$K$191,"식별 불가") | E24: =COUNTIFS(거래!$B$4:$B$191,$A24,거래!$K$4:$K$191,"미확인") | F24: =COUNTIFS(거래!$B$4:$B$191,$A24,거래!$K$4:$K$191,"해당 없음") | G24: =SUM(B24:F24)
A25: Kakao | B25: =COUNTIFS(거래!$B$4:$B$191,$A25,거래!$K$4:$K$191,"있음") | C25: =COUNTIFS(거래!$B$4:$B$191,$A25,거래!$K$4:$K$191,"없음 (확인)") | D25: =COUNTIFS(거래!$B$4:$B$191,$A25,거래!$K$4:$K$191,"식별 불가") | E25: =COUNTIFS(거래!$B$4:$B$191,$A25,거래!$K$4:$K$191,"미확인") | F25: =COUNTIFS(거래!$B$4:$B$191,$A25,거래!$K$4:$K$191,"해당 없음") | G25: =SUM(B25:F25)
A26: Naver | B26: =COUNTIFS(거래!$B$4:$B$191,$A26,거래!$K$4:$K$191,"있음") | C26: =COUNTIFS(거래!$B$4:$B$191,$A26,거래!$K$4:$K$191,"없음 (확인)") | D26: =COUNTIFS(거래!$B$4:$B$191,$A26,거래!$K$4:$K$191,"식별 불가") | E26: =COUNTIFS(거래!$B$4:$B$191,$A26,거래!$K$4:$K$191,"미확인") | F26: =COUNTIFS(거래!$B$4:$B$191,$A26,거래!$K$4:$K$191,"해당 없음") | G26: =SUM(B26:F26)
A27: 합계 | B27: =SUM(B24:B26) | C27: =SUM(C24:C26) | D27: =SUM(D24:D26) | E27: =SUM(E24:E26) | F27: =SUM(F24:F26) | G27: =SUM(G24:G26)
A29: 기업별 편입 시점 판정
A30: 기업 | B30: 편입 후 | C30: 편입 전 | D30: 지분법 합작 계열 | E30: 합계
A31: CJ ENM | B31: =COUNTIFS(거래!$B$4:$B$191,$A31,거래!$M$4:$M$191,"편입 후") | C31: =COUNTIFS(거래!$B$4:$B$191,$A31,거래!$M$4:$M$191,"편입 전") | D31: =COUNTIFS(거래!$B$4:$B$191,$A31,거래!$M$4:$M$191,"지분법 합작 계열") | E31: =SUM(B31:D31)
A32: Kakao | B32: =COUNTIFS(거래!$B$4:$B$191,$A32,거래!$M$4:$M$191,"편입 후") | C32: =COUNTIFS(거래!$B$4:$B$191,$A32,거래!$M$4:$M$191,"편입 전") | D32: =COUNTIFS(거래!$B$4:$B$191,$A32,거래!$M$4:$M$191,"지분법 합작 계열") | E32: =SUM(B32:D32)
A33: Naver | B33: =COUNTIFS(거래!$B$4:$B$191,$A33,거래!$M$4:$M$191,"편입 후") | C33: =COUNTIFS(거래!$B$4:$B$191,$A33,거래!$M$4:$M$191,"편입 전") | D33: =COUNTIFS(거래!$B$4:$B$191,$A33,거래!$M$4:$M$191,"지분법 합작 계열") | E33: =SUM(B33:D33)
A34: 합계 | B34: =SUM(B31:B33) | C34: =SUM(C31:C33) | D34: =SUM(D31:D33) | E34: =SUM(E31:E33)
A36: 기업별 금액 대조
A37: 기업 | B37: 일치 | C37: 불일치 | D37: 기타 | E37: 합계
A38: CJ ENM | B38: =COUNTIFS(거래!$B$4:$B$191,$A38,거래!$L$4:$L$191,"일치") | C38: =COUNTIFS(거래!$B$4:$B$191,$A38,거래!$L$4:$L$191,"불일치") | D38: =COUNTIFS(거래!$B$4:$B$191,$A38,거래!$L$4:$L$191,"기타") | E38: =SUM(B38:D38)
A39: Kakao | B39: =COUNTIFS(거래!$B$4:$B$191,$A39,거래!$L$4:$L$191,"일치") | C39: =COUNTIFS(거래!$B$4:$B$191,$A39,거래!$L$4:$L$191,"불일치") | D39: =COUNTIFS(거래!$B$4:$B$191,$A39,거래!$L$4:$L$191,"기타") | E39: =SUM(B39:D39)
A40: Naver | B40: =COUNTIFS(거래!$B$4:$B$191,$A40,거래!$L$4:$L$191,"일치") | C40: =COUNTIFS(거래!$B$4:$B$191,$A40,거래!$L$4:$L$191,"불일치") | D40: =COUNTIFS(거래!$B$4:$B$191,$A40,거래!$L$4:$L$191,"기타") | E40: =SUM(B40:D40)
A41: 합계 | B41: =SUM(B38:B40) | C41: =SUM(C38:C40) | D41: =SUM(D38:D40) | E41: =SUM(E38:E40)
A43: 그룹이 산 거래(확인 분류 MA①②③)의 손상
A44: 기업 | B44: 거래 | C44: 있음 | D44: 없음 (확인) | E44: 식별 불가 | F44: 미확인 | G44: 해당 없음 | H44: 손상 비율 (있음 ÷ (있음+없음))
A45: CJ ENM | B45: =COUNTIFS(거래!$B$4:$B$191,$A45,거래!$I$4:$I$191,"MA①")+COUNTIFS(거래!$B$4:$B$191,$A45,거래!$I$4:$I$191,"MA②")+COUNTIFS(거래!$B$4:$B$191,$A45,거래!$I$4:$I$191,"MA③") | C45: =COUNTIFS(거래!$B$4:$B$191,$A45,거래!$I$4:$I$191,"MA①",거래!$K$4:$K$191,"있음")+COUNTIFS(거래!$B$4:$B$191,$A45,거래!$I$4:$I$191,"MA②",거래!$K$4:$K$191,"있음")+COUNTIFS(거래!$B$4:$B$191,$A45,거래!$I$4:$I$191,"MA③",거래!$K$4:$K$191,"있음") | D45: =COUNTIFS(거래!$B$4:$B$191,$A45,거래!$I$4:$I$191,"MA①",거래!$K$4:$K$191,"없음 (확인)")+COUNTIFS(거래!$B$4:$B$191,$A45,거래!$I$4:$I$191,"MA②",거래!$K$4:$K$191,"없음 (확인)")+COUNTIFS(거래!$B$4:$B$191,$A45,거래!$I$4:$I$191,"MA③",거래!$K$4:$K$191,"없음 (확인)") | E45: =COUNTIFS(거래!$B$4:$B$191,$A45,거래!$I$4:$I$191,"MA①",거래!$K$4:$K$191,"식별 불가")+COUNTIFS(거래!$B$4:$B$191,$A45,거래!$I$4:$I$191,"MA②",거래!$K$4:$K$191,"식별 불가")+COUNTIFS(거래!$B$4:$B$191,$A45,거래!$I$4:$I$191,"MA③",거래!$K$4:$K$191,"식별 불가") | F45: =COUNTIFS(거래!$B$4:$B$191,$A45,거래!$I$4:$I$191,"MA①",거래!$K$4:$K$191,"미확인")+COUNTIFS(거래!$B$4:$B$191,$A45,거래!$I$4:$I$191,"MA②",거래!$K$4:$K$191,"미확인")+COUNTIFS(거래!$B$4:$B$191,$A45,거래!$I$4:$I$191,"MA③",거래!$K$4:$K$191,"미확인") | G45: =COUNTIFS(거래!$B$4:$B$191,$A45,거래!$I$4:$I$191,"MA①",거래!$K$4:$K$191,"해당 없음")+COUNTIFS(거래!$B$4:$B$191,$A45,거래!$I$4:$I$191,"MA②",거래!$K$4:$K$191,"해당 없음")+COUNTIFS(거래!$B$4:$B$191,$A45,거래!$I$4:$I$191,"MA③",거래!$K$4:$K$191,"해당 없음") | H45: =IF(C45+D45=0,0,C45/(C45+D45))
A46: Kakao | B46: =COUNTIFS(거래!$B$4:$B$191,$A46,거래!$I$4:$I$191,"MA①")+COUNTIFS(거래!$B$4:$B$191,$A46,거래!$I$4:$I$191,"MA②")+COUNTIFS(거래!$B$4:$B$191,$A46,거래!$I$4:$I$191,"MA③") | C46: =COUNTIFS(거래!$B$4:$B$191,$A46,거래!$I$4:$I$191,"MA①",거래!$K$4:$K$191,"있음")+COUNTIFS(거래!$B$4:$B$191,$A46,거래!$I$4:$I$191,"MA②",거래!$K$4:$K$191,"있음")+COUNTIFS(거래!$B$4:$B$191,$A46,거래!$I$4:$I$191,"MA③",거래!$K$4:$K$191,"있음") | D46: =COUNTIFS(거래!$B$4:$B$191,$A46,거래!$I$4:$I$191,"MA①",거래!$K$4:$K$191,"없음 (확인)")+COUNTIFS(거래!$B$4:$B$191,$A46,거래!$I$4:$I$191,"MA②",거래!$K$4:$K$191,"없음 (확인)")+COUNTIFS(거래!$B$4:$B$191,$A46,거래!$I$4:$I$191,"MA③",거래!$K$4:$K$191,"없음 (확인)") | E46: =COUNTIFS(거래!$B$4:$B$191,$A46,거래!$I$4:$I$191,"MA①",거래!$K$4:$K$191,"식별 불가")+COUNTIFS(거래!$B$4:$B$191,$A46,거래!$I$4:$I$191,"MA②",거래!$K$4:$K$191,"식별 불가")+COUNTIFS(거래!$B$4:$B$191,$A46,거래!$I$4:$I$191,"MA③",거래!$K$4:$K$191,"식별 불가") | F46: =COUNTIFS(거래!$B$4:$B$191,$A46,거래!$I$4:$I$191,"MA①",거래!$K$4:$K$191,"미확인")+COUNTIFS(거래!$B$4:$B$191,$A46,거래!$I$4:$I$191,"MA②",거래!$K$4:$K$191,"미확인")+COUNTIFS(거래!$B$4:$B$191,$A46,거래!$I$4:$I$191,"MA③",거래!$K$4:$K$191,"미확인") | G46: =COUNTIFS(거래!$B$4:$B$191,$A46,거래!$I$4:$I$191,"MA①",거래!$K$4:$K$191,"해당 없음")+COUNTIFS(거래!$B$4:$B$191,$A46,거래!$I$4:$I$191,"MA②",거래!$K$4:$K$191,"해당 없음")+COUNTIFS(거래!$B$4:$B$191,$A46,거래!$I$4:$I$191,"MA③",거래!$K$4:$K$191,"해당 없음") | H46: =IF(C46+D46=0,0,C46/(C46+D46))
A47: Naver | B47: =COUNTIFS(거래!$B$4:$B$191,$A47,거래!$I$4:$I$191,"MA①")+COUNTIFS(거래!$B$4:$B$191,$A47,거래!$I$4:$I$191,"MA②")+COUNTIFS(거래!$B$4:$B$191,$A47,거래!$I$4:$I$191,"MA③") | C47: =COUNTIFS(거래!$B$4:$B$191,$A47,거래!$I$4:$I$191,"MA①",거래!$K$4:$K$191,"있음")+COUNTIFS(거래!$B$4:$B$191,$A47,거래!$I$4:$I$191,"MA②",거래!$K$4:$K$191,"있음")+COUNTIFS(거래!$B$4:$B$191,$A47,거래!$I$4:$I$191,"MA③",거래!$K$4:$K$191,"있음") | D47: =COUNTIFS(거래!$B$4:$B$191,$A47,거래!$I$4:$I$191,"MA①",거래!$K$4:$K$191,"없음 (확인)")+COUNTIFS(거래!$B$4:$B$191,$A47,거래!$I$4:$I$191,"MA②",거래!$K$4:$K$191,"없음 (확인)")+COUNTIFS(거래!$B$4:$B$191,$A47,거래!$I$4:$I$191,"MA③",거래!$K$4:$K$191,"없음 (확인)") | E47: =COUNTIFS(거래!$B$4:$B$191,$A47,거래!$I$4:$I$191,"MA①",거래!$K$4:$K$191,"식별 불가")+COUNTIFS(거래!$B$4:$B$191,$A47,거래!$I$4:$I$191,"MA②",거래!$K$4:$K$191,"식별 불가")+COUNTIFS(거래!$B$4:$B$191,$A47,거래!$I$4:$I$191,"MA③",거래!$K$4:$K$191,"식별 불가") | F47: =COUNTIFS(거래!$B$4:$B$191,$A47,거래!$I$4:$I$191,"MA①",거래!$K$4:$K$191,"미확인")+COUNTIFS(거래!$B$4:$B$191,$A47,거래!$I$4:$I$191,"MA②",거래!$K$4:$K$191,"미확인")+COUNTIFS(거래!$B$4:$B$191,$A47,거래!$I$4:$I$191,"MA③",거래!$K$4:$K$191,"미확인") | G47: =COUNTIFS(거래!$B$4:$B$191,$A47,거래!$I$4:$I$191,"MA①",거래!$K$4:$K$191,"해당 없음")+COUNTIFS(거래!$B$4:$B$191,$A47,거래!$I$4:$I$191,"MA②",거래!$K$4:$K$191,"해당 없음")+COUNTIFS(거래!$B$4:$B$191,$A47,거래!$I$4:$I$191,"MA③",거래!$K$4:$K$191,"해당 없음") | H47: =IF(C47+D47=0,0,C47/(C47+D47))
A48: 합계 | B48: =SUM(B45:B47) | C48: =SUM(C45:C47) | D48: =SUM(D45:D47) | E48: =SUM(E45:E47) | F48: =SUM(F45:F47) | G48: =SUM(G45:G47) | H48: =IF(C48+D48=0,0,C48/(C48+D48))
A49: 손상 구분은 data/ma188_impairment_class.csv(nbs/ma188_impairment_class.py)의 판정이다. 손상 비율은 판정할 수 있는 거래(있음·없음) 안에서 계산했다.

Sheet 거래
A1: 식별 | H1: 분류 요약 | N1: 원자료 (Capital IQ) | S1: v4 분야 (수집에서 확인 안 함) | U1: 10-19 설명란 판정 | Z1: 공시 확인 | AH1: 인수 목적·핵심 | AM1: 규모 | AS1: 주가 이벤트 | AV1: 전후 이벤트 | AZ1: 성과 | BF1: 수집
A2: 거래 | B2: 기업 | C2: 날짜 | D2: 대상회사 | E2: 금액 순위 | F2: 상위 50 | G2: 사건 묶음 | H2: 거래 형태 (설명란 판정) | I2: 거래 형태 (공시 확인) | J2: 형태 변경 | K2: 손상 구분 | L2: 금액 대조 | M2: 편입 시점 | N2: 상태 | O2: 금액 $M | P2: 매수자 | Q2: 매도자 | R2: 설명란 | S2: 분야 | T2: 세부 분야 | U2: 그룹 역할 (설명란 판정) | V2: 지분 규모 (설명란 판정) | W2: 거래 형태 (설명란 판정) | X2: 편입 전 표시 (배경지식) | Y2: 금액 의심 (설명란 대조) | Z2: 거래 형태 (공시 확인) | AA2: 편입 시점 (공시 확인) | AB2: 상태 (공시 확인) | AC2: 금액 확인 (현지 통화) | AD2: 금액 확인 ($M) | AE2: 발표일 | AF2: 확인 메모 | AG2: 특이사항 | AH2: 인수 주체 | AI2: 발표 당시 목적 | AJ2: 인수 주체 주력 사업 | AK2: 핵심 여부 | AL2: 핵심 판정 근거 | AM2: 인수 주체 총자산 | AN2: 그룹 정점 총자산 | AO2: 총자산 대비 | AP2: 자기자본 대비 | AQ2: 시가총액 | AR2: 규모 기준 | AS2: 종목 | AT2: 종목 근거 | AU2: 처음 알려진 날 | AV2: 인수 전 사건 | AW2: 인수 후 사건 | AX2: 손상 | AY2: 손상 구분 근거 | AZ2: 매출 (인수 전) | BA2: 매출 (인수 후) | BB2: 영업이익 (인수 전) | BC2: 영업이익 (인수 후) | BD2: 실적 기준 | BE2: 어닝콜·IR 언급 | BF2: 수집 상태 | BG2: 수집 일시
A3: deal_id | B3: firm | C3: date | D3: target | E3: value_rank | F3: top50 | G3: event_group | H3: (파생) | I3: (파생) | J3: (파생) | K3: impairment_class | L3: (파생) | M3: (파생) | N3: status | O3: value | P3: buyers | Q3: sellers | R3: comment | S3: cat | T3: subcat | U3: role | V3: stake | W3: subtype | X3: pre_incorp | Y3: value_flag | Z3: subtype_chk | AA3: pre_incorp_chk | AB3: status_chk | AC3: value_chk_local | AD3: value_chk_usdmm | AE3: announce_date_chk | AF3: chk_note | AG3: notes | AH3: acquirer_entity | AI3: purpose_quote | AJ3: acquirer_core | AK3: is_core | AL3: core_basis | AM3: acq_total_assets | AN3: apex_total_assets | AO3: deal_to_assets_pct | AP3: deal_to_equity_pct | AQ3: acq_mktcap | AR3: size_basis | AS3: event_ticker | AT3: event_ticker_basis | AU3: first_filing_date | AV3: pre_events_summary | AW3: post_events_summary | AX3: impairment | AY3: impairment_class_basis | AZ3: target_rev_pre | BA3: target_rev_post | BB3: target_op_pre | BC3: target_op_post | BD3: perf_basis | BE3: earnings_call_note | BF3: collect_status | BG3: collected_on
A4: C001 | B4: CJ ENM | C4: 2006-01-09 | D4: CJ Entertainment Inc. | E4: 10 | F4: True | H4: MA② | I4: MA② | J4: 같음 | K4: 해당 없음 | L4: 불일치 | M4: 편입 전 | N4: Closed | O4: 549.08 | P4: CJ Corporation (KOSE:A001040) | Q4: - | R4: CJ Corp. (KOSE: A001040) agreed to acquire the remaining stake in CJ Entertainment Inc. for KRW 264 billion in stocks on January 9, 2006. As per the terms of the agreement, CJ Corp. will pay 17.8 shares of its common stock to every 100 shares of CJ Entertainment. The Board of CJ Corp approved the transaction. The acquisition is subject top approval of shareholders of CJ Corp. A shareholder meeting is scheduled on March 7, 2006 and the transaction is expected to complete on April 10, 2006. | S4: Content Production & Investment | T4: Content Investment / Distribution | U4: MA-1 그룹이 매수자 | V4: 기존 자회사 잔여지분 | W4: MA② 기존 지분 확대 | Y4: False | Z4: MA② 기존 지분 확대 | AA4: 편입 전 (매수자는 CJ ENM 계보 밖: CJ㈜(CJ그룹 지배회사, 당시 식품·제약 사업지주, 2007-11 순수지주회사 전환)). 참고: 대상 구 CJ엔터테인먼트는 이 거래에서 영화사업을 물적분할(신설 씨제이엔터테인먼트㈜, CJ㈜ 100%)한 뒤 존속 투자법인 CJ EH㈜가 CJ㈜에 흡수돼 소멸했고, 영화사업 법인은 2011-03-01 오미디어홀딩스(CJ E&M)에 합병(C005)된 뒤 2018-07-01 CJ오쇼핑의 CJ E&M 흡수합병으로 현 CJ ENM 법인에 들어옴 | AB4: 완료 (2006-04-10 합병기일·분할기일; 2006-04-17 해산등기, 2006-04-20 구 CJ엔터테인먼트 코스닥 상장폐지, 2006-04-25 CJ㈜ 합병신주 상장 예정) | AC4: 397,237,024,295원 (합병신주 3,176,905주 × CJ㈜ 합병가액 125,039원; 피합병 CJ EH(구 CJ엔터테인먼트) 발행주식 17,827,713주 × 0.1782004). 이 중 CJ㈜ 보유 6,556,101주(36.77%)에 배정된 약 1,168,300주는 CJ㈜ 자기주식이 됨(합병신고서). 나머지 지분 중 14.85%(2,647,042주)는 CJ그룹 회장 이재현, 0.13%(23,040주)는 대표이사 박동호 몫이라 CJ㈜·특수관계인 합계 9,226,183주(51.76%). 특수관계인 밖 외부주주(8,601,530주, 48.24%)의 실질 대가 = 주식매수청구 현금 67,416,510,174원(3,123,159주 × 21,586원) + 잔여 외부주주 5,478,371주에 교부된 신주 976,247주(합병가액 기준 122,068,948,633원) = 189,485,458,807원(계산). 참고: 이재현 몫 신주 471,703주(58,981,271,417원) | AD4: 원자료와 불일치: 합병신주 전체 397,237백만원 = 409.2백만 달러, 특수관계인 밖 외부주주 실질 대가 189,485백만원 = 195.2백만 달러 (Yahoo Finance KRW=X 2006-01-09 종가 970.72원/달러 적용, 계산). 원자료 549.08은 같은 환율로 약 5,330억원으로, 합병신주 가치·발표 직전 CJ㈜ 종가(136,000원) 기준 신주 가치 4,321억원·여기에 CJ엔터 부채(2005-09-30 841억원 또는 2005-12-31 1,523억원)를 더한 값·CJ엔터 100% 시가 4,154억원 중 어느 것으로도 재현되지 않음 | AE4: 2006-01-09 | AF4: 기준 분류 유지(MA②): CJ㈜는 거래 전 CJ엔터테인먼트 지분 36.77%를 가진 지배회사(합병결정 공시 '회사와의 관계: 지배회사', CJ㈜ 2006 감사보고서 '자회사')였고 특수관계인(이재현 14.85%, 박동호 0.13%) 포함 51.76%를 지배했으며, 이 거래로 영화사업 법인(신설 CJ엔터테인먼트)을 100% 자회사로 만들고 나머지 소수주주를 흡수함. 원자료 설명란 정정: (1) 거래 형식은 '주식교환'이 아니라 CJ엔터테인먼트를 물적분할(영화사업→신설 씨제이엔터테인먼트㈜)한 뒤 존속 투자사업법인 CJ EH㈜를 CJ㈜가 흡수합병한 구조(회사분할결정·회사합병결정). (2) 'KRW 264 billion'은 합병결정 공시에 적힌 CJ엔터테인먼트의 2005년 3분기 자산총계 264,025백만원과 같은 숫자로 거래대금이 아님(외부 지분을 발표 직전 종가 23,300원으로 평가한 2,626억원과도 비슷하나 공시된 대가는 아님). 공시 기준 대가는 합병신주 전체 3,972억원, 특수관계인 밖 외부주주 실질 대가 1,895억원. (3) '17.8 shares per 100 shares'(0.1782004), 주총 2006-03-07, 완료 2006-04-10은 공시와 일치. 원자료 sellers '-'는 CJ엔터테인먼트 소수주주(이재현 등 특수관계인 14.98%와 외부주주 48.24%, 주식매수청구 3,123,159주 포함). 분류 해석 주의: 매수자 CJ㈜를 '그룹'으로 본 원자료 기준을 따름 — 최신 CJ 계보 규칙처럼 그룹을 CJ ENM 계보로 좁히면 CJ㈜는 계보 밖이라 구조상 MA⑥으로도 볼 수 있음(사용자 확인 필요) | AG4: C005의 선행 거래: 이 합병으로 신설된 씨제이엔터테인먼트㈜(DART 00576309, 2006-04-10 설립, CJ㈜ 100%)가 2010-11-16 결정된 6사 합병(C005)에서 CJ E&M에 흡수됨. 구 CJ엔터테인먼트(DART 00330406, 코스닥 A049370)는 1997-07-28 설립 투자자문회사로 2000-04-18 CJ㈜ 엔터테인먼트 사업부를 현물출자받아 영화사업을 시작했고 2002-02-05 코스닥에 등록됨(CJ㈜ 2006 감사보고서 주석 22). 합병 전 구 CJ엔터테인먼트는 CJ CGV 36.73%, CJ미디어 31.16%, CJ인터넷 9.53%, 시네마서비스 40.00%, 아트서비스 59.72%, CJ엔키노 86.13% 등을 가진 미디어 중간지주였고(합병신고서 출자내역, 2005-09-30), 이 거래로 CJ㈜가 이 지분을 직접 보유하게 됨 — 공시된 합병목적 자체가 'CJ미디어·CJ CGV·CJ인터넷의 직접 지배'임. 주주 구성(2006-01-06): CJ㈜ 36.78%, 이재현 14.85%, 박동호 0.13%(특수관계 계 51.76%), 랜드마크자산운용 5.00%; 이재현은 합병으로 CJ㈜ 신주 471,703주를 받음(합병종료보고서 지분변동표). CJ㈜도 반대주주 주식매수청구 732,736주(보통주 청구가 114,298원)를 받음. 회계처리: 지배·종속회사 간 합병이라 CJ EH의 자산·부채를 연결재무제표상 장부가액으로 승계하고 차액은 자본잉여금 처리(CJ㈜ 2006 감사보고서 주석 22) → 이 거래로 새 영업권은 생기지 않음. 같은 날(2006-01-09) CJ㈜는 CJ모닝웰 소규모합병도 결정함(별개 거래, 신주 683,299주). 공시 시점: CJ엔터 매매거래정지가 2006-01-09 17:11:07에 시작돼(정규장 마감 후) 2006-01-10까지 연장됨(20060109900089). 조사 한계: 2006년 DART 문서 일부(구 CJ엔터 사업보고서 연혁·타법인출자 절)는 서버가 깨진 글자로 돌려줘 읽지 못함. 2006년 당시 언론 보도·IR 자료는 찾지 못함(수집 2회·검토 3회 웹 검색). 영화사업 법인이 2006-04 신설돼 2006년 실적은 9개월치이고, 구 CJ엔터 실적에는 지분법손익 등 투자사업이 섞여 있어 전후 비교에 주의. collect_status 부분: earnings_call_note 미확인 | AH4: CJ㈜ (CJ주식회사, 당시 식품·사료·제약을 직접 영위하던 CJ그룹 지배회사, 유가증권시장 001040; 2007-09 CJ제일제당 인적분할로 순수지주회사 전환) | AI4: "CJ엔터테인먼트㈜가 지배하고 있는 CJ 미디어, CJ CGV, CJ 인터넷은 신성장사업으로 지속적 투자가 요구되는 바, CJ㈜가 직접 지배함으로써 지속 성장시키기 위함" (회사합병결정 공시 합병목적) / "경영 효율성 향상 및 기업 가치 극대화" (합병신고서 합병의 목적) / "투자사업부문과 영화사업부문으로 분리하여 업종 전문화를 통해 ... 전문화된 사업영역에 기업의 역량을 집중" (CJ엔터테인먼트 회사분할결정 분할목적) | AJ4: 식품·사료·제약 제조업(합병결정 공시상 주요사업 '당분유제조'); 2005년 별도 매출 2,459,901백만원·영업이익 192,480백만원(CJ㈜ 2005 사업보고서). 미디어·엔터 사업은 직접 영위하지 않고 지분법 자회사로 보유(2005-09-30 CJ엔터테인먼트 36.78%, CJ미디어 58.06%, CJ인터넷 16.23%, CJ뮤직 95.51%, CJ홈쇼핑 29.99%; 합병신고서 출자내역) | AK4: 비핵심 | AL4: 인수 주체 CJ㈜의 직접 사업은 식품·제약이고 영화·미디어는 자회사로만 보유했으므로 CJ㈜ 기준으로는 비핵심 영역의 자회사 지분 확대. 다만 CJ그룹은 2000년부터 CJ엔터테인먼트를 통해 영화사업을 해 왔고, 그룹 정점 CJ ENM 기준으로 보면 영화사업은 현 CJ ENM 영화드라마 부문의 전신이라 핵심 영역 | AM4: 2,790,157백만원 (CJ㈜ 별도, 2005-12-31; CJ㈜ 2005 사업보고서 요약재무정보, CJ㈜ 2006 감사보고서 주석 22의 2005-12-31 요약대차대조표도 같은 값). 참고: CJ엔터테인먼트가 낸 합병결정 공시의 CJ㈜ 2005-09-30 자산총계 2,759,575백만원, 합병종료보고서 '합병전'(CJ모닝웰 합병 반영 후) 2,820,644,848천원 | AN4: acq_total_assets와 같음 (인수 주체 CJ㈜가 상장 지배회사 자신). 연결 기준 CJ㈜ 및 종속회사 총자산 5,990,100,383천원 (2005-12-31, CJ㈜ 연결감사보고서; 2006년 연결감사보고서의 비교표시는 5,997,710,235천원). 참고: 2004-12-31 연결 5,197,979,683천원 | AO4: 계산: 14.24 (합병신주 전체 397,237백만원 ÷ CJ㈜ 별도 총자산 2,790,157백만원, 2005-12-31). 특수관계인 밖 외부주주 실질 대가 기준 6.79 (189,485백만원 ÷ 같은 분모). 연결 총자산(5,990,100백만원) 대비 6.63. 합병 공시에 총자산대비 항목 없음 | AP4: 계산: 26.91 (397,237백만원 ÷ CJ㈜ 별도 자본총계 1,476,097백만원, 2005-12-31). 특수관계인 밖 외부주주 실질 대가 기준 12.84 | AQ4: 계산: 3,271,374,872,000원 (보통주만: 2006-01-06 종가 136,000원 × 보통주 24,054,227주; 종가는 합병신고서 합병가액 표, 주식수는 같은 신고서의 2006-01-06 기준 발행주식수). 우선주 6,051,488주(1우 3,587,656·2우 1,617,526·3우 846,306주)는 당시 종가를 확인하지 못해 제외. 참고: 공시가 2006-01-09 정규장 마감 후라 발표 직전 거래일을 2006-01-09로 보면 추정: 종가 약 133,500원(Yahoo Finance 001040.KS 수정종가 21,192.42 × 136,000/21,586.34) × 24,054,227주 ≈ 3,211,239,304,500원 | AR4: 총자산·자본은 CJ㈜ 2005-12-31 별도 값(2005 사업보고서 20060331000758 요약재무, 2006 감사보고서 20070309000171 주석 22), 연결 총자산은 2005 연결감사보고서(20060501000035). 거래금액은 합병신고서(20060109000341)의 합병가액 125,039원·22,282원과 합병종료보고서(20060419000229)의 신주 3,176,905주, 주식매수청구 3,123,159주×21,586원, 합병신고서 주식분포(특수관계인 9,226,183주)로 계산. 시가총액은 2006-01-06 종가 기준(2006-01-09 종가 추정치 병기). Yahoo Finance 001040.KS 종가는 이후 분할 등을 반영한 수정값(2006-01-06 21,586원)이라 직접 쓰지 않고 비율로만 씀 | AS4: KRX:001040 | AT4: 인수 주체 CJ㈜(유가증권시장). 공시는 2006-01-09 정규장 마감 후(CJ엔터 매매정지 17:11:07)라 CJ㈜의 첫 반응일은 2006-01-10. 대상 구 CJ엔터테인먼트도 코스닥 상장사(KRX:049370, 2002-02-05 상장, 2006-04-20 피흡수합병으로 상장폐지): 발표 직전 2006-01-06 종가 23,300원, 시가총액 계산 415,385,712,900원(17,827,713주 기준); 주권 매매거래정지 2006-01-09 17:11:07~2006-01-10(20060109900082, 정지기간변경 20060109900089)이라 대상 주식의 첫 반응일은 2006-01-11. 049370은 상장폐지 종목이라 Yahoo Finance에 시세 없음 | AU4: 2006-01-09 정규장 마감 후: DART에 CJ㈜ 회사합병결정(20060109000243)·합병신고서, CJ엔터테인먼트 회사분할결정(20060109000249)·회사합병결정이 같은 날 공시되고 CJ엔터테인먼트 주권 매매거래정지(17:11:07부터, 2006-01-10까지 연장). 2005-09~2006-01 CJ엔터 공시 목록에 관련 조회공시 없음, 사전 보도는 찾지 못함 | AV4: 1997-07: 법인 설립(투자자문·경영자문업); 2000-04: CJ㈜ 엔터테인먼트 사업부 현물출자로 영화사업 개시; 2002-02: 코스닥 등록; 2005-09: CJ㈜가 36.78% 보유, CJ엔터는 CJ CGV 36.73%·CJ미디어 31.16%·CJ인터넷 9.53% 등 보유한 미디어 중간지주; 2004→2005: 별도 매출 118,986→124,364백만원, 영업손실 2,576→3,942백만원(일부 투자작품 손실·인건비 증가; 2004년 경상이익 26,058백만원은 지분법주식 처분이익 영향) | AW4: 2006-03-07: 양사 임시주총 분할·합병 승인, CJ엔터테인먼트는 CJ EH㈜로 상호 변경; 2006-04-10: 영화사업 물적분할(신설 씨제이엔터테인먼트㈜, CJ㈜ 100%)과 CJ EH㈜ 흡수합병 동시 완료, 주식매수청구 3,123,159주(21,586원); 2006-04-20: 구 CJ엔터 상장폐지; 2006-12: <타짜> 685만 관객; 2007-09: CJ㈜ 인적분할(CJ제일제당 신설)로 지주회사 전환; 2009-08: <해운대> 1,152만 관객; 2010-11-16: 신설 CJ엔터테인먼트 등 5사를 오미디어홀딩스가 흡수합병 결정(C005); 2011-03-01: CJ E&M 영화사업부문으로 편입; 2016·2017: CJ E&M 영화부문 영업손실(-23,874·-9,044백만원); 2018-07-01: CJ오쇼핑이 CJ E&M 흡수합병, CJ ENM 출범; 2024: CJ ENM 영화드라마사업부문 매출 1,704,683백만원·영업손실 26,925백만원(스튜디오드래곤·Fifth Season 포함) | AX4: 해당 없음 (이 합병으로 영업권이 생기지 않음: CJ㈜ 2006 감사보고서 주석 22에 지배·종속회사 간 합병으로 연결재무제표상 장부가액 승계, 차액은 자본잉여금 처리라고 기재. CJ㈜ 2006 무형자산 주석의 '합병으로 인한 증가' 영업권 13,826백만원은 같은 해 4개사 합병 합계로 CJ EH 몫은 구분 공시되지 않음). 후속 사업 수준 참고: CJ E&M 2015년 판권 손상차손 95,154백만원(방송·영화 판권 전체, CJ E&M 2015 사업보고서 주석 15) | AY4: 지배·종속회사 간 합병으로 영업권이 생기지 않음(CJ㈜ 2006 감사보고서) | AZ4: 2004: 118,986백만원; 2005: 124,364백만원 (구 CJ엔터테인먼트 별도) | BA4: 2006(2006-04-10~12-31, 신설 CJ엔터테인먼트 제1기): 118,381백만원; 2007: 129,857백만원; 최근(독립 법인 마지막 연도) 2010: 163,080,002,913원. 후속 사업 대리지표 — CJ E&M 영화부문(연결): 2011 166,784백만원(합병 후 3~12월), 2012 218,960백만원, 2017 198,667백만원; CJ ENM 영화드라마사업부문 2024 1,704,683백만원(드라마 제작사 포함으로 비교 불가) | BB4: 2004: -2,576백만원; 2005: -3,942백만원 (구 CJ엔터테인먼트 별도; 감사 완료 정정공시 2006-03-09 기준 2004 -2,576,063,521원·2005 -3,942,273,146원. 2006-01-26 최초 잠정공시는 감사 전 수치로 2004 1,045,124,599원·2005 -4,180,994,921원이었음) | BC4: 2006(9개월): -14,148백만원; 2007: -17,149백만원; 최근(독립 법인 마지막 연도) 2010: 8,329,368,008원. CJ E&M 영화부문: 2011 5,834백만원, 2012 9,220백만원, 2017 -9,044백만원; CJ ENM 영화드라마 2024 -26,924,539천원 | BD4: 인수 전: 구 CJ엔터테인먼트(CJ EH) 별도·K-GAAP·12월 결산, 2005 사업보고서(20060331002319) 요약재무정보와 감사 완료 정정공시(20060309001167; 2005 매출 124,363,747,563원·영업손실 3,942,273,146원, 2004 매출 118,985,835,542원·영업손실 2,576,063,521원), CJ㈜ 2006 감사보고서 주석 22(2005년 매출 124,364·영업손실 3,942백만원 일치). 구 법인 실적에는 영화사업 외에 지분법 등 투자사업 손익이 섞임. 인수 후: 2006-04-10 물적분할로 신설된 씨제이엔터테인먼트㈜(영화사업 법인) 별도·K-GAAP — 2006~2009는 2010 증권신고서(합병, 20101202000223) 요약재무, 2010은 감사보고서(20110331003203). 2011-03 이후는 CJ E&M 연결 영화부문(K-IFRS, 사업보고서 '사업부문별 요약 연결재무현황')과 CJ ENM 영화드라마사업부문(2024 사업보고서 영업부문 주석)으로 대신함 — 범위가 계속 바뀌어 시계열 비교에 주의 | BE4: 미확인 — 2006년 CJ㈜ IR 자료·실적발표와 어닝콜 기록을 찾지 못함(DART에는 IR 자료 없음; 수집 2회·검토 3회(한국어 2·영어 1) 웹 검색). 참고: 2010-11-16 CJ그룹 발표(이투데이 보도)는 신설 CJ엔터테인먼트를 포함한 6사 통합 목적을 '콘텐츠 사업의 글로벌화와 계열사간 시너지 극대화'로 밝힘(C005 참조) | BF4: 부분 | BG4: 2026-10-26
A5: C002 | B5: CJ ENM | C5: 2006-10-12 | D5: Orion Cinema Network Co., Ltd. | E5: 70 | F5: False | H5: MA② | I5: MA② | J5: 같음 | K5: 식별 불가 | L5: 불일치 | M5: 편입 후 | N5: Closed | O5: 20.89 | P5: On Media Corp. | Q5: - | R5: On Media Corp. (KOSE:A045710) acquired an additional stake in Orion Cinema Network Co., Ltd. for KRW 20 billion in cash on October 12, 2006. | S5: Media Platforms | T5: Broadcasting Channel | U5: MA-1 그룹이 매수자 | V5: 추가지분 | W5: MA② 기존 지분 확대 | Y5: False | Z5: MA② 기존 지분 확대 | AA5: 편입 후 (CJ ENM 전신 계보: 온미디어, 2011 CJ ENM 계보로 합병 — 2011-03-01 CJ E&M(옛 오미디어홀딩스)에 흡수합병, CJ E&M은 2018-07-01 CJ오쇼핑(현 CJ ENM 법인)에 흡수합병). 참고(시점 사실): 거래 당시(2006-10) 온미디어는 ㈜오리온이 최대주주인 오리온그룹 계열 상장사로 CJ와 자본관계가 없었고, CJ오쇼핑의 온미디어 경영권 취득은 2010-06-08(오리온 측 40.18% 대금지급, C004)임 | AB5: 완료 (2006-11-14 주금 납입; 이사회 결의 2006-10-12, 실권주 인수로 취득 규모 확대 정정 2006-11-14) | AC5: 23,957,220,000원 (오리온시네마네트워크 주주배정 유상증자 신주 4,791,444주 × 발행가 5,000원(액면가) 전량 인수; 최초 공시는 배정분 4,000,000주·20,000,000,000원이었으나 2대주주 ㈜중앙일보사 배정분 791,444주가 실권돼 온미디어가 인수 — 2006-11-14 정정공시) | AD5: 원자료와 불일치(최종 금액 기준): 23,957백만원 = 25.58백만 달러 (계산: Fed H.10 2006-11-14 936.70원/달러; 2006-10-12 957.60원 적용 시 25.02). 원자료 20.89는 최초 공시액 200억원 ÷ 957.60원(2006-10-12) = 20.89로 재현됨 — 실권주 인수분이 빠진 값 | AE5: 2006-10-12 | AF5: 기준 분류 유지(MA② 기존 지분 확대): 온미디어는 거래 전 OCN 5,740,000주(83.48%)를 가진 지배주주였고 이 거래로 90.27%(10,531,444주/11,667,165주)가 됨. 다만 매도자에게서 산 거래가 아니라 자회사 주주배정 유상증자 참여(신주 인수)이며 대가는 OCN으로 들어가 단기차입금 상환에 쓰임(OCN 2006 감사보고서). 금액 정정: 원자료 'KRW 20 billion'은 최초 결의액이고 확정 취득액은 23,957,220,000원(4,791,444주). 원자료 sellers '-'는 구조상 맞음(신주 발행). 분류·상태는 원자료와 일치 | AG5: 온미디어 계보 묶음(CJ-B)의 첫 거래로 CJ 편입 4년 전 오리온그룹 시절 거래. 대상 OCN(㈜오리온시네마네트워크)은 2013-12-01 CJ E&M에 흡수합병(C012 — 잔여 9.73%를 가진 ㈜중앙일보사 몫을 합병신주로 정리)되므로 C002→C012가 OCN 지분 100% 정리의 앞뒤 단계. 9.73%는 바로 이 증자에서 중앙일보가 실권해 16.52%→9.73%로 낮아진 지분임. 공시상 '발행회사의 요약 재무상황'(자산 298,356·매출 59,801백만원 등)은 OCN이 아니라 온미디어 자신의 2005 재무로 보임(OCN 2005 자산총계는 99,306,934,951원) — 공시 표 오기 가능성. 증자 목적은 공시상 '운영자금'이며 OCN은 증자 대금으로 단기차입금(2005말 11,515,684천원)을 전액 상환함. 같은 달(2006-10-27) 온미디어는 온라인게임사 이플레이온을 200억원에 100% 출자 설립(별건, 2010-10 청산 결정). 시가총액은 발표 직전 거래일 종가를 찾지 못해 월간 범위로 추정함(KRX 일별 시세 접근 불가, Yahoo Finance에 상장폐지 종목 045710 시세 없음). 이후 실적은 2013-12 합병 전까지 OCN 별도 감사보고서로, 합병 뒤에는 개별 실적이 공시되지 않아 CJ E&M 방송부문·CJ ENM 미디어플랫폼 부문으로만 대리 추적 가능 | AH5: ㈜온미디어 (ON*Media Corp., 유가증권시장 045710 — 2006-07-03 상장; 당시 ㈜오리온이 최대주주(44,152,210주, 발행주식 115,797,990주 대비 38.13% 계산)인 오리온그룹 계열 방송채널사용사업 겸 사업지주회사. 2010-06 CJ오쇼핑에 인수, 2011-03-01 CJ E&M에 흡수합병돼 소멸) | AI5: "자회사의 운영자금 조달을 위한 유상증자참여" (타법인주식및출자증권취득결정 취득목적) / 자금조달의 목적: 운영자금 23,957,220,000원 (자회사 OCN 유상증자결정, 자회사의 주요경영사항) | AJ5: 방송채널사용사업(MPP)을 영위하는 사업지주회사. 2005 별도 영업수익 59,776백만원 = 지분법평가이익 19,940 + 자회사 수수료수익 14,433 + 직영 채널(투니버스) 광고 16,304·시청료 5,287·사업수익 3,812(2006 사업보고서 매출실적, 백만원). 자회사 OCN·바둑TV·온게임넷(PP), 4개 SO, 디지틀온미디어 보유. 2005 MPP 매출 점유율 12.2%(16개 채널, 방송위원회 자료 인용) | AK5: 핵심 | AL5: OCN은 영화채널 OCN·Super Action·Catch On·On Style 등 6개 채널을 운영하는 온미디어의 최대 자회사(2005 매출 100,340백만원)로 인수 주체의 주력인 케이블 PP 사업 그 자체. 그룹 정점(현 CJ ENM, 미디어플랫폼 부문의 TV채널 사업) 기준으로도 OCN은 지금도 운영 중인 핵심 채널이라 '핵심' | AM5: 298,355,727,088원 (온미디어 별도, 2005-12-31; 타법인주식취득결정 '최근 사업연도말 자산총액') | AN5: acq_total_assets와 같음 (인수 주체 온미디어가 상장사 자신; 당시 상위 상장 지배회사 ㈜오리온은 CJ ENM 계보 밖). 참고: 온미디어 연결 총자산 379,287백만원(2005-12-31, 2009 사업보고서 요약연결재무정보 제6기) | AO5: 8.03 | AP5: 8.36 | AQ5: 추정: 약 7,295억~9,785억원 (발표 직전 거래일 2006-10-11 종가 미확인. 2006년 10월 월중 최저 6,300원·최고 8,450원(2006 사업보고서 '최근 6개월 간의 주가') × 발행주식 115,797,990주(2006-11-10 신주인수권 행사 350,000주 전; 2006말 116,147,990주 = 자본금 58,074백만원/액면 500원에서 역산). 참고: 2006-09-27 장중 7,310원(이투데이) 기준 8,465억원) | AR5: 총자산·자기자본(286,535,479,074원)·비율은 2006-11-14 정정 타법인주식취득결정(20061114001237) 값(분모 2005-12-31 별도). 최초 공시(20061012000143)는 200억원 기준 총자산대비 6.70%·자기자본대비 6.98%. 시가총액은 일별 종가가 없어 월간 범위로 추정 | AS5: KRX:045710 | AT5: 인수 주체 온미디어(유가증권시장 045710, 2011-03 합병으로 상장폐지 — Yahoo Finance 시세 없음). 대상 OCN은 비상장. 당시 최대주주 ㈜오리온(KRX:001800, 현 오리온홀딩스)도 참고 가능. 공시는 2006-10-12 장중/장후 여부 미확인 | AU5: 2006-10-12: DART 온미디어 '유상증자결정(자회사의 주요경영사항)'·'타법인주식및출자증권취득결정' 동시 공시. 사전 보도나 조회공시는 찾지 못함(온미디어 2006-07~10 공시 목록 확인) | AV5: 1999-05-18: OCN 설립(오리온그룹), 1999년 중 ㈜대우 DCN 채널(매수가 150억원)과 ㈜중앙일보 Catch One 채널(74억원) 사업권 양수(OCN 감사보고서 영업권 주석: 자산·부채 양수, 매수가 DCN 15,000,000천원·Catch One 7,400,000천원). 추정: 중앙일보사가 OCN 지분 16.52%(1,135,721주)를 갖게 된 경위와 관련 있을 수 있으나 주식 취득 경위는 감사보고서에 기재되지 않음; 2000-06-15: 온미디어 설립 시 OCN 지분 50.48% 현물출자로 취득(지주회사); 2004: OCN 매출 75,043백만원·영업이익 12,471백만원; 2005: 매출 100,341백만원·영업이익 24,452백만원, 단기차입금 11,516백만원; 2006-07-03: 온미디어 유가증권시장 상장(공모가 5,200원); 2006-10 초: 외국계 주주(Capital International·Tabimax·New Asia East) 32.69% 보호예수 해제 | AW5: 2006-11-14: 증자 납입, 온미디어 지분 90.27%·중앙일보 9.73%; OCN이 증자 대금으로 단기차입금 전액 상환; 2006: OCN 매출 140,322백만원(+39.8%, '광고시장 성장에 따른 매출액 증가')·영업이익 38,781백만원; 2007~2009: 매출 180,395→170,529→161,261백만원, 영업이익 39,291→21,213→10,005백만원으로 둔화; 2010-06: CJ오쇼핑이 온미디어 55.17% 취득(C004)으로 OCN이 CJ 계열 편입; 2010-09-15: 온미디어 지분이 CJ오쇼핑 인적분할 신설 오미디어홀딩스로 이전; 2011-03-01: 온미디어가 CJ E&M에 흡수합병돼 OCN 지분 90.27%를 CJ E&M이 승계(C009); 2011~2012: OCN 매출 222,297→242,856백만원·영업이익 30,929→33,657백만원; 2013-12-01: CJ E&M이 OCN을 흡수합병(합병비율 1:0.6485944, 중앙일보 9.73%에 CJ E&M 주식 교부, C012) — 법인 소멸, 채널 OCN은 CJ E&M 방송부문으로; 2018-07-01: CJ오쇼핑이 CJ E&M을 흡수합병해 CJ ENM 출범, OCN 채널은 CJ ENM 미디어플랫폼 부문이 운영 | AX5: 확인 안 됨 (온미디어 2009 사업보고서 타법인출자 현황에서 OCN 주식 장부가 162,410→167,120백만원으로 지분법이익만 반영·손상 기재 없음; CJ E&M(오미디어홀딩스) 2010 연결감사보고서 무형자산 변동표 영업권 손상 없음; CJ E&M 2013·2017 연결 무형자산 변동표의 영업권 손상 957백만원·854백만원은 현금창출단위·대상이 특정되지 않음; 2013-12 OCN 합병은 동일지배 합병으로 장부가 승계라 새 영업권 없음. OCN 관련 손상 기재를 찾지 못함) | AY5: 2009~2010 손상 기재 없음, 이후 OCN 관련 영업권이 방송사업부문 현금창출단위에 묶여 개별 손상을 알 수 없음 | AZ5: 2004: 75,042,524,947원; 2005: 100,340,749,421원 | BA5: 2006: 140,321,911,950원; 2007: 180,395,349,700원; 최근 확인 가능 연도 2014: 224,274백만원(CJ E&M 사업보고서 '합병등 전후의 재무사항 비교표' 실적; 2013 242,595백만원, 독립 법인 마지막 감사 연도 2012 242,856,440,260원). 합병 후 대리지표(OCN 외 채널 포함): CJ E&M 방송부문 2014 825,918백만원·2017 1,294,153백만원, CJ ENM 미디어플랫폼 2025 1,341,617백만원(외부매출) | BB5: 2004: 12,471,195,779원; 2005: 24,451,561,884원 | BC5: 2006: 38,780,607,442원; 2007: 39,290,729,401원; 최근 확인 가능 연도 2014: 34,944백만원(비교표 실적, 합병 전 예측 58,767백만원 대비 41% 미달; 2013 23,250백만원·예측 45,918백만원; 2012 감사보고서 33,656,826,184원). 합병 후 대리지표: CJ E&M 방송부문 영업이익 2014 2,150백만원·2017 61,822백만원, CJ ENM 미디어플랫폼 부문 영업이익 2025 1,332,256천원 | BD5: OCN 별도 재무제표, 12월 결산. 2004~2009는 K-GAAP 감사보고서(2005 감사보고서 20060320000290: 2004·2005; 2007 감사보고서 20080408001290: 2006·2007; 2009 감사보고서 20100326000591: 2008·2009 — 2006 이후 손익계산서는 '영업수익·영업비용' 표시), 2010~2012는 K-IFRS 감사보고서(2011 감사보고서 20120328000227, 2012 감사보고서 20130326000223; 2011 영업이익은 2011 감사보고서 30,929백만원, 2012 감사보고서 비교표시 32,032백만원으로 기타영업손익 분류 차이). 2013·2014는 CJ E&M 2014 사업보고서(20150331004213) '합병등 전후의 재무사항 비교표'의 OCN 실적(1차연도 2013·2차연도 2014로 판단 — FY2014 보고서에 두 해 실적이 모두 실림; 합병 후 OCN은 CJ E&M 내부 사업이라 기준·배부 방식 미공시). 2013 1~11월 224,097,517천원은 CJ E&M 2013 연결감사보고서 합병 주석(지배력 획득 시 배분된 인수가격 반영). 합병 후 대리지표는 CJ E&M 사업보고서 '사업부문별 요약 연결재무현황'(2014: 20150331004213, 2017: 20180330004046)과 CJ ENM 2025 사업보고서(20260318001469) 영업부문 주석 — tvN 등 다른 채널·스튜디오드래곤·티빙이 섞여 OCN 단독 성과가 아님 | BE5: 2015-03-31 CJ E&M 2014 사업보고서(합병 사후 비교): OCN 2014 매출 224,274백만원·영업이익 34,944백만원으로 합병 전 예측(293,483·58,767) 대비 24%·41% 미달, 사유 "방송 광고시장의 업황 부진"·"킬러 콘텐츠 확보 및 제작역량 강화를 위해 제작투자를 계획대로 진행"; 2007-01-22(2007-02-06 감사 확정 정정) 온미디어 '매출액 또는 손익구조 30% 이상 변경(자회사 OCN)': 2006 OCN 매출 140,322백만원(+39.8%)·영업이익 38,781백만원(+58.6%), 변동 주요원인 "광고시장 성장에 따른 매출액 증가"; 2006-09-18~22 해외 IR(상반기 경영현황·장기전략)과 2007-02-13 2006 연결실적 발표 공정공시가 있으나 발표 자료 원문(온미디어 홈페이지, 폐쇄)은 확인하지 못함. 어닝콜 녹취록 없음 | BF5: 완료 | BG5: 2026-10-26
A6: C003 | B6: CJ ENM | C6: 2007-06-05 | D6: CJ Music Co., Ltd. | E6: 15 | F6: True | H6: MA④ | I6: MA④ | J6: 같음 | K6: 해당 없음 | L6: 불일치 | M6: 편입 후 | N6: Closed | O6: 284.43 | P6: M-net Media Corp | Q6: CJ Corporation (KOSE:A001040) | R6: M-net Media Corp (KOSDAQ: A056200) signed an agreement to acquire CJ Music Corporation from CJ Corp. (KOSE: A001040) for approximately KRW 260 billion in stock on February 5, 2007. As per the terms of the transaction, the exchange ratio of M-net and CJ Music is 1:0.9019140. | S6: Music & Fan Entertainment | T6: Music / Artist Management | U6: MA-2 그룹 내부 재편 | W6: MA④ 그룹 내부 재편 | Y6: False | Z6: MA④ 그룹 내부 재편 | AA6: 편입 후 (CJ ENM 전신 계보: 엠넷미디어, 2011 CJ ENM 계보로 합병 — 엠넷미디어는 2011-03-01 오미디어홀딩스(CJ E&M)에 흡수합병(C008)되고 CJ E&M은 2018-07-01 CJ오쇼핑에 합병돼 현 CJ ENM이 됨). 참고: 거래 당시 엠넷미디어는 CJ㈜(20.40%, CJ미디어 포함 26.84%)가 최대주주인 CJ그룹 계열사로, 현 CJ ENM 법인(당시 CJ홈쇼핑)의 종속회사는 아니었음 | AB6: 완료 (2007-05-31 합병기일; 2007-06-04 합병등기, 2007-06-05 합병종료보고서 제출 — 원자료 date 2007-06-05는 종료보고서 날짜) | AC6: 126,664,301,610원 (합병신주 14,575,869주 × 엠넷미디어 합병가액 8,690원; = 씨제이뮤직 16,161,041주 × 본질가치 7,837.63원, 합병비율 1:0.9019140). 배정: CJ㈜ 9,196,994주(79,922백만원), CJ미디어 5,116,218주(44,460백만원), 씨제이뮤직 자기주식분 262,657주(엠넷 자기주식이 됨). 씨제이뮤직 주주가 모두 CJ 계열이라 그룹 밖으로 나간 대가는 없음 | AD6: 원자료와 불일치: 공시 기준 126,664백만원 = 136.9백만 달러 (Yahoo Finance KRW=X 2007-02-05 종가 925.15원/달러, 계산). 원자료 284.43은 같은 환율로 약 2,631억원으로 설명란 'KRW 260 billion'과 맞음. 추정: 2006-12-29 2대1 감자 전 씨제이뮤직 주식수 32,322,082주를 쓴 값 — ×0.9019140 = 29,151,738주를 합병가액 8,690원으로 평가하면 2,533억원(273.8백만 달러, 원자료와 -3.7%), 엠넷 기준주가 산술평균 9,083원으로 평가하면 2,648억원(286.2백만 달러, +0.6%). 공시상 합병 시점 씨제이뮤직 주식은 감자 후 16,161,041주였으므로 원자료 금액은 약 2배 과대 | AE6: 2007-02-05 | AF6: 기준 분류 유지(MA④): 매수자 엠넷미디어(CJ㈜ 20.40%·CJ미디어 6.44%로 CJ 계열이 최대주주)와 매도자 씨제이뮤직 주주(CJ㈜ 63.1%, CJ미디어 35.1%, 자기주식 1.8%)가 모두 CJ그룹 회사(합병결정 공시 '회사와의 관계: 계열회사'). 원자료 sellers 'CJ Corporation'만 적었으나 CJ미디어 35.1%도 매도자. 원자료 date(2007-06-05)는 합병종료보고서 제출일이고 최초 발표는 2007-02-05(이사회·합병계약·공시). 합병비율 1:0.9019140은 공시와 일치. 금액은 원자료보다 공시값이 약 절반(value_chk_usdmm 참조). 비상장 씨제이뮤직이 상장사 엠넷미디어에 합병되며 최대주주 지분이 늘어 공시상 '우회상장 해당 여부: 예'로 분류됨. 분류 해석 주의: 매도자 CJ㈜를 '그룹'으로 본 원자료 기준을 따름 — 최신 CJ 계보 규칙처럼 CJ ENM 계보로 좁히면 CJ㈜는 계보 밖이라 구조상 MA①(계보 회사 엠넷미디어가 계보 밖 CJ㈜로부터 씨제이뮤직 100% 취득)으로도 볼 수 있음(사용자 확인 필요) | AG6: C008의 선행 거래: 이 합병으로 씨제이뮤직의 음반·음원 사업과 Mnet 음악채널 사업이 엠넷미디어로 들어갔고, 엠넷미디어는 2010-11-16 결정된 CJ E&M 6사 합병에서 소멸(C008). 씨제이뮤직(DART 00525031)은 2003-02 씨제이미디어라인으로 설립, 2004-12 (구)씨제이뮤직과 합병, 2005-03-17 씨제이뮤직으로 상호 변경, 2006-09 CJ미디어의 현물출자로 Mnet 음악채널 사업부를 넘겨받음, 2006-12 2대1 무상감자. 엠넷미디어(DART 00335562, 코스닥 056200)는 1994년 설립 e-러닝·SI 회사 ㈜메디오피아테크날리지로 2002-01 코스닥 상장, 2006-07 CJ㈜·CJ미디어 제3자배정 유상증자(9,090,908주)로 최대주주가 CJ㈜로 바뀌고 같은 달 지엠기획·에이디이천엔터테인먼트를 포괄적 주식교환으로 편입(2006-09 소규모 합병), 2006-08-22 엠넷미디어로 상호 변경, 2006-09 기존 사업을 물적분할(메디오피아테크, 2006-12 매각). 2006년 엠넷 당기순손실 45,860백만원은 '합병으로 인한 무형자산 감액손실(316억원)'이 주원인(2007-01-30 손익구조변동 공시). 합병 후 엠넷미디어 반대주주 1,748,989주가 주당 9,225원(16,134백만원, 차입금)에 주식매수청구됨 — 매수자 측 현금 유출이지 대상회사 주주에 대한 대가는 아님. 회계: 합병 전후 요약재무에서 씨제이뮤직 순자산 22,094백만원을 단순합산해 자본금 7,288백만원·자본잉여금 15,375백만원으로 반영하고, 엠넷 2008 감사보고서 영업권 주석에도 2007년 합병 증가분이 없음 → 이 합병의 영업권은 없음. 공시 시점: 엠넷 매매거래정지 2007-02-05 16:18:36(장 마감 후)~2007-02-06 해제. 합병 전 회사 전망(2007-04-17 공정공시: 2007년 매출 1,210억원·영업이익 119억원)과 실제(매출 629억원·영업손실 183억원)의 괴리가 크고 회사가 정정공시로 사유를 밝힘(earnings_call_note). 조사 한계: 2006~2007년 엠넷미디어 사업보고서 일부 절은 DART 서버가 깨진 글자로 돌려줘 2010 증권신고서의 5년 요약재무를 씀. 당시 언론 보도·IR 발표자료는 찾지 못해 회사의 공정공시로 대신함 | AH6: 엠넷미디어㈜ (영문 M-net Media Corp., 코스닥 056200; CJ㈜ 20.40%·CJ미디어 6.44%가 최대주주인 CJ그룹 계열사, 옛 ㈜메디오피아테크날리지) | AI6: "음반,방송 시장에서의 경쟁력 제고와 경영효율성 증대를 통하여 시너지 효과를 극대화하고 주주가치 극대화를 추구하고자 합니다" (회사합병결정 공시 합병목적·합병신고서 합병의 목적) | AJ6: 음반·음원 기획·유통, 온라인 음악 포털(스트리밍·다운로드), 연예 매니지먼트. 2006년(제13기) 매출 22,643,185천원 중 분할·합병 후 영위사업(2006-09-23~12-31) 6,278,717천원(컨텐츠사업 2,932,387천원 + 포털사업 3,346,330천원), 나머지 16,364,468천원은 2006-09 물적분할로 넘긴 e-러닝·SI 기존사업(2007 합병신고서 엠넷미디어 매출실적). 2006년 영업손실 10,137,612천원 | AK6: 핵심 | AL6: 씨제이뮤직의 주력은 음반·음원(2006년 매출 16,922,980,862원, 66%)으로 엠넷미디어의 음반·음원·온라인 음악 사업과 같은 영역. 함께 들어온 Mnet 음악채널(방송사업 8,705,728,248원, 34%)은 음악 콘텐츠 유통 경로로 인접 영역. 그룹 정점 CJ ENM 기준으로도 음악·음악채널(Mnet)은 현 음악사업 부문의 전신이라 핵심 | AM6: 139,878,437천원 (엠넷미디어 별도, 2006-12-31; 2007 합병신고서 요약재무정보 제13기). 참고: 합병종료보고서의 2007-03-31 기준 134,993,665,460원 | AN6: 7,200,333,028천원 (상장 지배회사 CJ㈜ 및 종속회사 연결 총자산, 2006-12-31; CJ㈜ 2006 연결감사보고서). 인수 주체 엠넷미디어도 코스닥 상장사이나 지배회사는 CJ㈜. 2007년에는 CJ E&M이 없었고 당시 CJ홈쇼핑(현 CJ ENM 법인)은 이 거래와 무관 | AO6: 계산: 90.55 (126,664백만원 ÷ 엠넷미디어 총자산 139,878백만원, 2006-12-31). CJ㈜ 연결 총자산 대비 1.76. 합병 공시에 총자산대비 항목 없음 | AP6: 계산: 105.74 (126,664백만원 ÷ 엠넷미디어 자본총계 119,783백만원, 2006-12-31) | AQ6: 계산: 294,270,730,050원 (2007-02-02 종가 8,690원 × 발행주식 33,863,145주; 종가는 합병비율 평가의견의 기준주가 산정표, 주식수는 합병신고서 합병 전 발행주식수). 주의: 합병 공시가 2007-02-05 정규장 마감 후(매매정지 16:18:36)라 엄밀한 '발표 직전 거래일'은 2007-02-05이나, 그날 종가는 상장폐지 종목이라 Yahoo Finance에 없고 공시에서도 찾지 못함 | AR6: 총자산·자본은 엠넷미디어 2006-12-31 감사 재무(2007 합병신고서 20070329001139 요약재무정보). 합병가액 8,690원은 2007-02-02 종가가 산술평균가(9,083원)보다 낮아 기준주가로 쓰인 값(평가기관 우리회계법인). 신주 배정은 합병신고서 최대주주 변동표(CJ㈜ 6,909,090→16,106,084주, CJ미디어 2,181,818→7,298,036주)와 보호예수 내역(CJ㈜ 9,196,994주, CJ미디어 5,116,218주, 씨제이뮤직 262,657주)에서 확인 | AS6: KRX:056200 | AT6: 인수 주체 엠넷미디어(코스닥 056200; 2011-03 CJ E&M에 피합병돼 상장폐지라 Yahoo Finance 시세 없음). 대상 씨제이뮤직은 비상장. 그룹 정점 CJ㈜(KRX:001040)도 함께 볼 수 있음. 엠넷미디어 주권은 2007-02-05 16:18:36(정규장 마감 후) '우회상장 여부 및 요건충족 확인'으로 매매거래정지(20070205900084)됐다가 2007-02-06 해제(20070205900119, 해제사유 '합병신고서 제출(우회상장 해당)')돼 첫 반응일은 2007-02-06 | AU6: 2007-02-05 정규장 마감 후: DART 엠넷미디어 회사합병결정·합병신고서, 씨제이뮤직 회사합병결정 공시, 엠넷미디어 주권 매매거래정지(16:18:36)·2007-02-06 해제. 2006-12~2007-02 엠넷미디어 공시 목록에 관련 조회공시 없음, 사전 보도는 찾지 못함 | AV6: 2003-02: 씨제이미디어라인 설립; 2004-12: (구)씨제이뮤직과 합병; 2005-03: 씨제이뮤직으로 상호 변경; 2005-07~2006-02: 유상증자(80억원씩) 후 갑·DSP·울림·팜·H2·오렌지쇼크·플레디스·마스터플랜·스타애비뉴·원오원 등 기획사 지분 투자, 좋은콘서트 인수; 2006-05: 음악포털 Mnet.com 오픈; 2006-07: CJ㈜·CJ미디어가 엠넷미디어 제3자배정 유상증자로 26.84% 취득(최대주주 변경); 2006-09: CJ미디어 현물출자로 Mnet 음악채널 사업부 양수; 2006-12: 2대1 무상감자; 2005→2006: 씨제이뮤직 매출 1,973,050천원→25,628,709천원, 영업이익 -2,194,875천원→2,512,586천원 | AW6: 2007-04-16: 엠넷미디어 임시주총 합병 승인; 2007-04-17: 합병 반영 2007년 매출 1,210억원·영업이익 119억원 전망 공정공시; 2007-05-07~17: 반대주주 1,748,989주 주식매수청구(9,225원); 2007-05-31: 합병기일(발행주식 33,863,145→48,439,014주, CJ㈜ 33.25%·CJ미디어 15.07%); 2007-06-28: 합병신주 14,575,869주 추가상장(2009-05-30까지 보호예수, 우회상장 표시); 2007·2008: 엠넷미디어 영업권 손상(7,684·26,944백만원, 2006년 기획사 인수분으로 보임); 2008-02-29: 2007년 전망을 매출 629억원·영업손실 183억원으로 정정(음반시장 침체·포털 유료화 차질·매니지먼트 매출 순연); 2008-03-28: 영문 상호 Mnet Media Corp.로 변경; 2009-10: SC PE·CJ㈜ 대상 300억원 CB·BW 발행; 2010-12~2011-02: BW 행사·CB 전환으로 주식수 65,170,746주; 2010-11-16: 오미디어홀딩스(CJ E&M)의 엠넷미디어 흡수합병 결정(C008); 2011-03-01: CJ E&M 음악·공연 및 방송(Mnet·KM 채널) 부문으로 편입; 2016-12-01: 음악플랫폼(Mnet.com) 물적분할 → 씨제이디지털뮤직; 2018-07-01: CJ ENM 출범; 2018-10: 씨제이디지털뮤직이 ㈜지니뮤직에 흡수합병(CJ ENM 지니뮤직 지분 2024년말 15.35%); 2024: CJ ENM 음악사업(엠넷 채널 포함) 매출 702,102백만원·영업이익 30,883백만원, 지니뮤직 관계기업투자주식 손상 30,293백만원 | AX6: 해당 없음 (이 합병은 씨제이뮤직 순자산을 장부금액으로 단순합산해 자본금·자본잉여금으로 반영, 영업권 미인식 — 합병종료보고서 합병 전후 요약재무; 엠넷 2008 감사보고서 영업권 주석에도 2007년 합병 증가분 없음). 참고: 엠넷미디어 영업권 손상차손 2007년 7,683,957천원, 2008년 26,944,153천원(2008 감사보고서 주석 9; 추정: 2006년 지엠기획·에이디이천엔터테인먼트 주식교환·합병에서 생긴 영업권 — 2005년말 무형자산 585,710천원 → 2006년말 64,170,062천원, 2006년 감액손실 316억원 별도), 2008년 지분법적용투자주식 손상차손 13,073,303,878원. 후속 사업 수준 참고: Mnet.com 사업을 흡수한 지니뮤직 지분에 CJ ENM이 2024년 관계기업투자주식 손상차손 30,293백만원 인식(CJ ENM 2024 사업보고서 연결 관계기업 주석) | AY6: 동일지배 합병·그룹 내 이전으로 새 영업권·투자주식 평가가 생기지 않음 | AZ6: 2005: 1,973,050천원; 2006: 25,628,709천원 (씨제이뮤직 별도; 2006년은 음악사업 16,922,981천원 + 2006-09 양수한 Mnet 채널 방송사업 8,705,728천원) | BA6: 2007: 62,892,777천원; 2008: 118,535,379천원 (합병 후 엠넷미디어 별도, 씨제이뮤직 사업은 2007-06부터 포함); 최근(독립 법인 마지막 연도) 2010: 146,925,601,938원(포털 44,037백만원·음악 49,209백만원·방송 40,208백만원·기타 13,472백만원). 후속 사업 대리지표 — CJ E&M 음악·공연(·온라인) 부문: 2011 132,460백만원(합병 후 3~12월), 2017 음악부문 230,732백만원; CJ ENM 음악사업 2024 702,102백만원 | BB6: 2005: -2,194,875천원; 2006: 2,512,586천원 (씨제이뮤직 별도) | BC6: 2007: -18,270,619천원; 2008: -3,109,256천원 (엠넷미디어 별도); 최근(독립 법인 마지막 연도) 2010: 1,577,740,895원. CJ E&M 음악·공연 부문 2011 -847백만원, 2017 음악부문 11,778백만원; CJ ENM 음악사업 2024 30,882,579천원 | BD6: 인수 전: 씨제이뮤직 별도·K-GAAP·12월 결산(2007 합병신고서 20070329001139 씨제이뮤직 요약재무·매출실적; 2006 감사보고서 기준). 인수 후: 대상은 2007-05-31 소멸해 사업을 이어받은 엠넷미디어 별도 실적으로 대신함 — 엠넷미디어 자체의 기존 음반·포털·매니지먼트 사업이 섞여 있음. 2007~2009는 2010 CJ E&M 합병 증권신고서(20101202000223) 엠넷미디어 요약재무(천원), 2010은 엠넷미디어 감사보고서(20110310000462). 2011 이후는 CJ E&M 연결 음악·공연 부문(2014년부터 음악부문 분리 공시)과 CJ ENM 음악사업 부문(K-IFRS) — Mnet 채널은 CJ E&M 시절 방송부문, CJ ENM 2024년에는 음악사업에 포함돼 범위가 다름 | BE6: 2007-04-17 엠넷미디어 영업실적 전망 공정공시('향후 당사의 IR자료로 활용'): 합병 반영 2007년 매출 1,210억원·영업이익 119억원(합병 미반영 821억원·31억원), 근거 '방송채널의 시청율 및 점유율 상승', '컨텐츠 제작 및 공연사업등과의 시너지를 통한 제작원가 절감'; 2008-02-29 정정공시: 2007년 매출 629억원·영업이익 -183억원으로 수정, 사유 '음반시장 침체로 인하여 매출 약 70억 차질', 포털 '유료화 수입 차질 ... 약240억 차질', 매니지먼트 '약288억 차질', '매출부진에 따른 이익감소 약300억 차질'; 2009-03-05 2008년 실적 공시: '당초 영업이익 흑자전환을 기대하였으나, 연도말 금융위기에 따른 대손금 설정증가로 달성하지 못하였음'. 어닝콜 녹취록·IR 발표자료는 찾지 못함 | BF6: 완료 | BG6: 2026-10-26
A7: C004 | B7: CJ ENM | C7: 2009-12-24 | D7: On Media Corp. | E7: 11 | F7: True | H7: MA① | I7: MA① | J7: 같음 | K7: 식별 불가 | L7: 불일치 | M7: 편입 후 | N7: Effective | O7: 435.77 | P7: CJ ENM CO., Ltd. (KOSDAQ:A035760) | Q7: ORION Holdings Corp. (KOSE:A001800) | R7: CJ O Shopping Co., Ltd. (KOSE: A035760) agreed to acquire a 55.17% stake in On Media Corp. from Orion Corporation (KOSE: A001800), Tam Cheol-gon and other shareholders for approximately KRW 430 billion in cash on December 24, 2009. CJ O Shopping will offer KRW 6669 per share of On Media. The offer price represents a 71% premium to the On Media’s closing price of December 23, 2009. If South Korea's Fair Trade Commission doesn't approve of the majority stake purchase, then CJ O Shopping is expected to acquire about 15% stake of On Media. The deal is subject to regulatory approval and approval of South Korea's Fair Trade Commission. The transaction was approved by the Board of Directors. The deal is expected to close by the first half of 2010. As of May 31, 2010, the deal was approved by the South Korea's Fair Trade Commission. As of June 8, 2010, Orion Corporation sold it share in On Media Corp. HSBC Bank plc acted as financial advisor to Orion Corporation. Morgan Stanley acted as financial advisor and Kpmg Samjong Accounting Corporation acted as a financial due diligence to CJ O Shopping. | S7: Media Platforms | T7: Broadcasting Channel | U7: MA-1 그룹이 매수자 | V7: 과반 인수(≥50%) | W7: MA① 경영권 인수 | Y7: False | Z7: MA① 경영권 인수 | AA7: 편입 후 (매수자 ㈜씨제이오쇼핑은 현 CJ ENM 법인 자체 — DART 고유번호 00265324, 2018-07-01 CJ E&M 흡수합병 후 CJ ENM으로 사명 변경. 대상 온미디어는 이 거래로 2010-05-28 CJ오쇼핑의 자회사로 편입(지주회사의 자회사 편입 공시), 2010-06-08·06-30 대금지급으로 소유 확정) | AB7: 완료 (2010-06-30; 공정위 기업결합 승인통보 2010-05-28, 오리온 및 특수관계인 40.18% 대금지급·주식양수 2010-06-08, 외국계 3개 펀드 14.99% 대금지급 2010-06-30 — 합병등종료보고서의 자산양수도 완료일 2010-06-30) | AC7: 434,479,300,000원 (온미디어 보통주 65,148,910주·55.17%, 평균 주당 6,669원. 매도자별: ㈜오리온 및 특수관계인 5인 47,448,210주(40.18%) 345,976백만원(주당 약 7,292원, 경영권 프리미엄 포함); Tabimax SGPS Lda 8,459,598주 42,298백만원·Capital International GEM PE Fund 7,392,882주 36,964백만원·New Asia East Investment Fund 1,848,220주 9,241백만원(이상 주당 5,000원, 소계 88,503.5백만원). 현금, 계약 시 위약금 346억원 예치) | AD7: 원자료와 불일치: 434,479백만원 = 370.38백만 달러 (계산: Fed H.10 2009-12-24 1,173.07원/달러). 대금 지급일 환율로 나누면 352.87백만 달러(오리온분 2010-06-08 1,233.99원 → 280.37 + 외국계분 2010-06-30 1,220.85원 → 72.49). 원자료 435.77은 어느 기준으로도 재현되지 않으며 설명란 'approximately KRW 430 billion'을 원/달러 약 987원으로 나눈 값에 해당해 환산 오류로 보임 | AE7: 2009-12-24 | AF7: 기준 분류 유지(MA① 경영권 인수): CJ오쇼핑이 지분이 없던 온미디어의 55.17%를 사 최대주주·경영권을 처음 확보. 원자료 buyers 'CJ ENM CO., Ltd. (KOSDAQ:A035760)'는 현 사명 기준 표기이며 당시 인수 주체는 ㈜씨제이오쇼핑(같은 법인 00265324) — 다른 CJ 계열사(CJ㈜·CJ미디어 등)가 아님을 공시로 확인. 원자료 sellers 'ORION Holdings Corp.'는 당시 ㈜오리온(현 오리온홀딩스)이며 담철곤 외 4인과 외국계 펀드 3곳도 매도자. 설명란의 'KRW 6669 per share'는 평균값으로 실제는 오리온 측 약 7,292원·외국계 5,000원의 이중 가격이며, '71% premium'은 평균가 기준(6,669/3,910원 = 70.6%; 외부평가 기준 오리온 측 86.5%·기타 27.88%). 'approved by FTC as of May 31, 2010'은 공정위 승인통보 2010-05-28·발표 2010-05-30이 정확함. 금액 435.77백만 달러는 환산 오류로 보여 370.38로 정정 제안 | AG7: 온미디어 계보(CJ-B)의 중심 거래. 선행: C002(2006, 오리온 시절 OCN 증자). 후행: C009(2010-11 결정·2011-03-01 오미디어홀딩스=CJ E&M이 온미디어를 흡수합병하며 잔여 지분 정리 — 같은 날 C005~C008 CJ E&M 출범 합병과 한 건), C010(2010-12 온게임넷 7%), C011·C012(2013-12 바둑TV·OCN 흡수합병). 인수 주체 문제: 거래는 CJ오쇼핑이 했지만 2010-09-01 CJ오쇼핑 인적분할로 온미디어 지분 55.17%가 신설 ㈜오미디어홀딩스(2010-12-30 CJ E&M으로 사명 변경)로 넘어가 이후 성과는 CJ E&M 쪽에서 나타남; CJ오쇼핑과 CJ E&M은 2018-07-01 다시 합쳐져 현 CJ ENM이 되므로 계보상 같은 그룹 안. 매각 경과: 오리온은 2009-04 매각설 조회공시에 '검토 중', 2009-09-04 '매각하지 않기로 결정' 통보, 2009-12-10 CJ의 인수 제안 확인 후 2009-12-24 계약 — 인수가격 재협상 가능성이 당시 분석(신한금융투자)에서 거론됨. 자금: 자기자금 2,285억(2009말 보유현금 약 2,500억, 2009 회사채 1,300억 포함)·차입 600억(국민은행·농협)·기타 1,460억(공모사채 600억, 자회사 CJ헬로비전드림씨티방송 유상감자 대금 약 860억). 공시 불일치: 2009-12-24 타법인주식취득결정은 '공정거래위원회 신고대상 여부: 미해당'이라 적었으나 실제로는 공정위 기업결합심사를 거침(2010-06-03 대량보유보고서·언론 보도). 합병등종료보고서의 '1주당 액면가액 5,000원'은 온미디어 액면 500원(2006 분할)의 오기. 사후 가치 시사점: 평균 취득가 6,669원 대비 2010-11 합병가액 3,535원, 2011-01-28 CJ E&M의 블록세일 가격 4,900원(10%, 578.2억원)으로 시장가는 취득가를 크게 밑돌았음(승자의 저주 검토 자료). 방통위 최다액출자자 변경 승인일 자체는 찾지 못함(2010-02-09 심사계획 보도만 확인, 2010-06-03 대량보유보고서는 '최종 정부기관(방통위,공정위) 승인 후 장외 매매계약 확정'이라고만 기재) | AH7: ㈜씨제이오쇼핑 (CJ O Shopping, 코스닥 035760; 현 CJ ENM 법인. 최대주주 CJ㈜ 39.96%(2010-06). 당시 TV홈쇼핑·카탈로그·인터넷몰 사업자이자 MSO ㈜씨제이헬로비전의 모회사) | AI7: "홈쇼핑 사업 경쟁력 강화 등" (타법인주식및출자증권취득결정 취득목적) / "CJ오쇼핑의 차별화를 위한 핵심 역량의 강화는 물론, 기존 사업 기반의 확대와 보유 자산의 가치 증대에도 기여할 것으로 판단" (주요사항보고서 자산양수도의 배경) / "미디어에 쇼핑을 접목한 '컨버전스(Convergence)'모델을 통해 새로운 성장 동력을 만들어간다는 전략의 일환" (주요사항보고서) / "유통과 미디어를 결합해 다른 경쟁사와 차별화시키겠다" (CJ오쇼핑, 머니투데이 2009-12-24) | AJ7: 케이블 TV홈쇼핑 중심의 무점포 유통(TV홈쇼핑·카탈로그·인터넷 통신판매). 2008 별도 영업수익 542,420백만원·영업이익 87,251백만원, TV홈쇼핑 취급고 점유율 25.1%(2008). 연결로는 SO 자회사 CJ헬로비전(260만 가입자) 포함 2008 매출 963,557백만원·영업이익 119,012백만원(2009 사업보고서 요약재무·사업의 내용) | AK7: 인접 | AL7: CJ오쇼핑은 홈쇼핑 채널을 공급하는 PP이자 SO(CJ헬로비전)를 가진 유통·플랫폼 회사로, 일반 PP 콘텐츠(MPP 채널)는 같은 유료방송 가치사슬의 다른 단계 — 공시도 '컨버전스'·'MSP(MSP+MPP) 사업모델'(원문 표기 그대로; MSO+MPP의 오기로 보임)과 SO 가입자 320만 확보를 내세움. 온미디어의 SO 4곳(56만 가입자)은 CJ헬로비전과 같은 사업이지만 매출 비중이 작음. 인수 직후 지분이 미디어 전문 법인(오미디어홀딩스→CJ E&M)으로 넘어갔고, 현 CJ ENM(미디어플랫폼·영화드라마·음악·커머스) 기준으로는 TV채널 사업의 핵심 축이 됨 | AM7: 969,862,669,601원 (CJ오쇼핑 별도, 2008-12-31; 주요사항보고서·타법인주식취득결정 '최근 사업연도말 자산총액') | AN7: acq_total_assets와 같음 (인수 주체 CJ오쇼핑이 상장 지배회사 자신). 참고: CJ오쇼핑 연결 총자산 1,669,955,092천원 (2008-12-31, 2009 사업보고서 요약연결재무정보 제15기); 거래금액/연결총자산 26.0%(계산) | AO7: 44.80 | AP7: 86.97 | AQ7: 계산: 834,610,832,600원 (발표 직전 거래일 2009-12-23 종가 75,800원 × 발행주식 11,010,697주(2009-12-31 자본금 55,053,485,000원/액면 5,000원)). 종가는 Yahoo Finance 035760.KQ 수정주가 104,635.53원을 조정계수 1.380416으로 나눠 복원 — 계수는 2009년 12월 Yahoo 최고·최저 종가(118,025.57·99,942.12)를 2009 사업보고서의 12월 종가 기준 최고 85,500원·최저 72,400원과 맞춰 산출(두 값 모두 1.380416으로 일치). 발표일 2009-12-24 종가 78,200원(+3.2%) | AR7: 총자산·자기자본(499,578,002,714원)·비율은 2009-12-24 타법인주식및출자증권취득결정(20091224900008)과 2009-12-28 주요사항보고서(20091228000114) 기재값(분모 2008-12-31 별도). 연결 총자산은 2009 사업보고서(20100331000039). 시가총액은 복원 종가 × 2009말 발행주식수(계산) | AS7: KRX:035760 | AT7: 인수 주체 CJ오쇼핑(코스닥 035760, 현 CJ ENM — Yahoo 시세는 2010-09 인적분할·이후 주식배당 등을 소급 조정한 값이라 원래 종가는 1.380416으로 나눠야 함, 2009-12 기준). 대상 온미디어도 유가증권시장 상장사(KRX:045710, 2011-03 합병으로 상장폐지·Yahoo 시세 없음): 2009-12-23 종가 3,910원(외부평가 기준주가표), 시가총액 461,763,140,900원(계산, 118,097,990주), 발표 후 상한가·시가총액 한때 5,300억원 이상(머니투데이). 매도자 ㈜오리온(KRX:001800)도 분석 가능. 사전 반응: 2009-09-07 매각 무산 보도에 온미디어 −2.34%·CJ오쇼핑 +2.42%(뉴스토마토) | AU7: 2009-04-29: 거래소의 온미디어 '최대주주 지분매각설' 조회공시 요구 → 04-30 답변(미확정, 최대주주가 매각 검토 중); 2009-06-22: CJ오쇼핑 자율공시 '온미디어 인수 검토의 건'(확인일 06-19, 07-17·08-17 재공시); 2009-09-04: 온미디어 '오리온이 매각하지 않기로 결정' 통보 공시(부인); 2009-12-10: 'CJ그룹으로의 피인수설' 조회공시 → 답변(오리온이 CJ그룹으로부터 인수의향과 가격 제안을 받음, 미확정); 2009-12-24: 이사회 결의·계약 및 공시 | AV7: 2000-06-15: 온미디어 설립(오리온그룹 지주회사, OCN 50.48%·바둑TV 53.47% 현물출자); 2000-10: 투니버스·온게임네트워크 지분 취득; 2000-12~2001-09: 동구·전남동부·서남·영동·수성·서대구 등 SO 지분 취득; 2004-04: 투니버스 흡수합병(사업지주회사); 2006-07-03: 유가증권시장 상장; 2007~2009: 온미디어 연결 매출 316,356→312,917→281,091백만원, 연결 영업이익 63,041→22,182→24,002백만원(2008 급감); 2008: MPP 매출 점유율 CJ 20.8%(1위)·온미디어 11.1%(2위); 2009-04-29: 매각설 조회공시; 2009-06-22: CJ오쇼핑 인수 검토 공시; 2009-09-04: 오리온 매각 철회 통보; 2009-10-01: 온미디어 8개 채널 SK브로드밴드 IPTV 공급계약(경쟁 IPTV에 채널 공급); 2009-12-10: CJ 제안 확인; 2009-12-12: 외부평가(지성회계법인) 계약 — DCF 주당 4,846~7,406원 | AW7: 2010-02-09: 방통위 심사계획(최다출자자 변경·소유제한 검토) 보도; 2010-05-28: 공정위 최종 기업결합심사 승인통보(조건부 — 경쟁 다채널유료방송사업자, 특히 IPTV에 정당한 이유 없이 콘텐츠 동등 접근 기회 제공, 2013년 말까지; 결합 후 PP 점유율 31.9%, 영화·생활여성 100%·만화 82%), CJ오쇼핑 자회사 편입; 2010-06-08: 오리온 측 40.18% 대금지급, 최대주주 변경; 2010-06-10: CJ오쇼핑 유통/투자부문 인적분할 결정(0.55:0.45); 2010-06-30: 외국계 14.99% 대금지급(자산양수도 완료), 온미디어 담철곤·조경민 사임·김성수 단독대표; 2010-09-15: 분할신설 ㈜오미디어홀딩스 설립등기(분할기일 09-01), 온미디어 최대주주가 오미디어홀딩스로 변경; 2010-10-15: 오미디어홀딩스 코스닥 재상장; 2010-10-27: 이플레이온 청산 결정; 2010-11-16: 온미디어 등 5사 합병 결정(C009); 2010-12-07: CJ E&M 합병설명회 — 2011 통합법인 매출 13,970억·영업이익 1,550억원, 방송사업 2011 매출 6,978억·영업이익 703억원 전망, 온미디어 지분 최대 15% 매각·디지틀온미디어·SO 4사 매각 계획; 2010-12-30: 오미디어홀딩스→씨제이이앤엠 사명 변경; 2011-01-28: CJ E&M이 온미디어 11,800,000주(10.0%)를 주당 4,900원(578.2억원)에 블록세일(재무구조 개선); 2011-02-22: 디지틀온미디어 지분 전량 235억원 매각; 2011-03-01: 온미디어 흡수합병·소멸(해산등기 03-03); 2011: CJ E&M 방송부문 매출 6,358억·영업이익 474억원(전망 대비 미달); 2012-03-14: 옛 온미디어 SO 4사(영동·대구수성·대구동구·아라방송) 지분 전량을 CJ헬로비전에 1,697억원 매각('비핵심 사업에 대한 사업구조조정', 자산양수도 완료 2012-05-30); 2013-12-01: OCN·온게임넷·바둑TV 흡수합병(C011·C012); 2018-07-01: CJ오쇼핑이 CJ E&M 흡수합병, CJ ENM 출범; 2025: CJ ENM 미디어플랫폼 부문 매출 1조 3,416억원·영업이익 13억원 | AX7: 온미디어 인수 영업권 자체의 손상은 확인 안 됨. 근거: 오미디어홀딩스(CJ E&M) 2010 연결감사보고서(K-GAAP) 영업권 기초 184,355,735천원(2010-09-01)→기말 181,257,320천원(상각 3,098,415천원만, 손상 없음) — 온미디어 인수로 생긴 영업권과 온미디어 자체 영업권이 섞인 금액으로 보임(추정: 오미디어홀딩스의 유일한 자회사가 온미디어); K-IFRS 전환 뒤 CJ E&M 영업권은 방송사업부문 등 현금창출단위에서 손상검사(2013·2017 연결 주석), 영업권 손상은 2013 957,306천원·2017 853,984천원 정도로 대상 미특정·소액; CJ ENM 2025 사업보고서 연결 주석의 영업권 현금창출단위 표상 미디어플랫폼사업부문 영업권은 2024말 376,778,468천원 → 2025말 371,615,748천원(−5,162,720천원, 변동 사유는 표에 부문별로 나오지 않음); 영업권 손상 합계는 2025 19,940,683천원·2024 38,388,927천원이나 현금창출단위별 배분이 표에 드러나지 않아 온미디어 계보 채널 사업과의 관련을 판단할 수 없음. 2014~2016·2018~2023 연도별 주석은 대조하지 않음 | AY7: 2010 영업권 상각만 있고 손상 없음, 이후 방송·미디어플랫폼 현금창출단위에 묶여 온미디어 몫을 알 수 없음 | AZ7: 2008: 연결 312,917백만원 (별도 75,837백만원); 2009: 연결 281,091백만원 (별도 67,746백만원) | BA7: 2010: 온미디어 연결 260,354,763,959원 (별도 73,556,536,273원; 마지막 독립 회계연도); 2011: CJ E&M 방송부문 635,789백만원(합병기일 3월 이후, CJ미디어·엠넷 채널 포함); 2012: CJ E&M 방송부문 764,151백만원; 최근 2025: CJ ENM 미디어플랫폼 부문 1,341,617백만원(외부매출; 부문간 포함 1,500,699백만원). 참고: 2010-12-07 합병설명회 방송사업 전망 2011 6,978억·2012 7,523억원 | BB7: 2008: 연결 22,182백만원 (별도 9,346백만원); 2009: 연결 24,002백만원 (별도 18,685백만원) | BC7: 2010: 온미디어 연결 21,799,200,936원 (별도 15,701,866,969원); 2011: CJ E&M 방송부문 47,394백만원; 2012: 44,554백만원; 최근 2025: CJ ENM 미디어플랫폼 부문 1,332백만원(1,332,256천원). 참고: 전망 2011 703억·2012 765억원 | BD7: 인수 전·2010은 온미디어 K-GAAP 12월 결산(2008·2009: 2009 사업보고서 20100401001044 요약재무·요약연결재무; 2010: 2010 감사보고서 20110331002850·연결감사보고서 20110426000457). 2011년 이후 온미디어는 법인이 없어 CJ E&M 사업보고서 '사업부문별 요약 연결재무현황'의 방송부문(K-IFRS 연결; 2011: 20120330002738 — 합병소멸법인 1~2월 실적 제외, 2012: 20130401001853)과 CJ ENM 2025 사업보고서(20260318001469) 영업부문 주석의 미디어플랫폼사업으로 대신함. 방송부문에는 옛 CJ미디어(tvN 등)·엠넷 채널이, 미디어플랫폼에는 티빙 등이 포함돼 온미디어 단독 성과가 아니며 2010 연결은 9월 이후 SO 매각 계획 등 구조 변화가 있음 | BE7: CJ E&M 2012·2013 사업보고서 '합병등 전후의 재무사항 비교표'(2011-03 합병): 통합 CJ E&M 매출 예측 1,397,000·1,661,000 / 실적 1,279,186(괴리 8%)·1,394,585(16%)백만원, 영업이익 예측 155,000·189,000 / 실적 75,420(51%)·38,947(79%) — "종편출범에 따른 경쟁비용 증가, 킬러콘텐츠 확보 및 제작역량 강화를 위한 콘텐츠 투자 확대 및 게임사업부문의 역성장으로 인해 예측치보다 저조한 실적"; 2010-06-08 온미디어 기관 대상 IR(1:1): '온미디어 최대주주 변경 관련 주요 경영현황 설명', 안건에 '최대주주 변경에 따른 조직 안정화를 위한 일회성 비용' 포함(IR 안내공시; 자료 원문은 폐쇄된 온미디어 홈페이지라 미확인); 2010-12-07 CJ E&M 합병 설명회(공정공시): 통합법인 2011 매출 13,970억·영업이익 1,550억원, 방송사업 2011 매출 6,978억·영업이익 703억원 전망, 근거로 'OSMU(One Souce Multy Use)강화', '컨텐츠 구매 경쟁력 강화를 통한 비용 절감' — 실제 2011 CJ E&M 연결 매출 11,431억·영업이익 701억, 방송부문 6,358억·474억원으로 전망 미달; 2011 사업보고서 경영진단: '방송 부문의 콘텐츠 투자 … 투자비용이 반영되어 영업이익은 701억원'; 2009-12-24 머니투데이: CJ오쇼핑 측 '보유 현금이 많고 자회사 배당금도 들어올 예정', 애널리스트 'CJ오쇼핑에는 별다른 시너지가 없으나 CJ미디어와는 시너지'. CJ오쇼핑 어닝콜 녹취록은 찾지 못함 | BF7: 완료 | BG7: 2026-10-26
A8: C005 | B8: CJ ENM | C8: 2010-11-16 | D8: CJ Entertainment Inc. | E8: 29 | F8: True | G8: C005 | H8: MA④ | I8: MA④ | J8: 같음 | K8: 해당 없음 | L8: 불일치 | M8: 편입 후 | N8: Closed | O8: 110.18 | P8: CJ E&M Corporation | Q8: CJ Corporation (KOSE:A001040) | R8: O Media Holdings Co., Ltd. (KOSE: A130960) signed a statuary merger agreement to acquire CJ Entertainment Inc. from CJ Corp. (KOSE: A001040) for approximately KRW 100 billion in stock on November 16, 2010. The exchange ratio for the transaction is 1: 1.1731389. O Media Holdings Co., Ltd. will survive and CJ Entertainment Inc will be dissolved on closing of the transaction. O Media Holdings Co., Ltd. also signed agreement to acquire remaining 44.83% stake in On Media Corp. (KOSE: A045710), M-net Media Corp, CJ Internet Corp. and CJ Media Inc. The deal is expected to close on March 1, 2011. Lee & Ko acted as legal advisor for the transaction. Gene Park and Craig Oh of WOORI Investment & Securities Co. Ltd. and Morgan Stanley acted as financial advisor for O Media Holdings Co., Ltd. Hyundai Securities Co., Ltd. acted as financial advisor for CJ Corp. Sang Gon Kim and Jun Taek Lee of Lee & Ko acted as legal advisors for O Media Holdings Co., Ltd. and acquire CJ Entertainment Inc. | S8: Content Production & Investment | T8: Content Investment / Distribution | U8: MA-2 그룹 내부 재편 | W8: MA④ 그룹 내부 재편 | Y8: False | Z8: MA④ 그룹 내부 재편 | AA8: 편입 후 (CJ ENM 전신 계보: ㈜오미디어홀딩스(2010-12-30 씨제이이앤엠㈜으로 상호 변경, 이 합병의 존속법인 CJ E&M 자체), 2018 CJ ENM 계보로 합병 — 2018-07-01 ㈜씨제이오쇼핑이 씨제이이앤엠㈜을 흡수합병하고 ㈜씨제이이엔엠으로 사명 변경, 증권발행실적보고서 20180702000188). 참고: 거래 당시 매수자는 CJ㈜가 최대주주(39.94%)인 CJ 계열 코스닥 상장사로, 현 CJ ENM 법인(당시 CJ오쇼핑)의 종속회사는 아니었음(2010-09-15 CJ오쇼핑 미디어사업 투자부문에서 인적분할된 자매회사). 대상 씨제이엔터테인먼트는 CJ㈜ 100% 자회사로 이 합병(2011-03-01)으로 CJ E&M에 편입 | AB8: 완료 (2011-03-01 합병기일; 2011-03-03 합병·해산등기, 합병신주 32,971,307주 2011-03-21 교부·2011-03-22 상장 예정 — 증권발행실적보고서) | AC8: 102,590,976,400원 (계산: 씨제이엔터테인먼트 3,000,000주 × 1.1731389 = 합병신주 3,519,416주 × 오미디어홀딩스 합병가액 29,150원; = 주당 합병가액 34,197원 × 3,000,000주 102,591,000,000원). 전량 CJ㈜에 배정돼 그룹 밖으로 나간 대가는 없음. 원자료 설명란 'approximately KRW 100 billion'과 일치 | AD8: 원자료와 불일치: 102,591백만원 = 90.1백만 달러 (Yahoo Finance KRW=X 2010-11-16 종가 1,138.10원/달러, 계산). 원자료 110.18은 같은 환율로 약 1,254억원으로, 원자료 자체 설명란('KRW 100 billion')과도 맞지 않음 | AE8: 2010-11-16 | AF8: 기준 분류 유지(MA④): 매수자 오미디어홀딩스(CJ㈜ 39.94%)와 매도자 CJ㈜(씨제이엔터테인먼트 지분 100%)가 모두 CJ그룹 회사이고 대가(합병신주)도 전부 CJ㈜가 받음. 원자료 buyers 'CJ E&M Corporation'은 합병 당시 사명 ㈜오미디어홀딩스(DART 00838421, 2010-12-30 씨제이이앤엠㈜으로 상호 변경)로, 현 CJ ENM 법인(00265324, 옛 CJ오쇼핑)과 다른 법인. 설명란의 비율 1:1.1731389와 2011-03-01 완료 예정은 공시와 일치. 설명란의 자문사(Lee & Ko, 우리투자증권·Morgan Stanley, 현대증권)는 공시에서 확인하지 못함(공시에는 외부평가기관 삼일회계법인만 기재). 같은 날 같은 매수자의 C006(CJ인터넷)·C007(CJ미디어)·C008(엠넷미디어)·C009(온미디어, 다른 묶음)와 한 합병 계약의 대상회사별 행 — 이중 집계 아님, 합산 시 합병신주 총 32,971,307주 | AG8: C001의 후속 거래: 대상 씨제이엔터테인먼트㈜(DART 00576309)는 2006-04-10 구 CJ엔터테인먼트(현 CJ EH, CJ㈜에 흡수)에서 물적분할로 신설된 영화 배급·투자·제작 법인(C001). 합병가액 34,197원은 비상장사라 외부평가기관 삼일회계법인이 본질가치(자산가치 40,264원·수익가치 30,152원, 1:1.5 가중)로 산정. 주식매수청구는 없었음(유일 주주 CJ㈜). 합병 후 CJ E&M 영화사업부문(대표 김정아)이 됐고, 영화부문 실적은 공연사업 포함 범위가 해마다 달라짐(2011~2013 음악/공연, 2014년부터 공연 별도). 어닝콜 녹취록은 찾지 못해 earnings_call_note는 실적 발표 기사·사업보고서 MD&A로 대신함 | AH8: ㈜오미디어홀딩스 (O Media Holdings Co., Ltd., DART 00838421, 코스닥 130960; 2010-09-15 ㈜씨제이오쇼핑의 미디어사업 투자부문이 인적분할돼 설립된 순수지주회사로 자회사 온미디어 55.17% 보유, 최대주주 CJ㈜ 39.94%(2010-11-16)→45.38%(2011-01-27); 2010-12-30 씨제이이앤엠㈜(CJ E&M)으로 상호 변경 — 합병 존속법인이 곧 CJ E&M) | AI8: "경영효율성을 증대시키고 엔터테인먼트사업(영화, 음악, 게임)과 미디어사업을 통합하여 시너지 효과를 극대화하고 규모의 경제를 갖추어 세계적 회사로 성장하기 위하여 합병하기로 결정함" (회사합병결정 공시 합병목적) / "① OSMU(One-Source-Multi-Use) 실현 가능 ② 광고 영업 효율화, 구매력 강화, 시너지 마케팅 활성화 ③ 세계시장 진출을 위한 규모의 경제 확보, 대규모 / 지속가능한 투자여력 확보" (주요사항보고서 예상 시너지) / "그룹이 목표로 하고 있는 콘텐츠 사업의 글로벌화와 계열사간 시너지 극대화를 위해 합병을 결정하게 됐다" (CJ 측, 이투데이 2010-11-16) | AJ8: 순수지주회사 — 자회사 ㈜온미디어(55.17%, 투니버스·OCN 등 케이블 방송채널사용사업자) 지분만 보유하고 영업수익은 지분법이익(증권신고서 투자위험요소 '순수지주회사로 영업수익은 지분법이익으로 구성'), 임직원 10명(2010-11 기준). 실질 사업은 온미디어의 케이블 PP: 2009년 온미디어 별도 매출 67,746백만원·자산 449,318백만원 | AK8: 인접 | AL8: 인수 주체(실질 사업은 자회사 온미디어의 케이블 영화·애니메이션 채널 OCN·투니버스 등)에게 영화 투자·배급은 같은 콘텐츠 가치사슬의 상류(영화 판권이 영화채널에 공급됨)라 인접 영역. 합병 공시도 OSMU를 첫 시너지로 꼽음. 그룹 정점 CJ ENM 기준으로는 영화가 현 영화드라마 부문의 전신이라 핵심 | AM8: 477,015백만원 (오미디어홀딩스 별도, 2010-09-30; 증권신고서 당사회사 요약·증권발행실적보고서 합병 전 요약재무). 설립 개시재무상태표(2010-09-01) 474,852,301,036원. 참고: 2010-12-31 별도 473,527,264,185원, 연결(K-IFRS) 810,677,928천원 | AN8: acq_total_assets와 같음 (인수 주체 오미디어홀딩스=CJ E&M이 상장 지배회사 자신; 2010-09-15 설립이라 직전 회계연도말이 없음). 참고: 첫 결산 2010-12-31 연결 총자산 810,677,928천원(K-IFRS 재작성, CJ E&M 2011 사업보고서), 합병 6사 단순합산 1,691,841백만원(2010-09-30, 증권발행실적보고서 '합병 후' 개략 연결) | AO8: 계산: 21.51 (102,591백만원 ÷ 오미디어홀딩스 별도 총자산 477,015백만원, 2010-09-30). 합병 6사 단순합산 총자산(1,691,841백만원) 대비 6.06. 공시에 비율 항목 없음 | AP8: 계산: 33.97 (102,591백만원 ÷ 오미디어홀딩스 별도 자본총계 302,024백만원, 2010-09-30) | AQ8: 계산: 144,533,191,550원 (발표 직전 거래일 2010-11-15 종가 29,150원 × 발행주식 4,958,257주; 종가는 주요사항보고서 합병가액 산정표, 주식수는 증권신고서 당사회사 요약). 2010-10-15 재상장 직후라 유통 이력이 한 달뿐임 | AR8: 인수 주체 규모는 오미디어홀딩스 2010-09-30 별도 재무(증권신고서 20101202000223, 증권발행실적보고서 20110310000585), 거래금액은 합병가액 29,150원 × 대상회사별 합병신주(합병기일 주식수 × 합병비율, 단주 버림, 계산). 합병 주요사항보고서(20101116000288)에는 총자산·자기자본 대비 항목이 없어 직접 계산함. 합병 후 CJ E&M 규모(6사 단순합산 1,691,841백만원) 대비 비율도 함께 적음 | AS8: KRX:130960 | AT8: 인수 주체 오미디어홀딩스=CJ E&M(코스닥 130960, 2018-07 CJ오쇼핑 합병으로 상장폐지돼 Yahoo Finance 시세 없음). 2010-11-16 장 마감 후 공시·16:24 거래정지·11-17 휴장, 2010-11-18 재개라 첫 반응일은 2010-11-18. 대상 씨제이엔터테인먼트는 비상장. 그룹 지주회사 CJ㈜(KRX:001040)도 함께 볼 수 있음 | AU8: 2010-11-16 장 마감 후: DART 회사합병결정·주요사항보고서(합병결정)·각 소멸회사 회사합병결정 공시와 CJ그룹 발표(이투데이 입력 16:14). 오미디어홀딩스 주권은 16:24 우회상장 여부 확인을 이유로 매매거래정지 후 2010-11-18 재개(우회상장 미해당), CJ인터넷(16:20)·엠넷미디어(16:22) 주권은 당일 장 종료까지만 정지. 발표 전 관련 조회공시·사전 보도는 찾지 못함(2010-09~11 공시 목록, 웹 검색 2회) | AV8: 2000-04: 구 씨제이엔터테인먼트㈜가 ㈜제일제당 영화사업부를 영업양수(2010 합병 증권신고서 연혁표); 2006-04: 구 CJ엔터테인먼트에서 물적분할로 설립(CJ㈜ 100%, C001); 2006-12: <타짜> 685만; 2007-08: <화려한 휴가> 730만·<트랜스포머> 750만; 2008-08: <좋은놈 나쁜놈 이상한놈> 688만; 2009-08: <해운대> 1,152만; 2009-11: 일본 T-JOY와 합작 선포; 2009-12: 합법 다운로드 업체 엠바로 설립; 2010-04: 일본 합작법인 CJEJ 설립; 2010-10-25: 삼일회계법인과 합병가액 평가 계약; 2009→2010: 매출 166,147→163,080백만원, 영업이익 9,722→8,329백만원 | AW8: 2010-12-30: 양사 주총 합병 승인·오미디어홀딩스 CJ E&M으로 상호 변경; 2011-03-01: 합병, CJ E&M 영화사업부문(대표 김정아); 2011: 영화부문 매출 166,784·영업이익 5,834백만원(3~12월); 2012: 218,960·9,220백만원; 2014: 공연 분리 후 영화 211,318·-3,975백만원; 2015: CJ E&M 판권 손상 95,154백만원(방송·영화 판권); 2016: 영화 189,551·-23,874백만원; 2017: 198,667·-9,044백만원; 2018-07-01: CJ오쇼핑이 CJ E&M 흡수합병, CJ ENM 출범; 2024: CJ ENM 영화드라마사업부문 매출 1,704,683백만원·영업손실 26,925백만원(스튜디오드래곤·Fifth Season 포함) | AX8: 해당 없음 (이 합병으로 영업권·투자주식 미인식: CJ E&M 2011 사업보고서 — '지배회사인 CJ 주식회사의 동일 지배 하에 있는 종속회사 간 합병'으로 피합병법인 자산·부채를 장부금액으로 승계, 합병대가와 순자산 차이는 자본잉여금에 가감). 후속 사업 수준 참고: CJ E&M 2015년 판권 손상차손 95,154백만원(2015 사업보고서 무형자산 주석 '판권 중 미래현금흐름의 발생가능성이 높지 않은 판권'; 영화·방송 등 부문별 귀속은 공시되지 않음), 2014년 판권 손상 7,556,919천원·ImaginAsian 영업권 손상 3,072,325천원(2015 사업보고서 무형자산 주석 전기 표). CJ E&M 2015 사업보고서 영업권 손상검사 가정 표의 CGU는 방송사업부문·음악사업부문 등이며 영화부문은 없음 | AY8: 동일지배 합병·그룹 내 이전으로 새 영업권·투자주식 평가가 생기지 않음 | AZ8: 2009: 166,147,408,998원; 2010: 163,080,002,913원 (씨제이엔터테인먼트 별도) | BA8: 2011(합병 후 3~12월): 166,784백만원; 2012: 218,960백만원 (CJ E&M 연결 영화부문); 최근: 2017 198,667백만원(CJ E&M 마지막 연도), CJ ENM 영화드라마사업부문 2024 1,704,683백만원(드라마 제작·해외 스튜디오 포함으로 범위 다름) | BB8: 2009: 9,721,771,839원; 2010: 8,329,368,008원 (씨제이엔터테인먼트 별도) | BC8: 2011: 5,834백만원; 2012: 9,220백만원 (CJ E&M 영화부문); 최근: 2017 -9,044백만원, CJ ENM 영화드라마 2024 -26,924,539천원 | BD8: 인수 전: 씨제이엔터테인먼트 별도·K-GAAP·12월 결산 감사보고서(2010 감사보고서 20110331003203, 2009는 같은 보고서 전기). 인수 후: 2011-03-01 소멸해 CJ E&M 연결 '영화부문'(K-IFRS, 사업보고서 사업부문별 요약 연결재무현황; 2011년은 합병소멸법인 1~2월 제외, 2011~2013 공연 일부는 음악/공연부문)으로 대신하고, 최근 연도는 CJ ENM '영화드라마사업'(2024 사업보고서 영업부문 주석)을 참고로 적음 — 2016년 스튜디오드래곤 분할·2022년 Fifth Season 인수 등으로 범위가 달라 직접 비교 불가 | BE8: 2011-02-28 출범(뉴스토마토): 영화부문은 '투자·배급 중심에서 제작 역량 강화로 재편', 2015년 매출 중 영화 비중 17% 목표; 2011 사업보고서(MD&A): 영화부문 '배급사별 관객 점유율에서 지난 수년간 지속적으로 시장점유율 1위', 매출 1,668억원; 2013-02-06(아이뉴스24): 2012년 영화 매출 2,190억원, 매출·영업이익 각각 14%·109% 증가(흥행작·VOD 부가판매). 어닝콜 녹취록은 찾지 못함 | BF8: 완료 | BG8: 2026-10-26
A9: C006 | B9: CJ ENM | C9: 2010-11-16 | D9: CJ Internet Corp. | E9: 14 | F9: True | G9: C005 | H9: MA④ | I9: MA④ | J9: 같음 | K9: 해당 없음 | L9: 일치 | M9: 편입 후 | N9: Closed | O9: 293.91 | P9: CJ E&M Corporation | Q9: CJ Corporation (KOSE:A001040) | R9: O Media Holdings Co., Ltd. (KOSE: A130960) signed a statuary merger agreement to acquire CJ Internet Corp. (KOSE: A037150) from CJ Corp. (KOSE: A001040) and others for approximately KRW 320 billion in stock on November 16, 2010. The exchange ratio for the transaction is 1: 0.4767753. O Media Holdings Co., Ltd. will survive and CJ Internet Corp. will be dissolved on closing of the transaction. O Media Holdings Co., Ltd. also signed agreement to acquire remaining 44.83% stake in On Media Corp. (KOSE: A045710), M-net Media Corp, CJ Media Inc. and CJ Entertainment Inc. The deal is subject to approval of shareholders of O Media Holdings Co., Ltd. The deal is expected to close on March 1, 2011. Morgan Stanley acted as financial advisor to CJ E&M Corporation. | S9: Gaming & Sport | T9: Game Development / Operating | U9: MA-2 그룹 내부 재편 | W9: MA④ 그룹 내부 재편 | Y9: False | Z9: MA④ 그룹 내부 재편 | AA9: 편입 후 (CJ ENM 전신 계보: ㈜오미디어홀딩스(2010-12-30 씨제이이앤엠㈜으로 상호 변경, 이 합병의 존속법인 CJ E&M 자체), 2018 CJ ENM 계보로 합병 — 2018-07-01 ㈜씨제이오쇼핑이 씨제이이앤엠㈜을 흡수합병하고 ㈜씨제이이엔엠으로 사명 변경, 증권발행실적보고서 20180702000188). 참고: 거래 당시 매수자는 CJ㈜가 최대주주(39.94%)인 CJ 계열 코스닥 상장사로, 현 CJ ENM 법인(당시 CJ오쇼핑)의 종속회사는 아니었음(2010-09-15 CJ오쇼핑 미디어사업 투자부문에서 인적분할된 자매회사). 대상 CJ인터넷은 2004-04 CJ㈜가 최대주주가 된 CJ㈜ 종속회사(발표 당시 CJ㈜ 27.45%)로 이 합병(2011-03-01)으로 CJ E&M에 편입 | AB9: 완료 (2011-03-01 합병기일; 2011-03-03 합병·해산등기, 합병신주 32,971,307주 2011-03-21 교부·2011-03-22 상장 예정 — 증권발행실적보고서) | AC9: 316,891,952,850원 (계산: CJ인터넷 합병기일 발행주식 22,801,263주 × 0.4767753 = 합병신주 약 10,871,079주 × 오미디어홀딩스 합병가액 29,150원; 단주는 현금 정산; 피합병회사 자기주식에도 합병신주 배정 — 증권발행실적보고서). 이 중 CJ 계열(CJ㈜ 7,458,307주·이재현 837,652주·임원·자기주식, 합계 8,432,860주·36.98%) 몫을 뺀 외부주주 몫(14,368,403주, 63.02%)은 합병신주 약 6,850,499주, 199,692백만원(계산). 주식매수청구 4,420주(13,674원) | AD9: 원자료와 일치 (293.91; 공시 기준 316,892백만원 = 278.4백만 달러, Yahoo Finance KRW=X 2010-11-16 종가 1,138.10원/달러, 차이 5.3%). 외부주주 몫만 보면 199,692백만원 = 175.5백만 달러 | AE9: 2010-11-16 | AF9: 기준 분류 유지(MA④): 매수자 오미디어홀딩스(CJ㈜ 39.94%)와 최대주주 매도자 CJ㈜(32.71%)가 CJ그룹 회사이고, CJ E&M 2011 사업보고서도 이 합병을 'CJ 주식회사의 동일 지배 하에 있는 종속회사 간 합병'으로 처리. 다만 CJ인터넷 주식의 63%는 그룹 밖 공모주주(Templeton 6.37%, 방준혁 5.08% 등)라 대가의 약 63%가 외부로 나간 거래 — 그룹 관점에서는 상장 종속회사의 소수지분 흡수(MA② 성격)도 겸함. 원자료 buyers 'CJ E&M Corporation'은 당시 ㈜오미디어홀딩스(00838421, 2010-12-30 씨제이이앤엠㈜으로 상호 변경). 설명란 비율 1:0.4767753, 'approximately KRW 320 billion'은 공시와 맞음(316,892백만원). sellers 'CJ Corporation ... and others'의 others는 공모 소수주주. 같은 날 C005·C007·C008·C009와 한 합병 계약의 대상회사별 행 | AG9: CJ인터넷(DART 00248691, 코스닥 037150, 옛 플레너스)은 1982년 동보강업으로 설립, 1999-12 코스닥, 2001 시네마서비스 인수·손노리 합병, 2003-09 넷마블 흡수합병(최대주주 방준혁), 2004-04 최대주주가 CJ㈜로 바뀌고 2004-07 CJ그룹 편입·상호 변경. 구 CJ엔터테인먼트도 2005-09 CJ인터넷 9.53%를 가졌고 2006-04 CJ㈜가 직접 보유(C001). 2010년 CJ인터넷은 게임하이 인수를 추진했으나 2010-05 넥슨이 인수(조회공시 답변). CJ㈜는 합병 발표 전후 장내 매수로 지분을 27.45%→31.58%(2010-11-30)→32.71%(2011-01-27)로 늘림. 합병 후 게임은 CJ E&M 게임사업부문(넷마블, 대표 남궁훈) → 2011-11 게임개발 자회사 관리부문 물적분할(CJ게임즈) → 2014-08 게임사업부문 물적분할(씨제이넷마블)·CJ게임즈에 매각, 같은 달 구조개편 완료로 CJ E&M 연결에서 빠져 지분법 관계기업이 됨 → 2014-10 넷마블게임즈 출범. 따라서 인수 후 실적은 2011~2013 CJ E&M 게임부문, 이후는 관계기업 넷마블의 실적으로만 추적 가능. 어닝콜 녹취록은 찾지 못해 earnings_call_note는 실적 발표 기사·사업보고서 MD&A로 대신함 | AH9: ㈜오미디어홀딩스 (O Media Holdings Co., Ltd., DART 00838421, 코스닥 130960; 2010-09-15 ㈜씨제이오쇼핑의 미디어사업 투자부문이 인적분할돼 설립된 순수지주회사로 자회사 온미디어 55.17% 보유, 최대주주 CJ㈜ 39.94%(2010-11-16)→45.38%(2011-01-27); 2010-12-30 씨제이이앤엠㈜(CJ E&M)으로 상호 변경 — 합병 존속법인이 곧 CJ E&M) | AI9: "경영효율성을 증대시키고 엔터테인먼트사업(영화, 음악, 게임)과 미디어사업을 통합하여 시너지 효과를 극대화하고 규모의 경제를 갖추어 세계적 회사로 성장하기 위하여 합병하기로 결정함" (회사합병결정 공시 합병목적) / "① OSMU(One-Source-Multi-Use) 실현 가능 ② 광고 영업 효율화, 구매력 강화, 시너지 마케팅 활성화 ③ 세계시장 진출을 위한 규모의 경제 확보, 대규모 / 지속가능한 투자여력 확보" (주요사항보고서 예상 시너지) / "그룹이 목표로 하고 있는 콘텐츠 사업의 글로벌화와 계열사간 시너지 극대화를 위해 합병을 결정하게 됐다" (CJ 측, 이투데이 2010-11-16) | AJ9: 순수지주회사 — 자회사 ㈜온미디어(55.17%, 투니버스·OCN 등 케이블 방송채널사용사업자) 지분만 보유하고 영업수익은 지분법이익(증권신고서 투자위험요소 '순수지주회사로 영업수익은 지분법이익으로 구성'), 임직원 10명(2010-11 기준). 실질 사업은 온미디어의 케이블 PP: 2009년 온미디어 별도 매출 67,746백만원·자산 449,318백만원 | AK9: 비핵심 | AL9: 인수 주체의 실질 사업(온미디어 케이블 PP)과 온라인 게임 포털·퍼블리싱은 다른 영역. 온미디어가 게임채널 온게임넷을 운영해 고객군이 일부 겹치지만 사업은 별개라 비핵심으로 판단. 그룹 정점 CJ ENM 기준으로도 게임은 2014년 분리돼 현재 사업 부문에 없는 비핵심 영역(지분법 투자로만 남음) | AM9: 477,015백만원 (오미디어홀딩스 별도, 2010-09-30; 증권신고서 당사회사 요약·증권발행실적보고서 합병 전 요약재무). 설립 개시재무상태표(2010-09-01) 474,852,301,036원. 참고: 2010-12-31 별도 473,527,264,185원, 연결(K-IFRS) 810,677,928천원 | AN9: acq_total_assets와 같음 (인수 주체 오미디어홀딩스=CJ E&M이 상장 지배회사 자신; 2010-09-15 설립이라 직전 회계연도말이 없음). 참고: 첫 결산 2010-12-31 연결 총자산 810,677,928천원(K-IFRS 재작성, CJ E&M 2011 사업보고서), 합병 6사 단순합산 1,691,841백만원(2010-09-30, 증권발행실적보고서 '합병 후' 개략 연결) | AO9: 계산: 66.43 (316,892백만원 ÷ 오미디어홀딩스 별도 총자산 477,015백만원, 2010-09-30). 합병 6사 단순합산 총자산(1,691,841백만원) 대비 18.73. 공시에 비율 항목 없음 | AP9: 계산: 104.92 (316,892백만원 ÷ 오미디어홀딩스 별도 자본총계 302,024백만원, 2010-09-30) | AQ9: 계산: 144,533,191,550원 (발표 직전 거래일 2010-11-15 종가 29,150원 × 발행주식 4,958,257주; 종가는 주요사항보고서 합병가액 산정표, 주식수는 증권신고서 당사회사 요약). 2010-10-15 재상장 직후라 유통 이력이 한 달뿐임 | AR9: 인수 주체 규모는 오미디어홀딩스 2010-09-30 별도 재무(증권신고서 20101202000223, 증권발행실적보고서 20110310000585), 거래금액은 합병가액 29,150원 × 대상회사별 합병신주(합병기일 주식수 × 합병비율, 단주 버림, 계산). 합병 주요사항보고서(20101116000288)에는 총자산·자기자본 대비 항목이 없어 직접 계산함. 합병 후 CJ E&M 규모(6사 단순합산 1,691,841백만원) 대비 비율도 함께 적음 | AS9: KRX:130960 | AT9: 인수 주체 오미디어홀딩스=CJ E&M(코스닥 130960, 2018-07 상장폐지라 Yahoo Finance 시세 없음; 2010-11-16 16:24 거래정지, 2010-11-18 재개). 대상 CJ인터넷도 코스닥 상장사(KRX:037150): 2010-11-15 종가 13,950원, 시가총액 계산 318,077,618,850원(22,801,263주); 2010-11-16 16:20~장 종료 거래정지라 첫 반응일 2010-11-17; 2011-02-22 구주권 제출로 거래정지 후 소멸. 037150도 Yahoo Finance에 시세 없음 | AU9: 2010-11-16 장 마감 후: DART 회사합병결정·주요사항보고서(합병결정)·각 소멸회사 회사합병결정 공시와 CJ그룹 발표(이투데이 입력 16:14). 오미디어홀딩스 주권은 16:24 우회상장 여부 확인을 이유로 매매거래정지 후 2010-11-18 재개(우회상장 미해당), CJ인터넷(16:20)·엠넷미디어(16:22) 주권은 당일 장 종료까지만 정지. 발표 전 관련 조회공시·사전 보도는 찾지 못함(2010-09~11 공시 목록, 웹 검색 2회) | AV9: 1982-10: 동보강업 설립; 1999-12: 코스닥 등록; 2001-01: 시네마서비스 인수; 2003-09: 넷마블 흡수합병(게임포털 진출); 2004-04: 최대주주 방준혁→CJ㈜; 2004-07: CJ그룹 편입, 씨제이인터넷으로 상호 변경; 2005~2006: 애니파크·게임알로 출자, CJ인터넷재팬 경영권 확보; 2008-12: CJ스포츠 지분 인수; 2010-02: 씨드나인엔터테인먼트, 2010-03: 미디어웹 지분 인수; 2010-02~05: 게임하이 인수 추진(넥슨이 인수해 종료); 2010-03: 대표 남궁훈; 2009→2010: 별도 매출 220,575→227,454백만원, 영업이익 47,165→36,639백만원 | AW9: 2010-12-30: 주총 합병 승인; 2011-03-01: 합병, CJ E&M 게임사업부문(넷마블); 2011-07: '서든어택' 넥슨 공동 퍼블리싱 계약으로 매출 차질; 2011-11-13: 게임개발 자회사 관리부문 물적분할(씨제이게임즈); 2012: 게임부문 매출 212,084백만원·영업손실 6,497백만원; 2013: 매출 496,789·영업이익 66,678백만원; 2013-11~2014-02: 게임사업 매각설 조회공시에 '매각은 계획하고 있지 않습니다'·CJ게임즈 투자유치 검토 답변; 2014-03: 게임사업부문과 CJ게임즈의 통합 및 중국 텐센트 투자유치 계약 체결; 2014-08-01: 게임사업부문 물적분할(씨제이넷마블), 같은 달 CJ게임즈에 100% 매각(처분결정 당시 예상금액 353,730,188,079원); 2014-08: 구조개편 완료로 CJ게임즈·씨제이넷마블 등 게임 종속회사 20개사가 CJ E&M 연결에서 제외(지분법 관계기업으로 전환), 게임 손익은 중단사업(2014 CJ E&M 연결 중단사업이익 290,356백만원); 2014-10-01: 씨제이게임즈가 씨제이넷마블을 흡수합병해 넷마블게임즈로 출범, CJ그룹에서 분리 독립(넷마블 연혁); 2017-04-29: 넷마블게임즈 유가증권시장 상장 목적 일반공모 유상증자 16,953,612주, 같은 해 상장 — 불균등 증자로 CJ E&M 지분 27.63%(2016년말)→22.02%(2017년말), 지분율 하락 처분이익 500,703백만원; 2018-07: CJ ENM 출범; 2024: CJ ENM 넷마블 지분 17.60%(2023년말 22.85%, 2024년 일부 처분), 넷마블 2024 매출 2,663,783백만원·영업이익 215,627백만원 | AX9: 해당 없음 (이 합병으로 영업권 미인식: CJ E&M 2011 사업보고서 — 동일지배 합병, CJ㈜ 연결 장부금액 승계, 차액은 자본잉여금). 후속 사업 수준 참고: CJ E&M 2013년 무형자산 손상차손 30,617,039천원(이 중 개발비 22,546,905천원·영업권 957,306천원; 추정: 개발비 손상은 게임 개발비로 보임 — CJ E&M 2014 사업보고서 무형자산 주석 전기 표, 부문 귀속은 공시되지 않음). 2014-08 게임사업 구조개편으로 지배력을 상실해 게임 손익은 중단사업으로 분류, 2014 CJ E&M 연결 중단사업이익 290,356백만원(손상이 아닌 이익이며 처분이익만 따로 떼어 확인하지는 못함 — 2014 사업보고서 요약재무) | AY9: 동일지배 합병·그룹 내 이전으로 새 영업권·투자주식 평가가 생기지 않음 | AZ9: 2009: 220,575,264,120원; 2010: 227,454,036,533원 (CJ인터넷 별도) | BA9: 2011(합병 후 3~12월): 208,115백만원; 2012: 212,084백만원 (CJ E&M 연결 게임부문); 2013: 496,789백만원(게임부문 마지막 전체 연도); 최근: 2014-08 분리 후 관계기업 넷마블(주) 2024 매출 2,663,783,170천원(CJ ENM 지분 17.60%) | BB9: 2009: 47,164,554,291원; 2010: 36,639,427,514원 (CJ인터넷 별도) | BC9: 2011: 17,755백만원; 2012: -6,497백만원; 2013: 66,678백만원 (CJ E&M 게임부문); 최근: 넷마블 2024 영업이익 215,627,215천원(2023 -69,000,730천원) | BD9: 인수 전: CJ인터넷 별도·K-GAAP·12월 결산 감사보고서(2010 감사보고서 20110331003138; 연결 기준 2008 매출 206,426·영업이익 40,891백만원은 2010 증권신고서 요약연결). 인수 후: 2011-03-01 소멸해 CJ E&M 연결 '게임부문'(K-IFRS, 사업보고서 사업부문별 요약 연결재무현황; 2011년은 1~2월 제외, 2012년부터 온라인 사업 일부 재분류)으로 대신함. 2014-08 게임 부문 분할·매각 뒤에는 CJ E&M/CJ ENM의 관계기업 넷마블(주) 전체 실적(CJ ENM 2024 사업보고서 관계기업 요약재무, 천원)으로만 추적 가능 — 넷마블은 이후 대형 인수(넷마블 자체 M&A)가 섞여 CJ인터넷 사업과 직접 비교 불가 | BE9: 2011-02-28 출범(뉴스토마토): 2015년 매출 중 게임 29% 목표, 게임부문 대표 남궁훈(전 CJ인터넷 대표); 2011 사업보고서(MD&A): 게임부문 '2011년 7월 서든어택이 넥슨과의 공동 퍼블리싱 계약 체결, 신규 게임의 완성도 집중 전략에 의한 론칭 일정 지연 등의 차질이 발생되며, 매출 2,081억원'; 2013-02-06(아이뉴스24): 2012년 게임 매출 2,121억원, 18% 감소 — 온라인게임 경쟁 심화·서든어택 계약 변경·신작 연기, 회사는 모바일게임으로 회복 기대; 2013-11-11 조회공시 답변: '당사는 게임사업부문에 대한 매각은 계획하고 있지 않습니다'; 2014-05-15 분할결정 분할목적 '게임사업력을 집약해 빠르게 성장하는 글로벌 시장에 적극적으로 대응'. 어닝콜 녹취록은 찾지 못함 | BF9: 완료 | BG9: 2026-10-26
A10: C007 | B10: CJ ENM | C10: 2010-11-16 | D10: CJ Media Inc. | E10: 28 | F10: True | G10: C005 | H10: MA④ | I10: MA④ | J10: 같음 | K10: 해당 없음 | L10: 일치 | M10: 편입 후 | N10: Closed | O10: 112.1 | P10: CJ E&M Corporation | Q10: CJ Corporation (KOSE:A001040) | R10: O Media Holdings Co., Ltd. (KOSE: A130960) signed a statuary merger agreement to acquire CJ Media Inc. from CJ Corp. (KOSE: A001040) and others for approximately KRW 130 billion in stock on November 16, 2010. The exchange ratio for the transaction is 1: 0.9471698. O Media Holdings Co., Ltd. will survive and CJ Media Inc. will be dissolved on closing of the transaction. O Media Holdings Co., Ltd. also signed agreement to acquire remaining 44.83% stake in On Media Corp. (KOSE: A045710), M-net Media Corp, CJ Internet Corp. and CJ Entertainment Inc. For the year ended December 31, 2009, total assets of KRW 223.4 billion, total shareholders' equity of KRW 83.4 billion, operating revenue of KRW 152.5 billion and operating loss of KRW 6.8 billion were reported for CJ Media Inc. The deal is subject to approval of shareholders of O Media Holdings Co., Ltd. The deal is expected to close on March 1, 2011. Sang Gon Kim and Jun Taek Lee of Lee & Ko acted as legal advisors for O Media Holdings Co., Ltd. and CJ Media Inc. Gene Park and Craig Oh of WOORI Investment & Securities Co. Ltd. and Morgan Stanley acted as financial advisor for O Media Holdings Co., Ltd. Hyundai Securities Co., Ltd. acted as financial advisor for CJ Corp. | S10: Media Platforms | T10: Broadcasting Channel | U10: MA-2 그룹 내부 재편 | W10: MA④ 그룹 내부 재편 | Y10: False | Z10: MA④ 그룹 내부 재편 | AA10: 편입 후 (CJ ENM 전신 계보: ㈜오미디어홀딩스(2010-12-30 씨제이이앤엠㈜으로 상호 변경, DART 00838421), 2018 CJ ENM 계보로 합병 — 2018-07-01 ㈜CJ오쇼핑이 CJ E&M을 흡수합병해 현 CJ ENM이 됨. 거래 당시 매수자는 2010-09-01 분할기일로 ㈜CJ오쇼핑의 투자사업부문(온미디어 지분 등)이 인적분할돼 2010-09-15 설립된 코스닥 상장사(CJ㈜ 39.94%, CJ오쇼핑 3.00%, 주요사항보고서 20101116000288)이고, 대상 씨제이미디어는 CJ㈜ 49.93%(특수관계 포함 60.39%)의 CJ㈜ 종속회사로 이 합병(2011-03-01)으로 CJ E&M 계보에 들어옴. 참고: 현 CJ ENM 법인(옛 CJ오쇼핑, 00265324)의 연결 종속회사가 된 시점은 2018-07-01 합병) | AB10: 완료 (2011-03-01 합병기일; 2011-03-03 합병·해산등기, 합병신주 32,971,307주 2011-03-21 교부·2011-03-22 상장 예정 — 증권발행실적보고서) | AC10: 127,005,996,150원 (계산: 씨제이미디어 4,600,000주 × 0.9471698 = 합병신주 약 4,356,981주 × 합병가액 29,150원; = 주당 합병가액 27,610원 × 4,600,000주 127,006,000,000원). 이 중 CJ 계열(CJ㈜ 2,296,611주·에스에이관리·이재현 일가·임원·자기주식, 합계 2,779,092주·60.42%) 몫을 뺀 외부주주 몫(1,820,908주, 39.58%; 신한국민연금제일호PEF 16.59%·프리모리스PEF 9.98%·이민주 9.62% 등)은 합병신주 약 1,724,709주, 50,275백만원(계산). 주식매수청구 1,347주(27,610원) | AD10: 원자료와 일치 (112.1; 공시 기준 127,006백만원 = 111.6백만 달러, Yahoo Finance KRW=X 2010-11-16 종가 1,138.10원/달러). 외부주주 몫만 보면 50,275백만원 = 44.2백만 달러 | AE10: 2010-11-16 | AF10: 기준 분류 유지(MA④): 매수자 오미디어홀딩스(CJ㈜ 39.94%)와 최대주주 매도자 CJ㈜(49.93%)가 모두 CJ그룹 회사이고, CJ E&M은 이 합병을 동일지배 종속회사 간 합병으로 회계처리. 지분 약 40%는 2007-01 투자한 사모펀드 등 외부주주 몫이라 그룹 관점에서는 소수지분 흡수(MA② 성격)도 겸함. 원자료 설명란 정정: (1) 'For the year ended December 31, 2009, total assets of KRW 223.4 billion, total shareholders' equity of KRW 83.4 billion'은 2009년말이 아니라 2010-10-01 분할 신설 씨제이미디어 개시재무상태표 값(자산 223,432,714,723원, 자본 83,440,695,375원). (2) 같은 문장의 2009년 매출 152.5bn·영업손실 6.8bn은 분할 전 구 씨제이미디어(현 에스에이관리) 회사 전체 값(매출 152,540,415,425원·영업손실 6,801,389,389원)으로, 합병된 방송사업만의 2009년 실적은 매출 152,323,284,941원·영업이익 3,314,568,853원(에스에이관리 2010 감사보고서 중단사업 주석). (3) 'approximately KRW 130 billion', 비율 1:0.9471698은 공시와 맞음. 원자료 buyers 'CJ E&M Corporation'은 당시 ㈜오미디어홀딩스. 같은 날 C005·C006·C008·C009와 한 합병 계약의 대상회사별 행 | AG10: 대상은 2010-10-01 구 씨제이미디어(DART 00197263, 1993년 뮤직네트워크로 설립)가 방송미디어 사업부문(종합유선방송 프로그램 공급, 프로그램·영상물 제작·판매)을 인적분할해 세운 신설 씨제이미디어(DART 00841452; tvN·채널CGV·XTM·O'live 등 PP)이고, 판권 재판매 사업을 남긴 존속법인은 에스에이관리㈜로 상호 변경(2012-09-20 주총 해산 결의, 청산 — 해산사유발생 공시). 즉 합병 발표 6주 전 방송사업만 떼어 낸 뒤 합병시킨 구조. 합병가액 27,610원은 비상장이라 삼일회계법인 본질가치(자산가치 17,798원·수익가치 34,152원)로 산정. 합병 후 CJ E&M 방송사업부문(대표 김성수, 온미디어 채널과 엠넷미디어의 Mnet·KM 채널도 함께)이 되어 대상 단독 실적은 따로 공시되지 않음 — 인수 후 실적은 방송부문 전체(온미디어 C009, 엠넷 채널 포함)로만 추적 가능. 어닝콜 녹취록은 찾지 못해 earnings_call_note는 실적 발표 기사·사업보고서 MD&A로 대신함 | AH10: ㈜오미디어홀딩스 (O Media Holdings Co., Ltd., DART 00838421, 코스닥 130960; 2010-09-15 ㈜씨제이오쇼핑의 미디어사업 투자부문이 인적분할돼 설립된 순수지주회사로 자회사 온미디어 55.17% 보유, 최대주주 CJ㈜ 39.94%(2010-11-16)→45.38%(2011-01-27); 2010-12-30 씨제이이앤엠㈜(CJ E&M)으로 상호 변경 — 합병 존속법인이 곧 CJ E&M) | AI10: "경영효율성을 증대시키고 엔터테인먼트사업(영화, 음악, 게임)과 미디어사업을 통합하여 시너지 효과를 극대화하고 규모의 경제를 갖추어 세계적 회사로 성장하기 위하여 합병하기로 결정함" (회사합병결정 공시 합병목적) / "① OSMU(One-Source-Multi-Use) 실현 가능 ② 광고 영업 효율화, 구매력 강화, 시너지 마케팅 활성화 ③ 세계시장 진출을 위한 규모의 경제 확보, 대규모 / 지속가능한 투자여력 확보" (주요사항보고서 예상 시너지) / "그룹이 목표로 하고 있는 콘텐츠 사업의 글로벌화와 계열사간 시너지 극대화를 위해 합병을 결정하게 됐다" (CJ 측, 이투데이 2010-11-16) | AJ10: 순수지주회사 — 자회사 ㈜온미디어(55.17%, 투니버스·OCN 등 케이블 방송채널사용사업자) 지분만 보유하고 영업수익은 지분법이익(증권신고서 투자위험요소 '순수지주회사로 영업수익은 지분법이익으로 구성'), 임직원 10명(2010-11 기준). 실질 사업은 온미디어의 케이블 PP: 2009년 온미디어 별도 매출 67,746백만원·자산 449,318백만원 | AK10: 핵심 | AL10: 인수 주체의 실질 사업(자회사 온미디어의 케이블 방송채널사용사업: OCN·투니버스 등)과 씨제이미디어의 사업(tvN·채널CGV 등 케이블 PP)이 같은 영역 — 합병 공시가 기대한 '광고 영업 효율화, 구매력 강화'도 같은 PP 사업 통합에서 나옴. 그룹 정점 CJ ENM 기준으로도 방송채널은 현 미디어플랫폼 부문의 전신이라 핵심 | AM10: 477,015백만원 (오미디어홀딩스 별도, 2010-09-30; 증권신고서 당사회사 요약·증권발행실적보고서 합병 전 요약재무). 설립 개시재무상태표(2010-09-01) 474,852,301,036원. 참고: 2010-12-31 별도 473,527,264,185원, 연결(K-IFRS) 810,677,928천원 | AN10: acq_total_assets와 같음 (인수 주체 오미디어홀딩스=CJ E&M이 상장 지배회사 자신; 2010-09-15 설립이라 직전 회계연도말이 없음). 참고: 첫 결산 2010-12-31 연결 총자산 810,677,928천원(K-IFRS 재작성, CJ E&M 2011 사업보고서), 합병 6사 단순합산 1,691,841백만원(2010-09-30, 증권발행실적보고서 '합병 후' 개략 연결) | AO10: 계산: 26.63 (127,006백만원 ÷ 오미디어홀딩스 별도 총자산 477,015백만원, 2010-09-30). 합병 6사 단순합산 총자산(1,691,841백만원) 대비 7.51. 공시에 비율 항목 없음 | AP10: 계산: 42.05 (127,006백만원 ÷ 오미디어홀딩스 별도 자본총계 302,024백만원, 2010-09-30) | AQ10: 계산: 144,533,191,550원 (발표 직전 거래일 2010-11-15 종가 29,150원 × 발행주식 4,958,257주; 종가는 주요사항보고서 합병가액 산정표, 주식수는 증권신고서 당사회사 요약). 2010-10-15 재상장 직후라 유통 이력이 한 달뿐임 | AR10: 인수 주체 규모는 오미디어홀딩스 2010-09-30 별도 재무(증권신고서 20101202000223, 증권발행실적보고서 20110310000585), 거래금액은 합병가액 29,150원 × 대상회사별 합병신주(합병기일 주식수 × 합병비율, 단주 버림, 계산). 합병 주요사항보고서(20101116000288)에는 총자산·자기자본 대비 항목이 없어 직접 계산함. 합병 후 CJ E&M 규모(6사 단순합산 1,691,841백만원) 대비 비율도 함께 적음 | AS10: KRX:130960 | AT10: 인수 주체 오미디어홀딩스=CJ E&M(코스닥 130960, 2018-07 상장폐지라 Yahoo Finance 시세 없음; 2010-11-16 16:24 거래정지, 2010-11-18 재개). 대상 씨제이미디어는 비상장. 그룹 지주회사 CJ㈜(KRX:001040)도 함께 볼 수 있음 | AU10: 2010-11-16 장 마감 후: DART 회사합병결정·주요사항보고서(합병결정)·각 소멸회사 회사합병결정 공시와 CJ그룹 발표(이투데이 입력 16:14). 오미디어홀딩스 주권은 16:24 우회상장 여부 확인을 이유로 매매거래정지 후 2010-11-18 재개(우회상장 미해당), CJ인터넷(16:20)·엠넷미디어(16:22) 주권은 당일 장 종료까지만 정지. 발표 전 관련 조회공시·사전 보도는 찾지 못함(2010-09~11 공시 목록, 웹 검색 2회) | AV10: 1993-09: ㈜뮤직네트워크 설립; 1997-04: 제일제당그룹 경영권 인수; 2002-07: 씨제이미디어로 상호 변경; 2003-10: XTM 개국; 2005-12: 채널CGV; 2006-09: Mnet 사업부문을 CJ뮤직에 양도(C003 선행); 2006-10: tvN 개국; 2007-01: 투자전문기관 700억원 자본유치; 2007-03: MPP 1위(시청점유율); 2009-08·09: 썬티브이·CJ파워캐스트 매각; 2009-11: tvN 법인 흡수합병; 2010-07-26: 방송사업 인적분할 이사회 결의; 2010-10-01: 방송사업 인적분할로 신설 씨제이미디어 설립(존속 에스에이관리); 2009→2010: 방송사업 매출 152,323→205,309백만원, 영업이익 3,315→18,699백만원(2010은 1~9월 구법인 중단사업 + 10~12월 신설법인, 계산) | AW10: 2010-12-30: 주총 합병 승인, 오미디어홀딩스 상호를 씨제이이앤엠㈜으로 변경; 2011-03-01: 합병, CJ E&M 방송사업부문(tvN·Mnet·OCN·채널CGV·투니버스 등; 회사 대표 하대중, 방송사업부문 대표 김성수); 2011: 방송부문 매출 635,789·영업이익 47,394백만원; 2012: 764,151·44,554백만원; 2013: 770,754·2,002백만원; 2014-03: 대표이사 강석희 → 강석희·김성수 각자대표; 2015-03: 김성수 단독대표; 2015: 판권 손상 95,154백만원; 2015-11: CJ헬로비전 OTT 티빙 영업양수 계약; 2016-05-01: 드라마사업부문 물적분할(스튜디오드래곤, 2017-11 코스닥 상장); 2017: 방송부문 매출 1,294,153·영업이익 61,822백만원; 2018-07-01: CJ ENM 출범(CJ오쇼핑의 CJ E&M 흡수합병); 2020-10: OTT 사업부문 티빙 물적분할(㈜티빙 설립); 2021-03: 대표이사 강호성; 2022-03: 대표이사 윤상현; 2022-12: ㈜티빙이 ㈜케이티시즌 합병; 2023-03: 구창근 선임(윤상현·구창근 각자대표); 2024: CJ ENM 미디어플랫폼사업(TV채널·OTT·콘텐츠 유통·광고) 매출 1,373,169·영업이익 25,978백만원; 2024-04: 윤상현 단독대표; 2025: 미디어플랫폼사업 매출 1,341,616·영업이익 1,332백만원; 2025-06-10: 공정위, 티빙·웨이브 기업결합 조건부 승인(2026-08 실적 컨퍼런스콜 기준 합병 논의 진행 중) | AX10: 해당 없음 (이 합병으로 영업권 미인식: CJ E&M 2011 사업보고서 — 동일지배 합병, CJ㈜ 연결 장부금액 승계). 후속 사업 수준 참고: CJ E&M 2015년 판권 손상차손 95,154백만원(방송·영화 판권, 2015 사업보고서 주석 15). 방송사업부문은 2015~2017 영업권 손상검사 CGU에 포함됨(2017년 CJ E&M 연결 영업권 손상 853,984천원이 있으나 현금창출단위 귀속은 공시에서 확인 못 함 — 2017 사업보고서 무형자산 주석). CJ ENM 2024년 미디어플랫폼사업부문 CGU 영업권 376,778,468천원(손상 없음; 영업권 원천에는 온미디어 인수 등이 섞임); CJ ENM 2025 연결 영업권 손상차손 19,940,683천원(현금창출단위별 귀속 미기재), 미디어플랫폼사업부문 CGU 영업권 2024말 376,778,468 → 2025말 371,615,748천원(감소 5,162,720천원의 원인은 확인 못 함; 2025 사업보고서 20260318001469 연결 주석) | AY10: 동일지배 합병·그룹 내 이전으로 새 영업권·투자주식 평가가 생기지 않음 | AZ10: 2009: 152,323,284,941원; 2010: 205,308,695,728원(계산: 1~9월 구 씨제이미디어 방송사업 140,366,956,685원 + 10~12월 신설 씨제이미디어 64,941,739,043원) — 방송사업 기준 | BA10: 2011(합병 후 3~12월): 635,789백만원; 2012: 764,151백만원 (CJ E&M 연결 방송부문, 온미디어·엠넷 채널 포함); 최근: CJ ENM 미디어플랫폼사업 2025 1,341,616,430천원(부문간 제거 후 외부매출; 2024 1,373,168,542천원). 참고: CJ E&M 마지막 연도 2017 방송부문 1,294,153백만원 | BB10: 2009: 3,314,568,853원; 2010: 18,698,962,802원(계산: 1~9월 10,847,499,866원 + 10~12월 7,851,462,936원) — 방송사업 기준. 참고: 구 씨제이미디어 회사 전체 영업손익 2009 -6,801,389,389원, 2010 1~9월 -2,512,095,919원(미감사) | BC10: 2011: 47,394백만원; 2012: 44,554백만원 (CJ E&M 방송부문); 최근: CJ ENM 미디어플랫폼사업 2025 1,332,256천원(2024 25,977,564천원). 참고: 2017 방송부문 61,822백만원 | BD10: 인수 전: 대상 신설 씨제이미디어는 2010-10-01 설립이라 자체 실적은 2010년 3개월분(감사보고서 20110401000217)뿐 — 분할 전 방송사업 실적은 존속법인 에스에이관리 2010 감사보고서(20110323000442) 주석 21 '중단사업손익'(2010-01-01~09-30 및 2009년, 감사)을 씀. 둘 다 별도·K-GAAP. 2010년 합계는 두 기간 단순합산(계산). 인수 후: CJ E&M 연결 방송부문(K-IFRS; 온미디어·엠넷미디어의 채널 포함, 2011년은 소멸법인 1~2월 제외)과 CJ ENM 미디어플랫폼사업(2024·2025 사업보고서 연결 영업부문 주석: TV채널·OTT 플랫폼·콘텐츠 유통·광고 — tvN·Mnet·OCN 채널 포함, 매출은 부문간 제거 후 외부매출, 최근 연도는 2025 사업보고서 20260318001469; 드라마 제작은 2016년부터 스튜디오드래곤으로 분리돼 영화드라마 부문) — 대상 단독 실적 아님 | BE10: 2011-02-28 출범(뉴스토마토): 방송사업부문이 CJ미디어·온미디어·엠넷미디어 채널을 통합 운영, 통합 전 방송 비중 52%를 2015년 36%로 낮추는 목표; 2011 사업보고서(MD&A): '슈퍼스타K3, 코리아갓탤런트 ... 등의 오디션 프로그램, ... 오리지널 드라마 ... 앵커프로그램 경쟁력을 통해 매출 6,358억원'; 2013-02-06(아이뉴스24): 2012년 방송 매출 7,641억원(+14%), 회사 측 '2012년 전체 방송시장이 5% 역성장한 가운데 올린 실적이라 매우 의미있는 성과'. 어닝콜 녹취록은 찾지 못함 | BF10: 완료 | BG10: 2026-10-26
A11: C008 | B11: CJ ENM | C11: 2010-11-16 | D11: M-net Media Corp | E11: 24 | F11: True | G11: C005 | H11: MA④ | I11: MA④ | J11: 같음 | K11: 해당 없음 | L11: 불일치 | M11: 편입 후 | N11: Closed | O11: 184.76 | P11: CJ E&M Corporation | Q11: CJ Corporation (KOSE:A001040); Standard Chartered Private Equity Limited; KB Investment Co., Ltd | R11: O Media Holdings Co., Ltd. (KOSE: A130960) signed a statuary merger agreement to acquire M-net Media Corp (KOSE: A056200) from CJ Corp. (KOSE: A001040) and others for approximately KRW 140 billion in stock on November 16, 2010. O Media Holdings Co., Ltd. will survive and M-net Media Corp will be dissolved on closing of the transaction. The exchange ratio for the transaction is 1: 0.0977702. O Media Holdings Co., Ltd. also signed agreement to acquire remaining 44.83% stake in On Media Corp. (KOSE: A045710), CJ Internet Corp., CJ Media Inc. and CJ Entertainment Inc. The deal is subject to approval of shareholders of O Media Holdings Co., Ltd. The deal is expected to close on March 1, 2011. | S11: Media Platforms | T11: Broadcasting Channel | U11: MA-2 그룹 내부 재편 | W11: MA④ 그룹 내부 재편 | Y11: False | Z11: MA④ 그룹 내부 재편 | AA11: 편입 후 (CJ ENM 전신 계보: ㈜오미디어홀딩스(2010-12-30 씨제이이앤엠㈜으로 상호 변경, DART 00838421), 2018 CJ ENM 계보로 합병 — 2018-07-01 ㈜CJ오쇼핑이 CJ E&M을 흡수합병해 현 CJ ENM이 됨. 거래 당시 매수자는 2010-09-01 분할기일로 ㈜CJ오쇼핑의 투자사업부문(온미디어 지분 등)이 인적분할돼 2010-09-15 설립된 코스닥 상장사(CJ㈜ 39.94%, CJ오쇼핑 3.00%, 주요사항보고서 20101116000288)이고, 대상 엠넷미디어(코스닥 056200)는 발표 당시 CJ㈜ 49.31%(합병 직전 45.21%)의 CJ㈜ 종속회사로 이 합병(2011-03-01)으로 CJ E&M 계보에 들어옴. 참고: 현 CJ ENM 법인(옛 CJ오쇼핑, 00265324)의 연결 종속회사가 된 시점은 2018-07-01 합병) | AB11: 완료 (2011-03-01 합병기일; 2011-03-03 합병·해산등기, 합병신주 32,971,307주 2011-03-21 교부·2011-03-22 상장 예정 — 증권발행실적보고서) | AC11: 185,736,687,400원 (계산: 합병기일 엠넷미디어 발행주식 65,170,746주 × 0.0977702 = 합병신주 약 6,371,756주 × 합병가액 29,150원). 발표 당시 발행주식 48,439,014주 기준으로는 합병신주 약 4,735,892주·138,051백만원(원자료 설명란 'approximately KRW 140 billion'과 일치) — 발표 뒤 BW 행사(2010-12-01)·CB 전환(2010-12-30, 2011-02-22)으로 엠넷 주식이 16,731,732주(주당 1,793원) 늘어 대가가 커짐. CJ 계열(CJ㈜ 29,462,133주 등 29,954,564주·45.97%)을 뺀 외부주주 몫(35,216,182주, 54.03%)은 합병신주 약 3,443,094주, 100,366백만원(계산). 주식매수청구 1,872주(2,966원) | AD11: 원자료와 불일치: 최종 185,737백만원 = 163.2백만 달러, 발표 당시 주식수 기준 138,051백만원 = 121.3백만 달러 (Yahoo Finance KRW=X 2010-11-16 종가 1,138.10원/달러, 계산). 원자료 184.76(같은 환율로 약 2,103억원)은 두 값과 모두 10% 넘게 다르고 원자료 설명란('KRW 140 billion')과도 맞지 않음 | AE11: 2010-11-16 | AF11: 기준 분류 유지(MA④): 매수자 오미디어홀딩스(CJ㈜ 39.94%)와 최대주주 매도자 CJ㈜(발표 당시 49.31%, 합병 직전 45.21%)가 CJ그룹 회사이고 CJ E&M은 동일지배 종속회사 간 합병으로 회계처리. 다만 대가의 약 54%는 그룹 밖 주주(2010-12-01 기준 Standard Chartered Private Equity (Mauritius) III Limited 10.33%·㈜포이보스 7.14% — 분모 54,016,258주, 증권신고서 5% 이상 주주 표; 공모주주 등)에게 감 — 그룹 관점에서 상장 종속회사 소수지분 흡수(MA② 성격)도 겸함. 원자료 sellers의 Standard Chartered Private Equity는 2009-10 발행 BW(행사가 1,793원)로 2010-12-01 5,577,244주를 받은 주주로 확인(증권신고서). KB Investment는 공시에서 확인하지 못함(2011-02-22 CB 전환 5,577,244주의 청구자는 공시에 미기재). 추정: 제3회 CB 200억원의 인수자는 CJ㈜ 100억원·SC PE 100억원(증권신고서 사채 발행내역)이고 2010-12-30 전환분이 CJ㈜ 몫(보유주식이 같은 수만큼 증가)이므로 2011-02-22 전환분은 SC PE 몫으로 보임 — 그렇다면 합병기일 SC PE 보유는 BW 행사분과 합쳐 11,154,488주(17.12%). 무기명식 사채라 양도 가능성은 배제하지 못함. 원자료 buyers 'CJ E&M Corporation'은 당시 ㈜오미디어홀딩스. 비율 1:0.0977702, 2011-03-01 완료 예정은 공시와 일치. 같은 날 C005·C006·C007·C009와 한 합병 계약의 대상회사별 행 | AG11: C003의 후속 거래: 엠넷미디어(DART 00335562, 코스닥 056200, 옛 ㈜메디오피아테크날리지)는 2007-05-31 씨제이뮤직을 흡수합병해 음반·음원·Mnet 음악채널을 갖게 된 회사(C003). 2009-10 SC PE와 CJ㈜를 통해 CB·BW 300억원 발행(BW 100억·CB 200억원, 행사·전환가 1,793원) — 합병 발표 뒤 모두 행사·전환돼 합병가액 2,850원 대비 싸게 받은 주식에도 합병신주가 배정됨. 추정: 2010-12-30 CB 전환분 5,577,244주는 CJ㈜ 몫(CJ㈜ 보유주식이 23,884,889주(2010-12-01)→29,462,133주(2011-01-27)로 같은 수만큼 증가). 합병 후 Mnet·KM 채널은 CJ E&M 방송사업부문으로, 음반·음원 유통·Mnet.com·공연은 음악/공연부문으로 나뉘어 대상 단독 실적은 공시되지 않음. 엠넷미디어 2007~2008 영업권 손상(7,684·26,944백만원, C003 참조)으로 합병 직전 자본총계가 27,956백만원(2010-09-30)에 불과했음. 어닝콜 녹취록은 찾지 못해 earnings_call_note는 실적 발표 기사·사업보고서 MD&A로 대신함 | AH11: ㈜오미디어홀딩스 (O Media Holdings Co., Ltd., DART 00838421, 코스닥 130960; 2010-09-15 ㈜씨제이오쇼핑의 미디어사업 투자부문이 인적분할돼 설립된 순수지주회사로 자회사 온미디어 55.17% 보유, 최대주주 CJ㈜ 39.94%(2010-11-16)→45.38%(2011-01-27); 2010-12-30 씨제이이앤엠㈜(CJ E&M)으로 상호 변경 — 합병 존속법인이 곧 CJ E&M) | AI11: "경영효율성을 증대시키고 엔터테인먼트사업(영화, 음악, 게임)과 미디어사업을 통합하여 시너지 효과를 극대화하고 규모의 경제를 갖추어 세계적 회사로 성장하기 위하여 합병하기로 결정함" (회사합병결정 공시 합병목적) / "① OSMU(One-Source-Multi-Use) 실현 가능 ② 광고 영업 효율화, 구매력 강화, 시너지 마케팅 활성화 ③ 세계시장 진출을 위한 규모의 경제 확보, 대규모 / 지속가능한 투자여력 확보" (주요사항보고서 예상 시너지) / "그룹이 목표로 하고 있는 콘텐츠 사업의 글로벌화와 계열사간 시너지 극대화를 위해 합병을 결정하게 됐다" (CJ 측, 이투데이 2010-11-16) | AJ11: 순수지주회사 — 자회사 ㈜온미디어(55.17%, 투니버스·OCN 등 케이블 방송채널사용사업자) 지분만 보유하고 영업수익은 지분법이익(증권신고서 투자위험요소 '순수지주회사로 영업수익은 지분법이익으로 구성'), 임직원 10명(2010-11 기준). 실질 사업은 온미디어의 케이블 PP: 2009년 온미디어 별도 매출 67,746백만원·자산 449,318백만원 | AK11: 인접 | AL11: 인수 주체의 실질 사업(온미디어 케이블 PP)과 엠넷미디어의 방송사업(Mnet·KM 음악채널, 2010년 매출의 27%)은 같은 PP 영역이나, 매출의 다수인 음반·음원 유통(33%)·음악포털(30%)은 콘텐츠 가치사슬상 붙어 있는 인접 영역이라 전체로는 인접으로 판단. 그룹 정점 CJ ENM 기준으로는 Mnet 채널과 음악사업이 현 음악사업 부문의 전신이라 핵심 | AM11: 477,015백만원 (오미디어홀딩스 별도, 2010-09-30; 증권신고서 당사회사 요약·증권발행실적보고서 합병 전 요약재무). 설립 개시재무상태표(2010-09-01) 474,852,301,036원. 참고: 2010-12-31 별도 473,527,264,185원, 연결(K-IFRS) 810,677,928천원 | AN11: acq_total_assets와 같음 (인수 주체 오미디어홀딩스=CJ E&M이 상장 지배회사 자신; 2010-09-15 설립이라 직전 회계연도말이 없음). 참고: 첫 결산 2010-12-31 연결 총자산 810,677,928천원(K-IFRS 재작성, CJ E&M 2011 사업보고서), 합병 6사 단순합산 1,691,841백만원(2010-09-30, 증권발행실적보고서 '합병 후' 개략 연결) | AO11: 계산: 38.94 (185,737백만원 ÷ 오미디어홀딩스 별도 총자산 477,015백만원, 2010-09-30; 발표 당시 주식수 기준 138,051백만원이면 28.94). 합병 6사 단순합산 총자산(1,691,841백만원) 대비 10.98. 공시에 비율 항목 없음 | AP11: 계산: 61.50 (185,737백만원 ÷ 오미디어홀딩스 별도 자본총계 302,024백만원, 2010-09-30; 발표 당시 주식수 기준 45.71) | AQ11: 계산: 144,533,191,550원 (발표 직전 거래일 2010-11-15 종가 29,150원 × 발행주식 4,958,257주; 종가는 주요사항보고서 합병가액 산정표, 주식수는 증권신고서 당사회사 요약). 2010-10-15 재상장 직후라 유통 이력이 한 달뿐임 | AR11: 인수 주체 규모는 오미디어홀딩스 2010-09-30 별도 재무(증권신고서 20101202000223, 증권발행실적보고서 20110310000585), 거래금액은 합병가액 29,150원 × 대상회사별 합병신주(합병기일 주식수 × 합병비율, 단주 버림, 계산). 합병 주요사항보고서(20101116000288)에는 총자산·자기자본 대비 항목이 없어 직접 계산함. 합병 후 CJ E&M 규모(6사 단순합산 1,691,841백만원) 대비 비율도 함께 적음 | AS11: KRX:130960 | AT11: 인수 주체 오미디어홀딩스=CJ E&M(코스닥 130960, 2018-07 상장폐지라 Yahoo Finance 시세 없음; 2010-11-16 16:24 거래정지, 2010-11-18 재개). 대상 엠넷미디어도 코스닥 상장사(KRX:056200): 2010-11-15 종가 2,850원, 시가총액 계산 138,051,189,900원(48,439,014주); 2010-11-16 16:22~장 종료 거래정지라 첫 반응일 2010-11-17; 2011-02-22 구주권 제출로 거래정지 후 소멸. 056200도 Yahoo Finance에 시세 없음 | AU11: 2010-11-16 장 마감 후: DART 회사합병결정·주요사항보고서(합병결정)·각 소멸회사 회사합병결정 공시와 CJ그룹 발표(이투데이 입력 16:14). 오미디어홀딩스 주권은 16:24 우회상장 여부 확인을 이유로 매매거래정지 후 2010-11-18 재개(우회상장 미해당), CJ인터넷(16:20)·엠넷미디어(16:22) 주권은 당일 장 종료까지만 정지. 발표 전 관련 조회공시·사전 보도는 찾지 못함(2010-09~11 공시 목록, 웹 검색 2회) | AV11: 1994-06: ㈜메디오피아테크날리지 설립(e-러닝·SI); 2002-01: 코스닥 상장; 2006-07: CJ㈜·CJ미디어 제3자배정 유상증자로 최대주주 CJ㈜, 지엠기획·에이디이천엔터테인먼트 주식교환; 2006-08: 엠넷미디어로 상호 변경; 2006-09: 기존 사업 물적분할(메디오피아테크, 2006-12 매각); 2007-05-31: 씨제이뮤직 흡수합병(C003); 2007~2008: 영업권 손상 34,628백만원; 2008-04: YG엔터테인먼트와 상호지분 보유·음반 독점 유통 계약; 2009-10: SC PE·CJ㈜ 대상 CB·BW 300억원 발행; 2009→2010: 별도 매출 128,773→146,926백만원, 영업이익 3,987→1,578백만원 | AW11: 2010-12-01: BW 행사 5,577,244주(SC PE); 2010-12-30·2011-02-22: CB 전환 각 5,577,244주(합병기일 발행주식 65,170,746주); 2010-12-30: 주총 합병 승인; 2011-03-01: 합병 — Mnet·KM 채널은 CJ E&M 방송사업부문, 음악·공연은 음악/공연부문(회사 대표 하대중, 음악·공연사업부문 대표 김병석); 2011: 음악/공연부문 매출 132,460·영업손실 847백만원(3~12월); 2012: 음악/공연/온라인 199,390·-8,330백만원; 2013: 239,615·-14,916백만원; 2014: 음악부문 180,703·-887백만원(공연부문 분리); 2014-03: 대표이사 강석희 → 강석희·김성수 각자대표; 2015-03: 김성수 단독대표; 2016-12-01: 음악플랫폼(Mnet.com 등) 물적분할 → 씨제이디지털뮤직; 2017: 음악부문 230,732·11,778백만원; 2018-07-01: CJ ENM 출범; 2018-10-10: 씨제이디지털뮤직이 ㈜지니뮤직에 흡수합병(CJ ENM 지니뮤직 지분 15.35%, 관계기업); 2021-03: 대표이사 강호성; 2022-03: 대표이사 윤상현; 2023-03: 윤상현·구창근 각자대표; 2024: CJ ENM 음악사업(음반·음원·매니지먼트·콘서트·커뮤니티 서비스; Mnet 채널은 미디어플랫폼사업) 매출 702,102·영업이익 30,883백만원, 지니뮤직 관계기업투자주식 손상 30,293백만원; 2024-04: 윤상현 단독대표; 2025: 음악사업 매출 817,589·영업이익 40,704백만원, 지니뮤직 사명 ㈜케이티지니뮤직(CJ ENM 지분 15.35% 유지, 장부금액 18,693→15,114백만원) | AX11: 해당 없음 (이 합병으로 영업권 미인식: CJ E&M 2011 사업보고서 — 동일지배 합병, CJ㈜ 연결 장부금액 승계). 후속 사업 수준 참고: CJ E&M 음악사업부문은 2015~2017 영업권 손상검사 CGU(할인율 2015 7.90%, 2016 13.01%, 2017 9.9%)였음(2017년 CJ E&M 연결 영업권 손상 853,984천원이 있으나 현금창출단위 귀속은 공시에서 확인 못 함). 합병 전 엠넷미디어 자체의 영업권 손상 2007년 7,683,957천원·2008년 26,944,153천원(2008 감사보고서 주석 9); Mnet.com 사업의 후신 지분(2016-12 씨제이디지털뮤직 분할 → 2018-10-10 지니뮤직 흡수합병으로 받은 지분 15.35%)에 대해 CJ ENM이 2024년 관계기업투자주식 손상차손 30,293백만원 인식(2024 사업보고서 연결 관계기업 주석, 2025 사업보고서 전기 표 주석에도 같은 기재); 2025년 관계기업 손상 합계는 998백만원이고 지니뮤직 개별 손상 기재는 없음 | AY11: 동일지배 합병·그룹 내 이전으로 새 영업권·투자주식 평가가 생기지 않음 | AZ11: 2009: 128,772,807,476원; 2010: 146,925,601,938원 (엠넷미디어 별도; 2010년 포털 44,037·음악 49,209·방송 40,208·기타 13,472백만원) | BA11: 2011(합병 후 3~12월): 132,460백만원; 2012: 199,390백만원 (CJ E&M 연결 음악/공연(·온라인) 부문 — Mnet·KM 채널은 방송부문이라 빠짐); 최근: CJ ENM 음악사업 2025 817,589,175천원(부문간 제거 후 외부매출; 2024 702,102,103천원; Mnet 채널은 미디어플랫폼사업이라 빠짐). 참고: CJ E&M 마지막 연도 2017 음악부문 230,732백만원 | BB11: 2009: 3,986,559,104원; 2010: 1,577,740,895원 (엠넷미디어 별도) | BC11: 2011: -847백만원; 2012: -8,330백만원 (CJ E&M 음악/공연(·온라인) 부문); 최근: CJ ENM 음악사업 2025 40,704,208천원(2024 30,882,579천원). 참고: 2017 음악부문 11,778백만원 | BD11: 인수 전: 엠넷미디어 별도·K-GAAP·12월 결산 감사보고서(2010 감사보고서 20110310000462, 2009는 같은 보고서 전기). 인수 후: 2011-03-01 소멸해 CJ E&M 연결 '음악/공연부문'(2012~2013 '음악/공연/온라인', 2014년부터 '음악부문'과 '공연부문' 분리; K-IFRS; 2011년은 소멸법인 1~2월 제외)으로 대신함 — Mnet·KM 음악채널은 CJ E&M 시절 방송부문이었고 CJ ENM에서도 미디어플랫폼사업(TV채널)에 속해 음악 부문 수치에서 빠짐(2024 사업보고서 사업의 개요 '방송채널사용사업자(PP)로서 현재 tvN, Mnet, OCN 등의 채널을 운영', 영업부문 주석의 음악사업 = 음반·음원·매니지먼트·콘서트·커뮤니티 서비스, 공연 기획·제작은 영화드라마사업), Mnet.com은 2016-12 분할·2018-10 지니뮤직 합병으로 빠짐. 최근 연도는 CJ ENM 2025 사업보고서(20260318001469) 연결 영업부문 주석(부문간 제거 후 외부매출) | BE11: 2011-02-28 출범(뉴스토마토): 음악·공연사업부문은 CJ엔터테인먼트와 엠넷미디어의 공연사업 통합, 엠넷미디어의 Mnet·KM 채널은 방송사업부문이 흡수, 2015년 매출 중 음악·공연 18% 목표; 2011 사업보고서(MD&A): 음악/공연부문 '음악유통 우위 사업자', 9월 글로벌 엠넷닷컴 론칭, 매출 1,325억원; 2013-02-06(아이뉴스24): 2012년 음악·공연·온라인 매출 1,994억원 — 자체 제작 음반·음원·콘서트와 대작 라이선스 공연이 실적을 끌어올림. 어닝콜 녹취록은 찾지 못함 | BF11: 완료 | BG11: 2026-10-26
A12: C009 | B12: CJ ENM | C12: 2010-11-16 | D12: On Media Corp. | E12: 12 | F12: True | G12: C005 | H12: MA② | I12: MA② | J12: 같음 | K12: 해당 없음 | L12: 불일치 | M12: 편입 후 | N12: Closed | O12: 348.41 | P12: CJ E&M Corporation | Q12: Capital International, Inc. | R12: O Media Holdings Co., Ltd. (KOSE: A130960) signed a statuary merger agreement to acquire remaining 44.83% stake in On Media Corp. (KOSE: A045710) from Capital International, Inc., CIPEF III, CIPEF II and others for approximately KRW 190 billion in stock on November 16, 2010. The exchange ratio for the transaction is 1: 0.1212693. O Media Holdings Co., Ltd. also signed agreement to acquire CJ Internet Corp., M-net Media Corp, CJ Media Inc. and CJ Entertainment Inc. The deal is subject to approval of shareholders of O Media Holdings Co., Ltd. The deal is expected to close on March 1, 2011. As of February 2, 2011, O Media Holdings Co., Ltd. (KOSE: A130960) agreed to acquire remaining 51.37% stake in On Media Corp. (KOSE: A045710). | S12: Media Platforms | T12: Broadcasting Channel | U12: MA-1 그룹이 매수자 | V12: 기존 자회사 잔여지분 | W12: MA② 기존 지분 확대 | Y12: False | Z12: MA② 기존 지분 확대 | AA12: 편입 후 (CJ ENM 전신 계보: 오미디어홀딩스(2010-12-30 씨제이이앤엠㈜으로 사명 변경, DART 00838421), 2018 CJ ENM 계보로 합병 — 2018-07-01 CJ오쇼핑이 CJ E&M을 흡수합병. 거래 당시 매수자는 2010-09-15 CJ오쇼핑 투자사업부문 인적분할로 설립된 상장사로 온미디어 55.17%를 보유해 온미디어는 이미 그 종속회사였음) | AB12: 완료 (합병기일 2011-03-01, 합병등기·온미디어 해산등기 2011-03-03; 양사 주주총회 승인 2010-12-30) | AC12: 발표 기준(잔여 44.83% = 52,949,080주): 합병신주 약 6,421,097주 × 합병가액 29,150원 = 약 187,175,000,000원(계산, 단주 처리 전) — 원자료 설명란 'approximately KRW 190 billion'과 일치. 합병기일 기준(오미디어홀딩스가 2011-01-28 10%를 매각해 비보유분 54.83% = 64,749,080주): 약 7,852,075주 = 약 228,888,000,000원(계산). 이 중 그룹 밖 주주 몫(온미디어 자기주식 5,626,141주·CJ㈜ 4,081,630주·이재현 1,663,200주 제외 53,378,109주)은 약 6,473,125주 = 약 188,692,000,000원(계산). 대가는 전액 신주(합병비율 1:0.1212693), 교부금 없음 | AD12: 원자료와 불일치: 발표 기준 187,175백만원 = 165.67백만 달러 (계산: Fed H.10 2010-11-16 1,129.80원/달러); 합병기일 기준 228,888백만원 = 203.73백만 달러 (2011-03-01 1,123.50원). 원자료 348.41(약 3,936억원 상당)은 어느 기준으로도 재현되지 않음 | AE12: 2010-11-16 | AF12: 기준 분류 유지(MA② 기존 지분 확대): 이미 55.17%(합병기일엔 45.17%)를 가진 지배회사가 합병으로 나머지 지분을 신주로 정리. 원자료 정정: (1) buyers 'CJ E&M Corporation'은 합병 존속법인 ㈜오미디어홀딩스(합병 결정 당시 사명, 2010-12-30 씨제이이앤엠으로 변경)로 같은 법인 — 맞음. (2) sellers 'Capital International, Inc., CIPEF…'는 합병으로 신주를 받은 소수주주 중 일부일 뿐(Capital International은 2010-06-30 CJ오쇼핑에 7,392,882주를 판 뒤 2,967,118주·2.51% 보유) — 거래 상대가 특정 매도자가 아니라 온미디어 소수주주 전체. (3) 'As of February 2, 2011 … remaining 51.37%'는 2011-01-28 오미디어홀딩스가 온미디어 11,800,000주(10%)를 블록세일한 뒤 CJ E&M(45.17%)+CJ㈜(3.46%) = 48.63%를 뺀 비율로, 계산은 맞지만 CJ㈜ 몫도 신주를 받음. (4) 금액 원자료 348.41백만 달러는 설명란(약 1,900억원)과도 맞지 않아 165.67(발표 기준)로 정정 제안. 온미디어의 역할: 존속법인이 아니라 합병으로 소멸한 피합병회사(존속법인 오미디어홀딩스=CJ E&M) | AG12: C005~C008(같은 날 오미디어홀딩스가 CJ엔터테인먼트·CJ인터넷·엠넷미디어·CJ미디어를 흡수합병해 CJ E&M 출범, 다른 묶음 CJ-A)과 한 합병 계약의 한 부분 — 6사 합병으로 발행한 신주는 총 32,971,307주(증권발행실적보고서)이며 이 행은 그중 온미디어 주주 배정분. 앞 단계는 C004(2010-06 CJ오쇼핑의 온미디어 55.17% 취득), 이 지분이 2010-09 인적분할로 오미디어홀딩스에 넘어옴. 회계: 연결 주석상 'CJ(주)의 동일 지배 하에 있는 종속기업 간 합병'으로 피합병법인 자산·부채를 장부금액 승계(새 영업권 없음). 이상한 점: 합병 직전 2011-01-28 오미디어홀딩스가 자기 보유 온미디어 10%를 4,900원에 팔아 578.2억원을 확보('재무구조 개선')했고, 그 결과 합병신주가 1,430,978주 늘어 그룹 밖으로 나간 신주가 오히려 증가(산 사람 중 CJ㈜ 4,081,630주). 합병가액 3,535원은 CJ오쇼핑 평균 취득가 6,669원의 53%이며 2010-11-15 종가 3,640원보다 2.9% 낮음. 온미디어 주식매수청구는 개인 4명 561주(3,521원)뿐. 사전 보도·조회공시는 찾지 못함(오미디어홀딩스·온미디어·CJ㈜ 2010-09~11-16 공시 목록 확인) | AH12: ㈜오미디어홀딩스 (합병 존속법인, 코스닥 130960; 2010-09-15 CJ오쇼핑 투자사업부문 인적분할 신설·2010-10-15 재상장, 최대주주 CJ㈜(2011-01-31 45.38%); 2010-12-30 씨제이이앤엠㈜(CJ E&M)으로 사명 변경 — 2018-07-01 CJ오쇼핑에 흡수합병돼 현 CJ ENM) | AI12: "경영효율성을 증대시키고 엔터테인먼트사업(영화, 음악, 게임)과 미디어사업을 통합하여 시너지 효과를 극대화하고 규모의 경제를 갖추어 세계적 회사로 성장하기 위하여" (회사합병결정 합병목적) / "그룹이 목표로 하고 있는 콘텐츠 사업의 글로벌화와 계열사간 시너지 극대화를 위해 합병을 결정" (CJ그룹 발표, 이투데이 2010-11-16) | AJ12: 온미디어 지분 55.17%를 보유한 순수지주회사(2010-09-01 분할 개시재무상태표 자산 474,852백만원 대부분이 온미디어 투자주식, 매출 없음). 실질 사업은 자회사 온미디어의 MPP(투니버스·OCN·바둑TV·온게임넷 등)와 SO 4사 | AK12: 핵심 | AL12: 인수 주체의 유일한 자회사가 대상 회사 자신이라 대상 사업이 곧 주력. 합병 뒤 CJ E&M 방송부문(2011 매출 6,358억원, 전체의 55.6%)의 중심이 됐고, 그룹 정점 현 CJ ENM의 미디어플랫폼(TV채널) 사업으로 이어짐 | AM12: 477,015백만원 (오미디어홀딩스 별도, 2010-09-30; 증권발행실적보고서 '합병 전' 요약재무). 참고: 분할 개시재무상태표(2010-09-01) 474,852,301,036원 | AN12: acq_total_assets와 같음 (오미디어홀딩스=CJ E&M이 상장 지배회사 자신, 2010-09 설립이라 직전 회계연도말 없음). 참고: 첫 결산 2010-12-31 연결 총자산 767,154,154천원(K-GAAP 연결감사보고서) | AO12: 계산: 39.24 (발표 기준 대가 187,175백만원 ÷ 오미디어홀딩스 총자산 477,015백만원, 2010-09-30); 합병기일 기준 228,888백만원이면 47.98 | AP12: 계산: 61.97 (187,175백만원 ÷ 자기자본 302,024백만원, 2010-09-30); 합병기일 기준 75.78 | AQ12: 계산: 144,533,191,550원 (발표 직전 거래일 2010-11-15 종가 29,150원 × 발행주식 4,958,257주; 종가는 주요사항보고서 합병가액 산정표, 주식수는 외부평가의견 분석기준일 발행주식총수) | AR12: 합병가액·비율은 온미디어 주요사항보고서(합병결정) 최종 정정본(20110223000249), 총자산·자기자본은 증권발행실적보고서(20110310000585)의 2010-09-30 별도 요약재무. 거래금액은 온미디어 주식수 × 0.1212693 × 29,150원으로 직접 계산(단주 처리 전). 공시에 총자산·자기자본 대비 비율 항목이 없음 | AS12: KRX:130960 | AT12: 인수 주체 오미디어홀딩스=CJ E&M(코스닥 130960; 2010-11-16 거래정지 후 11-17 해제, 2018-07 합병으로 상장폐지 — Yahoo 시세 없음). 대상 온미디어도 상장사(KRX:045710): 2010-11-15 종가 3,640원, 2010-11-16 16:28 거래정지·11-17 09:00 해제라 첫 반응일 2010-11-17, 2011-03 합병으로 상장폐지. 그룹 지주회사 CJ㈜(KRX:001040) 반응도 볼 수 있음 | AU12: 2010-10-05: 재경일보 '온미디어, CJ미디어와 합병 시너지 낸다'(14:41) — 증권사 연구원이 'CJ미디어가 오미디어홀딩스의 자회사로 편입되고 이후 온미디어와 CJ미디어가 합병할 것으로 전망'(공식 발표 전 증권가 전망일 뿐 회사 확인·조회공시는 없음, 한 매체만 확인); 2010-11-16: 온미디어·오미디어홀딩스 회사합병결정·주요사항보고서 공시(온미디어 16:28 거래정지~11-17 09:00 해제), 이투데이 16:14 보도 'CJ그룹, 엔터·미디어 통합 1조원대 미디어그룹 설립'. 인수설 보도·조회공시는 찾지 못함 | AV12: 2009-12-24: CJ오쇼핑 이사회, 온미디어 65,148,910주(55.17%)를 434,479,300,000원에 취득 결정(C004); 2010-06-08·06-30: CJ오쇼핑이 온미디어 55.17% 취득(C004); 2010-06-10: CJ오쇼핑 인적분할 결정; 2010-09-01: 분할기일, 2010-09-15 오미디어홀딩스 설립·온미디어 최대주주 변경; 2010-10-05: 증권사 연구원이 "CJ미디어가 오미디어홀딩스의 자회사로 편입되고 이후 온미디어와 CJ미디어가 합병할 것으로 전망"(재경일보, 공식 발표 전 증권가 전망); 2010-10-15: 오미디어홀딩스 코스닥 재상장; 2010-10-27: 온미디어 자회사 이플레이온 청산 결정; 실적 추세 — 온미디어 연결 매출 2009 281,091→2010 260,355백만원, 연결 영업이익 24,002→21,799백만원; 2010-11-15: 온미디어 종가 3,640원, 오미디어홀딩스 29,150원 | AW12: 2010-11-16: 합병 결정(합병비율 1:0.1212693), CJ㈜ 오미디어홀딩스·CJ인터넷 주식 장내매입 결정; 2010-12-07: 합병 설명회 — 2011 통합 매출 13,970억·영업이익 1,550억원 전망, 온미디어 지분 최대 15% 매각·디지틀온미디어·SO 4사 매각 계획; 2010-12-30: 양사 주총 승인, 오미디어홀딩스→씨제이이앤엠 사명 변경; 2011-01-28: 온미디어 10% 블록세일(4,900원, 578.2억원); 2011-02-18: 주식매수청구분(개인 4명 561주, 3,521원) 매수; 2011-02-22: 디지틀온미디어 235억원 매각; 2011-03-01: 합병기일 — 온미디어 소멸, OCN·바둑TV·온게임넷·SO 지분을 CJ E&M이 직접 보유; 2011-03-03: 합병등기; 2011: CJ E&M 방송부문 매출 6,358억·영업이익 474억원(전망 6,978억·703억 미달); 2012-03-14: 옛 온미디어 SO 4사를 CJ헬로비전에 1,697억원 매각; 2013-12-01: OCN·온게임넷·바둑TV 흡수합병(C011·C012); 2018-07-01: CJ오쇼핑이 CJ E&M 흡수합병, CJ ENM 출범; 2025: CJ ENM 미디어플랫폼 매출 1조 3,416억·영업이익 13억원 | AX12: 확인 안 됨 (이 합병은 'CJ(주)의 동일 지배 하에 있는 종속기업 간 합병'으로 장부금액 승계라 새 영업권이 생기지 않음 — CJ E&M 2011 연결 주석 40(20120330002738). 온미디어 관련 기존 영업권: 2010-12-31 연결 영업권 181,257,320천원(K-GAAP; 2010-09-01 이전 사업결합 영업권은 과거 회계기준 금액으로 이월), 이후 CJ E&M 방송사업부문(2015 사업보고서부터 현금창출단위 '씨제이이앤엠(주) 방송사업부문'으로 구분)·CJ ENM 미디어플랫폼사업부문에서 손상검사. 연도별 영업권 손상차손: 2014 3,072,325천원(CJ E&M 2014 사업보고서 주석 15; 그해 현금창출단위 표는 '씨제이이앤엠(주)'·메조미디어·제이에스픽쳐스로만 구분돼 대상 미특정), 2015 추가 손상 없음(2016 사업보고서 전기 표 손상차손누계액 3,072,325천원 유지), 2017 853,984천원(수집 기록, 대상 미특정·미대조), 2024 38,388,927천원·2025 19,940,683천원(CJ ENM 2025 사업보고서; 현금창출단위별 배분 미기재). 미디어플랫폼사업부문 영업권은 2024말 376,778,468천원 → 2025말 371,615,748천원으로 5,162,720천원 줄었으나 손상인지 연결범위 변동인지 표로 구분되지 않음. 수집 기록의 '2013 957,306천원'은 2014 사업보고서 전기 표의 상각·손상누계액 '처분금액' 행 값으로 보여 손상 인식액인지 불명. 2016·2018~2023 주석은 대조하지 않음) | AY12: 동일지배 합병·그룹 내 이전으로 새 영업권·투자주식 평가가 생기지 않음 | AZ12: 2009: 온미디어 연결 281,091,307,865원 (별도 67,746,337,164원); 2010: 연결 260,354,763,959원 (별도 73,556,536,273원) | BA12: 2011: CJ E&M 방송부문 635,789백만원(합병소멸법인 1~2월 제외, CJ미디어·엠넷 채널 포함); 2012: 764,151백만원; 최근 2025: CJ ENM 미디어플랫폼 부문 1,341,617백만원(외부매출). 참고: 합병 직전 온미디어 별도 자산 480,731,184천원(2011-03-01) | BB12: 2009: 온미디어 연결 24,001,768,039원 (별도 18,684백만원); 2010: 연결 21,799,200,936원 (별도 15,701,866,969원) | BC12: 2011: CJ E&M 방송부문 47,394백만원; 2012: 44,554백만원; 최근 2025: CJ ENM 미디어플랫폼 부문 1,332,256천원 | BD12: 인수 전 2009·2010은 온미디어 K-GAAP 연결·별도 감사보고서(2010 감사보고서 20110331002850, 연결감사보고서 20110426000457; 2009 비교표시). 합병으로 온미디어 법인이 사라져 이후는 CJ E&M 사업보고서의 방송부문(K-IFRS 연결; 2011 20120330002738, 2012 20130401001853)과 CJ ENM 2025 사업보고서(20260318001469) 미디어플랫폼사업 부문으로 대신 — 옛 CJ미디어(tvN 등)·엠넷·티빙 등이 섞여 온미디어 단독 성과가 아님 | BE12: CJ E&M 2012·2013 사업보고서 '합병등 전후의 재무사항 비교표'(2011-03 합병): 통합 CJ E&M 매출 예측 1,397,000·1,661,000 / 실적 1,279,186(괴리 8%)·1,394,585(16%)백만원, 영업이익 예측 155,000·189,000 / 실적 75,420(51%)·38,947(79%) — "종편출범에 따른 경쟁비용 증가, 킬러콘텐츠 확보 및 제작역량 강화를 위한 콘텐츠 투자 확대 및 게임사업부문의 역성장으로 인해 예측치보다 저조한 실적"; 2010-12-07 CJ E&M 합병 설명회(공정공시): 통합법인 2011 매출 13,970억·영업이익 1,550억, 2015 매출 31,070억·영업이익 4,290억원 전망; 방송사업 2011 6,978억/703억·2012 7,523억/765억원 전망, 근거 'OSMU(One Souce Multy Use)강화', '글로벌 사업 가속화', '컨텐츠 구매 경쟁력 강화를 통한 비용 절감' — 실제 2011 방송부문 6,358억/474억, 2012 7,642억/446억원으로 미달; 2010-11-16 신동휘 CJ 부사장(이투데이): 통합으로 '향후 지속적인 대규모 투자가 가능해지는 것은 물론' 글로벌 진출 기반 확보; CJ E&M 2011 사업보고서: '합병 이후 외부 환경에 적극적인 대응을 위한 방송 부문의 콘텐츠 투자 … 투자비용이 반영되어 영업이익은 701억원' | BF12: 완료 | BG12: 2026-10-26
A13: C010 | B13: CJ ENM | C13: 2011-01-06 | D13: On Game Network Inc. | E13: 160 | F13: False | H13: MA④ | I13: MA④ | J13: 같음 | K13: 해당 없음 | L13: 일치 | M13: 편입 후 | N13: Closed | O13: 0.866 | P13: On Media Corp. | Q13: CJ Internet Corp. | R13: On Media Corp. (KOSE: A045710) acquired an additional 7% stake in On Game Network Inc. from CJ Internet Corp. (KOSE: A037150) for approximately KRW 970 million on December 30, 2010. On Media Corp acquired 0.24 million shares at the price of KRW 4060 per share. On Game Network reported revenues of KRW 22.5 billion, net loss of KRW 899 million, total assets of KRW 21.3 billion and total stockholders equity of KRW 19 billion in 2010. | S13: Media Platforms | T13: Broadcasting Channel | U13: MA-2 그룹 내부 재편 | W13: MA④ 그룹 내부 재편 | Y13: False | Z13: MA④ 그룹 내부 재편 | AA13: 편입 후 (CJ ENM 전신 계보: 온미디어, 2011 CJ ENM 계보로 합병 — 2011-03-01 CJ E&M에 흡수합병. 거래 당시(2010-12-30) 온미디어는 씨제이이앤엠(옛 오미디어홀딩스, 55.17%)의 연결 종속회사였고 매도자 씨제이인터넷도 같은 날짜로 CJ E&M에 합병될 CJ ENM 전신 계보 회사) | AB13: 완료 (2010-12-30) | AC13: 971,996,480원 (온게임네트워크 보통주 239,408주 × 4,060원, 지분 7.0%; 현금) | AD13: 원자료와 일치 (0.866; 계산: 971,996,480원 ÷ Fed H.10 2011-01-06 1,121.00원/달러 = 0.867백만 달러. 거래일 2010-12-30 1,130.60원 적용 시 0.860) | AE13: 2011-01-06 | AF13: 기준 분류 유지(MA④ 그룹 내부 재편): 매수자 온미디어(CJ E&M 자회사)와 매도자 씨제이인터넷(CJ㈜ 계열 코스닥사) 모두 CJ ENM 계보 회사이며 두 회사는 두 달 뒤 2011-03-01 같은 합병으로 CJ E&M에 흡수됨. 원자료 날짜 2011-01-06은 공정거래법상 '최대주주 등의 주식보유 변동' 공시일이고 거래일은 2010-12-30. 금액·주식수·단가(KRW 4,060)와 설명란의 온게임네트워크 2010 실적(매출 225억·순손실 8.99억·자산 213억·자본 190억원)은 감사보고서와 일치 | AG13: 온미디어 계보(CJ-B)의 그룹 내부 정리 거래. C009(2010-11-16 결정된 오미디어홀딩스의 온미디어·CJ인터넷 등 흡수합병) 직전에 합병 대상 두 회사 사이에서 온게임넷 지분을 옮긴 것으로, 경제적으로는 같은 합병 범위 안의 이동임(목적 공시 없음). 결과: 온미디어 지분 79.7%(2,728,400주)→86.7%(2,967,808주), 2011-03-01 합병기일에 CJ E&M이 승계(온게임네트워크 공정위 공시 2011-03-11의 변동일 표기는 2011-03-03). 후행: 2013-12-01 CJ E&M의 온게임네트워크 흡수합병(합병비율 1:0.1673360, C011과 같은 합병 — 이 묶음엔 온게임넷 행이 따로 없음). 가격: 4,060원은 2009말 주당 순자산 5,817원(계산: 자본총계 19,905,320,811원 ÷ 3,421,808주)과 2010말 5,554원(계산)보다 낮음; 씨제이인터넷의 2009말 장부가 1,320백만원(239천주) 대비 약 348백만원 낮은 값이라 처분손실이 났을 것으로 추정(계산, 씨제이인터넷 감사보고서는 대조 안 함). 씨제이인터넷 지분의 기원: 2003말 주주명부에 '플레너스(구,플래너스엔터테인먼트(주))' 196,000주(9.80%)가 있었고 2006말에 씨제이인터넷 239,408주(7.00%)로 표기됨 — 씨제이인터넷은 2004년 CJ그룹 편입 때 상호를 바꾼 회사(2009 사업보고서)라 같은 지분을 이어받은 것으로 보임(추정). 소규모라 매수·매도 회사 모두 거래소 공시가 없고 근거는 공정위 공시·감사보고서·CJ E&M 연결 주석뿐 | AH13: ㈜온미디어 (유가증권시장 045710; 2010-09-15부터 씨제이이앤엠(옛 오미디어홀딩스) 55.17% 자회사인 CJ그룹 계열 MPP 사업지주회사, 2011-03-01 CJ E&M에 흡수합병) | AI13: 미확인 (공정거래법상 '최대주주 등의 주식보유 변동' 공시에는 목적 항목이 없고 온미디어·씨제이인터넷의 거래소 공시·보도자료를 찾지 못함). 추정: 2011-03 CJ E&M 합병을 앞둔 계열 내 지분 정리 | AJ13: 케이블 PP(MPP)를 영위하는 사업지주회사: 2009 별도 영업수익 67,746백만원 = 지분법이익 11,373 + 자회사 관리·광고대행 수수료 21,736 + 직영 채널(투니버스) 광고 12,250·시청료 13,092·사업수익 9,294(2009 사업보고서 매출실적, 백만원); 자회사 OCN·바둑TV·온게임넷·SO 4사·디지틀온미디어 | AK13: 핵심 | AL13: 온게임넷(ongamenet)은 온미디어가 2000년부터 지배해 온 게임 전문 PP 자회사로 인수 주체의 주력인 케이블 채널 사업 그 자체. 그룹 정점(CJ E&M→CJ ENM) 기준으로도 방송부문의 한 채널이었으나 2022년 OP.GG에 채널이 넘어감 | AM13: 455,121백만원 (온미디어 별도, 2010-09-30; CJ E&M 증권발행실적보고서 '합병 전' 요약재무). 참고: 2009-12-31 별도 449,318백만원 | AN13: 477,015백만원 (상장 지배회사 씨제이이앤엠(옛 오미디어홀딩스) 별도, 2010-09-30 — 2010-09 설립이라 직전 회계연도말 연결 총자산 없음). 참고: 첫 결산 2010-12-31 연결 767,154,154천원(K-GAAP) | AO13: 계산: 0.21 (971,996,480원 ÷ 온미디어 총자산 455,121백만원, 2010-09-30) | AP13: 계산: 0.22 (971,996,480원 ÷ 온미디어 자기자본 446,404백만원, 2010-09-30) | AQ13: 미확인 (거래일 직전 2010-12-29·공시일 직전 2011-01-05 온미디어 종가를 찾지 못함 — 상장폐지 종목이라 Yahoo 시세 없음, KRX 접근 불가). 참고 범위: 2010-11-15 종가 3,640원 기준 429,876,683,600원, 2011-01-27 종가 5,120원 기준 604,661,708,800원(계산, 118,097,990주). 상장 지배회사 씨제이이앤엠은 2010년 12월 주가 31,500~36,950원 × 4,958,257주 = 1,562억~1,832억원 | AR13: 거래금액은 공정위 공시(온게임네트워크 2011-01-06, 20110106000071). 총자산·자기자본은 CJ E&M 증권발행실적보고서(20110310000585)의 온미디어 2010-09-30 별도 요약재무. 시가총액은 일별 종가 미확보로 범위만 기재 | AS13: KRX:045710 | AT13: 인수 주체 온미디어(유가증권시장 045710, 2011-03 상장폐지). 다만 거래가 공정위 공시로만 알려진 소규모(자산의 0.2%) 그룹 내부 거래라 이벤트 분석의 정보 충격은 작을 것. 매도자 씨제이인터넷도 코스닥 상장사(원자료 표기 037150, 2011-03 합병으로 상장폐지), 상장 지배회사 씨제이이앤엠(KRX:130960). 대상 온게임네트워크는 비상장 | AU13: 2011-01-06: DART 온게임네트워크 '최대주주 등의 주식보유 변동'(공정거래법, 기업집단 씨제이) — 2010-12-30 온미디어 +239,408주·씨제이인터넷 −239,408주, 단가 4,060원 | AV13: 2000-02-02: 온게임네트워크 설립(자본금 12억원); 2000-10: 온미디어 62.99% 취득; 2003말: 온미디어 65.31%·한국통신하이텔 19.50%·플레너스 9.80%; 2004-12-31: 채널 퀴니 운영사 ㈜퀴니 흡수합병; 2006말: 온미디어 73.21%·한국통신하이텔 11.40%·씨제이인터넷 7.00%; 2007-05: 보유하던 디지틀온미디어 80.21%를 온미디어에 처분; 2007-12: 인터넷 방송 개국 계획(공정공시); 2009말: 온미디어 79.74%; 실적 — 2008 매출 24,596백만원·영업손실 1,843백만원, 2009 매출 21,847백만원·영업이익 1,968백만원; 2010-06: 모회사 온미디어가 CJ오쇼핑에 인수(C004); 2010-11-16: 온미디어·씨제이인터넷 모두 CJ E&M 합병 대상으로 결정(C009) | AW13: 2010-12-30: 지분 이전, 온미디어 86.73%·케이티하이텔 11.40%·이스트소프트 0.88%·엠게임 0.82%; 2010: 매출 22,520백만원·영업손실 963백만원; 2011-03-01: 합병기일 — 온미디어가 씨제이이앤엠(옛 오미디어홀딩스)에 흡수합병(CJ E&M 증권발행실적보고서); 2011-03-03: 온게임네트워크 공정위 공시(2011-03-11)상 변동일 — 최대주주가 온미디어에서 씨제이이앤엠으로 변경(2,967,808주, 86.7%); 2011: 매출 22,786백만원·영업손실 1,202백만원(K-IFRS); 2012: 매출 21,734백만원·영업이익 1,713백만원; 2013-08-21: CJ E&M이 OCN·바둑TV 등과 함께 흡수합병 결정(합병비율 1:0.1673360, 주식매수청구가 6,250원), ㈜엠게임 28,000주 매수청구; 2013-12-01: 흡수합병·법인 소멸, 채널은 CJ E&M 방송부문으로; 2014: 롤드컵 성공으로 매출 30,916백만원·영업이익 8,620백만원(합병 사후 비교표); 2018-07-01: CJ ENM 출범; 2019: 라이엇게임즈가 LoL 리그 자체 주관·중계로 전환해 OGN 경영위기(딜사이트); 2021-05: CJ ENM이 삼정KPMG를 매각주관사로 OGN 채널 운영권 포함 자산양도 매각 추진, 가치 100억원 미만 평가(KED); 2021: 스카이라이프·KT·SK브로드밴드에서 채널 퇴출(딜사이트); 2022-06: OP.GG(오피지지)가 CJ ENM으로부터 OGN 채널 인수 발표(인수 금액 미공개) | AX13: 확인 안 됨 (온게임넷 관련 별도 영업권·투자주식 손상 기재를 찾지 못함: CJ E&M 2011 연결 주석 41은 이 거래를 비지배지분 거래로 처리(취득대가 971,996천원, 비지배지분감소 1,677,862천원 — 영업권 미발생); 2013-12 합병은 동일지배 장부가 승계; CJ E&M 2013·2017 무형자산 변동표의 영업권 손상은 대상 미특정. 2022 OGN 매각 손익은 CJ ENM 2022 사업보고서에서 대조하지 않음) | AY13: 비지배지분 거래로 처리돼 영업권이 생기지 않음(CJ E&M 2011 연결 주석) | AZ13: 2008: 24,596,323,703원; 2009: 21,846,798,211원 | BA13: 2010: 22,520,215,867원; 2011: 22,785,834,260원; 최근 확인 가능 연도 2014: 30,916백만원(CJ E&M 사업보고서 '합병등 전후의 재무사항 비교표' 실적; 2013 21,925백만원; 독립 법인 마지막 감사 연도 2012 21,734,074,844원) | BB13: 2008: (1,843,198,733)원 영업손실; 2009: 1,967,918,893원 | BC13: 2010: (963,262,448)원 영업손실; 2011: (1,202,027,220)원 영업손실; 최근 확인 가능 연도 2014: 8,620백만원(비교표 실적, 예측 2,784백만원 대비 초과 — '롤드컵 성공으로 프로그램 협찬 매출 증가'; 2013 3,196백만원; 2012 감사 1,713,005,615원) | BD13: 온게임네트워크 별도 재무제표, 12월 결산. 2008~2010 K-GAAP 감사보고서(2009 감사보고서 20100325000114: 2008·2009; 2010 감사보고서 20110325000910), 2011~2012 K-IFRS 감사보고서(2012 감사보고서 20130326000654: 2011·2012). 2013·2014는 CJ E&M 2014 사업보고서(20150331004213) '합병등 전후의 재무사항 비교표'의 실적(1차연도 2013·2차연도 2014로 판단; 합병 후 내부 사업부 기준). 2015년 이후 채널 단독 실적은 공시되지 않음 | BE13: CJ E&M 2014 사업보고서 합병 사후 비교표: 온게임네트워크 2014 매출 30,916백만원·영업이익 8,620백만원으로 예측(25,286·2,784) 초과, 비고 "롤드컵 성공으로 프로그램 협찬 매출 증가"; 2021-05-21 KED: CJ ENM 관계자 "nothing has been decided yet"(OGN 매각 추진 관련), 매각 배경은 게임사들의 자체 e스포츠 중계 확대로 인한 시청률 하락. 이 거래 자체를 다룬 IR·어닝콜 언급은 찾지 못함 | BF13: 완료 | BG13: 2026-10-26
A14: C011 | B14: CJ ENM | C14: 2013-08-21 | D14: Korea Badook Television Inc. | E14: 97 | F14: False | G14: C011 | H14: MA② | I14: MA② | J14: 같음 | K14: 해당 없음 | L14: 일치 | M14: 편입 후 | N14: Closed | O14: 11 | P14: CJ E&M Corporation | Q14: - | R14: CJ E&M Corporation (KOSE:A130960) agreed to acquire remaining 33.79% stake in Baduk Television Co Ltd for $11 million in stock on August 21, 2013. CJ E&M will issue one share of its common stock for 0.2699598 shares of Baduk Television. Pursuant to the transaction, Baduk Television will be dissolved. In related transactions, CJ E&M will also acquire remaining stakes in Orion Cinema Network Co Ltd, On Game Network Inc, Korea Music Television Co., Ltd and International Media Genius in stock. As combined consideration, 0.8 million shares will be issued out of which 0.38 million shares will be issued from treasury. The consideration shares will be issued on December 16, 2013. On August 23, 2013 an agreement was entered. Upon completion of issuance of consideration shares, outstanding shares of CJ E&M will increase from 37.56 million to 38.35 million. Baduk Television reported revenues of $17.97 million, total assets of $25.22 million, net income of $3.12 million and total common equity of $21.11 million for the year ending December 31, 2012. The transaction is expected to close on December 1, 2013. PricewaterhouseCoopers Korea acted as accountant for CJ E&M. The currency conversion for the financials was done by www.oanda.com dated December 31, 2012. | S14: Media Platforms | T14: Broadcasting Channel | U14: MA-1 그룹이 매수자 | V14: 기존 자회사 잔여지분 | W14: MA② 기존 지분 확대 | Y14: False | Z14: MA② 기존 지분 확대 | AA14: 편입 후 (CJ ENM 전신 계보: CJ E&M(씨제이이앤엠㈜), 2018 CJ ENM 계보로 합병 — 2018-07-01 CJ오쇼핑에 흡수합병. 거래 당시 바둑텔레비전은 CJ E&M이 66.21%를 가진 연결 종속회사) | AB14: 완료 (합병기일 2013-12-01, 합병등기 2013-12-02; 바둑텔레비전 주주총회 승인 2013-10-23, 주식매수청구분 매수 2013-11-29) | AC14: 약 12,383,600,000원 (계산: 비지배 1,228,166주(33.79%) × 합병비율 0.2699598 = CJ E&M 주식 약 331,555주 × 합병가액 37,350원 ≈ 12,383,579,250원; = 1,228,166주 × 바둑TV 합병가액 10,083원). 실제 지급 구성: (재)한국기원 외 5명이 419,875주에 주식매수청구권을 행사해 바둑텔레비전이 2013-11-29 현금 4,233,599,625원(10,083원)을 지급하고, 나머지 808,291주에는 CJ E&M 주식 약 218,206주(37,350원 기준 약 8,149,994,100원)를 교부(계산; 매수청구 자기주식분에 배정된 CJ E&M 주식은 CJ E&M 자기주식이 됨) | AD14: 원자료와 일치 (11.0; 계산: 12,383.6백만원 ÷ Fed H.10 2013-08-21 1,116.86원/달러 = 11.09) | AE14: 2013-08-21 | AF14: 기준 분류 유지(MA② 기존 지분 확대): CJ E&M이 66.21%를 가진 종속회사의 잔여 33.79%(한국기원 9.80%·소액주주 236명 15.39% 등 그룹 밖 주주)를 흡수합병으로 정리. 원자료 설명란 보완: (1) 'for $11 million in stock'과 달리 약 3분의 1(4,234백만원)은 주식매수청구에 따른 현금으로 나감. (2) 바둑TV 2012 실적 중 매출 $17.97m(=19,184백만원)·순이익 $3.12m은 바둑TV 사업보고서와 맞지만 총자산 $25.22m·자본 $21.11m은 사업보고서(자산 19,813·자본 16,984백만원)가 아니라 CJ E&M 합병 주석의 2012-12-31 요약(자산 26,928,999·자본 22,534,415천원)에 가까움. (3) 'consideration shares … December 16, 2013'은 배정일·상장 전일과 일치, 0.8백만 신주·0.38백만 자기주식도 공시(795,565·377,618주)와 일치. (4) 설명란 'CJ E&M will issue one share of its common stock for 0.2699598 shares of Baduk Television'은 방향이 거꾸로임 — 회사합병결정의 합병비율은 바둑TV 1주당 CJ E&M 0.2699598주(합병가액 10,083원 ÷ 37,350원). 다만 연결 주석은 실제 교부 999,526주(신주 795,565+자기주식 203,961)로 계획 1,173,183주보다 적음 — 차이 173,657주의 내역(매수청구분 등)은 완전히 맞추지 못함 | AG14: C012(OCN 잔여 9.73%)와 같은 날 같은 합병(event_group C011) — 함께 흡수된 온게임네트워크(비지배 13.27%, C010의 후속)·케이엠티브이·인터내셔널미디어지니어스는 이 묶음에 별도 행 없음. 바둑TV 지분 경로: 1999-08 오리온그룹(동양제과)이 인수 → 2000-01-24 최대주주 동양제과(주) 외 8인 → 2000-06-15 최대주주 지주회사 온미디어(온미디어 설립 시 53.47%) → 2009말 64.84% → 2010-06 온미디어의 CJ오쇼핑 피인수(C004) → 2010-11-04 온미디어가 50,000주 추가취득(225,000,000원, 주당 4,500원; 공정위 공시 20101108000300·CJ E&M 2011 연결 주석 41) 66.21% → 2011-03 CJ E&M의 온미디어 흡수합병(C009)으로 CJ E&M 직접 보유 → 이 거래로 100%. 원래 운영자이던 한국기원은 이 합병에 반대해 현금을 받고 나갔다가, 2016-01-01 CJ E&M 방송사업부문으로부터 바둑TV 채널을 넘겨받아 직접 운영(세계일보 2016-03-10 — 같은 기사의 '1999년 8월 온미디어에 인수'는 온미디어가 2000-06 설립이라 '오리온그룹에 인수'의 오기로 보임; CJ E&M 사업보고서 채널 목록에 2015말엔 있고 2016말엔 없음) — 그룹 입장에선 2년 만의 사업 철수. 채널 양도 금액·방식은 찾지 못함. 바둑TV는 비상장이지만 소액주주가 많아 사업보고서를 냄 | AH14: 씨제이이앤엠㈜ (CJ E&M, 코스닥 130960; CJ㈜ 40.19%가 최대주주인 CJ 계열 MPP·엔터테인먼트 회사, 2018-07-01 CJ오쇼핑에 흡수합병돼 현 CJ ENM) | AI14: "5개 방송 자회사들을 통합하여 비용 절감 및 관리조직 일원화 등 경영 효율성을 증대하기 위함" (회사합병결정 합병목적) / "5개 PP(방송채널사용사업) 자회사들을 하나로 통합하여 비용 절감 및 관리조직 일원화 등 운영의 효율화를 도모하고, MPP(복수방송채널사용사업자)로서 합병회사의 브랜드 아이덴티티를 강화" (주요사항보고서 합병의 배경) | AJ14: 케이블·IPTV용 방송채널(MPP, tvN·Mnet·OCN 등 18개 채널 브랜드)과 게임·영화·음악/공연. 2012 연결 매출 1,394,585백만원 중 방송부문 764,151백만원(54.8%)·영업이익 44,554백만원(2012 사업보고서 사업부문별 요약) | AK14: 핵심 | AL14: 바둑TV는 CJ E&M 방송부문이 이미 연결로 운영하던 PP 채널이라 인수 주체의 주력(방송채널) 그 자체이며, 합병 목적도 방송사업부문 내부 법인 정리. 그룹 정점 현 CJ ENM 기준으로도 미디어플랫폼(TV채널) 사업에 속했으나 2016년 한국기원에 넘겨 현재는 보유하지 않음 | AM14: 1,777,340,322천원 (CJ E&M 별도, 2013-06-30; 증권발행실적보고서 '합병 전' 요약재무의 부채와자본총계 — 같은 표의 자산총계 2,294,779,980천원은 투자자산 517,439,659천원이 중복 합산된 것으로 보여 부채+자본 합계를 씀) | AN14: acq_total_assets와 같음 (인수 주체 CJ E&M이 상장 지배회사 자신). 참고: 직전 회계연도말 2012-12-31 연결 총자산 2,090,977,463,021원 | AO14: 계산: 0.70 (12,383.6백만원 ÷ 별도 1,777,340백만원, 2013-06-30); 연결 2012-12-31 기준 0.59 | AP14: 계산: 1.07 (12,383.6백만원 ÷ 별도 자기자본 1,158,968백만원, 2013-06-30) | AQ14: 계산: 1,416,929,171,400원 (발표 직전 거래일 2013-08-20 종가 37,350원 × 발행주식총수 37,936,524주(자기주식 377,618주 포함); 종가·주식수 모두 주요사항보고서 합병가액 산정표) | AR14: 합병가액·비율·주식수는 CJ E&M 주요사항보고서 최종 정정(20130912000216), 비지배 주식수 1,228,166주는 2013-09-04 정정본의 매수청구 한도 산정표, 매수청구는 증권발행실적보고서(20131206000312), 자기자본·총자산은 같은 보고서의 2013-06-30 별도 요약재무. 소규모합병이라 공시에 총자산대비 비율 항목이 없어 직접 계산 | AS14: KRX:130960 | AT14: 인수 주체 CJ E&M(코스닥 130960, 2018-07 합병으로 상장폐지 — Yahoo 시세 없음; 2013-07-22~08-20 일별 종가는 주요사항보고서에 수록). 대상 바둑텔레비전은 비상장. 거래 규모가 시가총액의 0.9%라 주가 충격은 작을 것 | AU14: 2013-08-21: DART CJ E&M '회사합병결정'·'자기주식처분결정'(5개 방송 자회사 합병); 2013-08-22 CJ E&M·바둑텔레비전 주요사항보고서(합병결정), 2013-08-23 바둑텔레비전 회사합병결정. 사전 보도는 찾지 못함 | AV14: 1994-12: 바둑텔레비전 창립(자본금 47.5억원), 1995-12 개국, 1996-04 한국기원 방송제작시설 완공; 1999-08: 오리온그룹(동양제과)이 바둑텔레비전 인수(오리온 기업집단 연혁 '1999. 8 ㈜바둑텔레비전 인수'), 1999-08-11 유상증자 50억원; 2000-01-24: 최대주주 (재)한국기원→동양제과(주) 외 8인; 2000-06-15: 최대주주 지주회사 (주)온미디어(자회사 편입); 2009: 매출 15,308백만원·영업이익 3,067백만원(K-GAAP); 2010-06: 온미디어의 CJ오쇼핑 피인수(C004), 2010-08-02 CJ 기업집단 편입; 2010-11-04: 온미디어가 기타 주주로부터 50,000주를 주당 4,500원(2.25억원)에 추가취득(64.84→66.21%, 공정위 공시 2010-11-08); 2011-03: 최대주주 씨제이이앤엠(C009); 2011: 매출 17,557백만원·영업이익 2,122백만원; 2012: 매출 19,184백만원·영업이익 3,929백만원, 주주 CJ E&M 66.21%·한국기원 9.80%·소액주주 236명 15.39% | AW14: 2013-09-04: 합병비율 정정(OCN만 변경); 2013-10-23: 바둑TV 주주총회 승인, 한국기원 외 5명 419,875주 매수청구(2013-11-29 매수, 10,083원); 2013-12-01: 합병기일, 법인 소멸·채널은 CJ E&M 방송부문으로; 2013-12-17: 합병신주 상장 예정; 2013: 바둑TV 매출 18,280백만원·영업이익 3,464백만원, 2014: 18,049·5,102백만원(합병 사후 비교표, 예측 21,083·5,004); 2016-01-01: 한국기원이 CJ E&M 방송사업부문으로부터 바둑TV 채널을 인수해 직접 운영(세계일보) — CJ E&M 2016 사업보고서 채널 목록에서 빠짐; 2018-07-01: CJ ENM 출범(바둑TV는 이미 그룹 밖) | AX14: 확인 안 됨 (합병은 동일지배 종속기업 간 합병으로 장부가 승계 — 새 영업권 없음, CJ E&M 2013 연결 주석 35; CJ E&M 2013·2017 무형자산 변동표의 영업권 손상 957,306·853,984천원은 대상 미특정. 2016 채널 양도 손익은 CJ E&M 2016 연결 주석에서 대조하지 않음) | AY14: 동일지배 합병·그룹 내 이전으로 새 영업권·투자주식 평가가 생기지 않음 | AZ14: 2011: 17,557백만원; 2012: 19,183,737천원 (사업보고서 요약 19,184백만원) | BA14: 2013: 18,280백만원 (참고: 합병기일까지 2013-01~11 17,028,805천원); 2014: 18,049백만원; 최근 확인 가능 연도 2014 (2015년은 채널 단독 실적 미공시, 2016-01-01 한국기원에 양도) | BB14: 2011: 2,122백만원 (개정 표시기준 재작성 2,121,543천원); 2012: 3,929,259천원 | BC14: 2013: 3,464백만원; 2014: 5,102백만원 (합병 전 예측 4,094·5,004백만원); 최근 확인 가능 연도 2014 | BD14: 인수 전은 바둑텔레비전 사업보고서(2012 사업보고서 20130401002237, K-IFRS 별도·12월 결산; 2011은 같은 보고서 비교표시). 인수 후 2013·2014는 CJ E&M 2014 사업보고서(20150331004213) '합병등 전후의 재무사항 비교표' 실적(1차연도 2013·2차연도 2014로 판단 — FY2014 보고서에 두 해가 모두 실림; 합병 후 CJ E&M 내부 사업 기준). 2013 1~11월 수치는 CJ E&M 2013 연결 주석 35(피합병법인 요약) | BE14: CJ E&M 2014·2016 사업보고서 합병 사후 비교표: 바둑텔레비전 매출 2013 18,280(예측 19,963, 괴리 8%)·2014 18,049백만원(예측 21,083, 14%), 비고 "방송 광고시장의 업황 부진으로 인한 매출 감소"; 영업이익 2014 5,102백만원으로 예측 5,004백만원 소폭 초과. 이 합병을 다룬 IR·어닝콜 언급은 찾지 못함 | BF14: 완료 | BG14: 2026-10-26
A15: C012 | B15: CJ ENM | C15: 2013-08-21 | D15: Orion Cinema Network Co., Ltd. | E15: 56 | F15: False | G15: C011 | H15: MA② | I15: MA② | J15: 같음 | K15: 해당 없음 | L15: 불일치 | M15: 편입 후 | N15: Closed | O15: 27.75 | P15: CJ E&M Corporation | Q15: - | R15: CJ E&M Corporation (KOSE:A130960) agreed to acquire remaining minority stake in Orion Cinema Network Co., Ltd. for KRW 29.8 billion in stock on August 21, 2013. CJ E&M will issue 0.651406 shares for every share of Orion. Pursuant to the transaction, Orion Cinema will be dissolved. The transaction is expected to close on December 1, 2013. As of September 4, 2013, the merger ratio was amended. CJ E&M will issue 0.648594 share for every share of Orion. CJ E&M will issue 0.8 million shares of its common stock. PricewaterhouseCoopers Korea acted as accountant for CJ E&M. | S15: Media Platforms | T15: Broadcasting Channel | U15: MA-1 그룹이 매수자 | V15: 합병 | W15: MA② 기존 지분 확대 | Y15: False | Z15: MA② 기존 지분 확대 | AA15: 편입 후 (CJ ENM 전신 계보: CJ E&M(씨제이이앤엠㈜), 2018 CJ ENM 계보로 합병 — 2018-07-01 CJ오쇼핑에 흡수합병. 거래 당시 오리온시네마네트워크는 CJ E&M이 90.27%를 가진 연결 종속회사) | AB15: 조건 변경 후 완료 (합병기일 2013-12-01; 합병등기 예정일 2013-12-02(실제 등기일은 공시로 미확인); 2013-09-04 변경이사회로 OCN 합병비율 0.6514056→0.6485944 하향. 간이합병이라 OCN 주주총회는 이사회 승인으로 갈음, OCN 주주 ㈜중앙일보사의 주식매수청구 없음(청구는 바둑TV·온게임 주주만, 증권발행실적보고서)) | AC15: 약 27,512,831,700원 (계산: ㈜중앙일보사 보유 1,135,721주(9.73%) × 합병비율 0.6485944 = CJ E&M 주식 736,622주(단주 버림) × 합병가액 37,350원; = 1,135,721주 × OCN 합병가액 24,225원 ≈ 27,512,841,225원). 대가는 전액 CJ E&M 주식(자기주식·신주 혼합 배정), 현금 없음. 정정 전 조건(0.6514056·24,330원)이면 약 27,632백만원 | AD15: 원자료와 불일치: 27,512.8백만원 = 24.63백만 달러 (계산: Fed H.10 2013-08-21 1,116.86원/달러, 원자료 27.75 대비 −11.2%). 합병기일 무렵 환율(2013-11-29 1,057.76원)이면 26.01백만 달러로 ±10% 이내 | AE15: 2013-08-21 | AF15: 기준 분류 유지(MA② 기존 지분 확대): CJ E&M이 90.27%를 가진 종속회사의 잔여 9.73%(그룹 밖 주주 ㈜중앙일보사 단독)를 흡수합병으로 정리. 원자료 금액 'KRW 29.8 billion'은 공시 조건(736,622주 × 37,350원 = 275.1억원)으로 재현되지 않으며, 추정: 736,622주에 CJ E&M 주가 약 40,450원(발표 이후 시세)을 곱한 값으로 보임. 'merger ratio amended … 0.648594 share'는 공시(0.6485944, 2013-09-04)와 일치. 'CJ E&M will issue 0.8 million shares'는 5개사 합병 전체 신주(795,565주) 기준. 원자료 sellers '-'는 실제로는 ㈜중앙일보사. 상태는 원자료 Closed를 '조건 변경 후 완료'로 구체화(발표 2주 뒤 2013-09-04 OCN 합병비율 하향 정정 후 그 조건으로 완료) | AG15: OCN 지분 계보의 마지막 단계: C002(2006 OCN 증자, 중앙일보가 실권해 9.73%로 희석) → C004(2010-06 CJ오쇼핑이 OCN 90.27%를 가진 온미디어 인수) → C009(2011-03 CJ E&M이 온미디어 흡수, OCN 90.27% 직접 보유) → C012(2013-12 OCN 흡수합병으로 100%). C011(바둑TV)과 같은 합병(event_group C011). 중앙일보의 OCN 지분 기원: OCN이 1999년 ㈜중앙일보의 Catch One 채널사업권을 양수(매수가 74억원)한 데서 비롯된 것으로 보임(추정, OCN 2006 감사보고서 주석). 합병비율 변경 사유는 'OCN 매출 추정 가정의 변경에 따른 수정'(수익가치 28,184→28,009원) — 공시 후 2주 만에 소수주주 몫을 줄인 조정. 회계상 동일지배 합병이라 장부가 승계. 합병 후 OCN 채널은 CJ E&M 방송부문→CJ ENM 미디어플랫폼 부문에서 계속 운영(2016 사업보고서 채널 목록 'OCN | 드라마ㆍ영화') | AH15: 씨제이이앤엠㈜ (CJ E&M, 코스닥 130960; CJ㈜ 40.19%가 최대주주인 CJ 계열 MPP·엔터테인먼트 회사, 2018-07-01 CJ오쇼핑에 흡수합병돼 현 CJ ENM) | AI15: "5개 방송 자회사들을 통합하여 비용 절감 및 관리조직 일원화 등 경영 효율성을 증대하기 위함" (회사합병결정 합병목적) / "5개 PP(방송채널사용사업) 자회사들을 하나로 통합하여 비용 절감 및 관리조직 일원화 등 운영의 효율화를 도모하고, MPP(복수방송채널사용사업자)로서 합병회사의 브랜드 아이덴티티를 강화" (주요사항보고서 합병의 배경) | AJ15: 케이블·IPTV용 방송채널(MPP, tvN·Mnet·OCN 등 18개 채널 브랜드)과 게임·영화·음악/공연. 2012 연결 매출 1,394,585백만원 중 방송부문 764,151백만원(54.8%)·영업이익 44,554백만원(2012 사업보고서 사업부문별 요약) | AK15: 핵심 | AL15: OCN(영화·장르 채널 OCN·Super Action·Catch On·On Style 등 운영, 2012 매출 2,429억원)은 CJ E&M 방송부문 최대 자회사로 인수 주체 주력 사업 그 자체; 그룹 정점 현 CJ ENM의 미디어플랫폼 부문에서도 OCN 채널을 계속 운영 | AM15: 1,777,340,322천원 (CJ E&M 별도, 2013-06-30; 증권발행실적보고서 '합병 전' 요약재무의 부채와자본총계이며 2013 반기보고서 별도 재무상태표 자산총계 1,777,340백만원과 일치. 같은 증권발행실적보고서 표의 CJ E&M 자산총계 2,294,779,980천원은 투자자산 517,439,659천원이 이중 합산된 표기 오류(차이 517,439,658천원). 참고: 연결 2013-06-30 자산총계 2,092,975백만원) | AN15: acq_total_assets와 같음 (인수 주체 CJ E&M이 상장 지배회사 자신). 참고: 직전 회계연도말 2012-12-31 연결 총자산 2,090,977,463,021원 | AO15: 계산: 1.55 (27,512.8백만원 ÷ 별도 1,777,340백만원, 2013-06-30); 연결 2012-12-31 기준 1.32 | AP15: 계산: 2.37 (27,512.8백만원 ÷ 별도 자기자본 1,158,968백만원, 2013-06-30) | AQ15: 계산: 1,416,929,171,400원 (발표 직전 거래일 2013-08-20 종가 37,350원 × 발행주식총수 37,936,524주(자기주식 377,618주 포함); 주요사항보고서 합병가액 산정표) | AR15: 합병가액·비율은 CJ E&M 주요사항보고서 최종 정정(20130912000216)과 회사합병결정 정정(20130904900112), 중앙일보 보유 주식수는 증권발행실적보고서(20131206000312), 자기자본·총자산은 같은 보고서의 2013-06-30 별도 요약. 공시에 총자산대비 항목이 없어 직접 계산 | AS15: KRX:130960 | AT15: 인수 주체 CJ E&M(코스닥 130960, 2018-07 상장폐지 — Yahoo 시세 없음; 발표 직전 1개월 일별 종가는 주요사항보고서 수록). 대상 OCN은 비상장. 거래 규모가 시가총액의 1.9%라 주가 충격은 작을 것. 상대방 중앙일보는 비상장 | AU15: 2013-08-21: DART CJ E&M '회사합병결정'(5개 방송 자회사 흡수합병); 2013-08-23 오리온시네마네트워크 '회사합병결정'. 사전 보도는 찾지 못함 | AV15: 1999-05-18: OCN 설립, 1999년 ㈜대우 DCN·㈜중앙일보 Catch One 채널사업권 양수; 2000-06: 온미디어 설립 시 50.48% 현물출자; 2006-11-14: 온미디어 주주배정 증자 실권주 인수로 90.27%(C002), 중앙일보 9.73%; 2010-06: 온미디어의 CJ오쇼핑 피인수(C004); 2011-03-01: 온미디어 흡수로 CJ E&M이 90.27% 직접 보유(C009); 2011: OCN 매출 222,297백만원·영업이익 30,929백만원(2012 감사보고서 비교표시 32,032백만원); 2012: 매출 242,856백만원·영업이익 33,657백만원·순이익 22,805백만원, 자산 252,482·자본 216,738백만원 | AW15: 2013-09-04: OCN 합병비율 하향 정정(0.6514056→0.6485944, 'OCN 매출 추정 가정의 변경'); 2013-12-01: 합병기일 — OCN 법인 소멸, ㈜중앙일보사 보유 1,135,721주에 CJ E&M 주식 736,622주 교부(신주권 교부 예정 2013-12-16·합병신주 상장 예정 2013-12-17), 채널은 CJ E&M 방송부문으로; 2013: OCN 매출 242,595백만원·영업이익 23,250백만원(예측 271,812·45,918 대비 11%·49% 미달), 2014: 224,274·34,944백만원(예측 293,483·58,767 대비 24%·41% 미달, '방송 광고시장의 업황 부진'; CJ E&M 2014 사업보고서 합병 사후 비교표); 2016-05: CJ E&M 드라마 사업본부를 스튜디오드래곤으로 물적분할(OCN 채널은 CJ E&M에 잔류, 2016 사업보고서 채널 목록 'OCN | 드라마ㆍ영화'); 2018-07-01: CJ오쇼핑이 CJ E&M 흡수합병, CJ ENM 출범 — OCN은 CJ ENM 미디어플랫폼 부문 채널로 계속; 2020-03-01: CJ ENM이 채널CGV·수퍼액션을 'OCN Movies'·'OCN Thrills'로 개명해 OCN 패밀리 브랜드로 재편(CJ ENM 뉴스룸 2020-03-02); 2025: CJ ENM 미디어플랫폼 부문 외부매출 1조 3,416억원·영업이익 13억원 | AX15: 확인 안 됨 (이 합병은 최상위 지배기업 CJ㈜의 동일지배 종속기업 간 합병으로 장부가 승계 — 새 영업권 없음, CJ E&M 2013 연결감사보고서 주석 35. OCN 관련 영업권은 CJ E&M 방송사업부문 → CJ ENM 미디어플랫폼사업부문 현금창출단위에 포함돼 손상검사. 2013 영업권 손상 957,306천원(같은 해 처분)과 2017 853,984천원은 대상 미특정. CJ ENM 2023 사업보고서 연결 주석: 미디어플랫폼 CGU 영업권 376,118,569천원, 그해 전체 영업권 손상 114,292,880천원은 '사업부문 재구분' 후 회수가능액 미달분으로만 기재돼 CGU 미특정(보도상 피프스시즌 관련, 기사 본문 미대조). CJ ENM 2025 사업보고서: 미디어플랫폼 CGU 영업권 371,615,748천원 유지. 2014~2016·2018~2022·2024 주석은 대조하지 않음) | AY15: 동일지배 합병·그룹 내 이전으로 새 영업권·투자주식 평가가 생기지 않음 | AZ15: 2011: 222,297,461,052원; 2012: 242,856,440,260원 | BA15: 2013: 242,595백만원 (참고: 합병기일까지 2013-01~11 224,097,517천원); 2014: 224,274백만원; 최근 2025(대리지표): CJ ENM 미디어플랫폼 부문 외부매출 1,341,617백만원 — OCN 단독 실적은 2015년 이후 미공시 | BB15: 2011: 32,031,931,093원 (2012 감사보고서 비교표시 — 영업이익 구분표시 회계정책 변경을 소급한 값으로 2012와 같은 기준; 2011 감사보고서 원표시는 30,929,197,125원); 2012: 33,656,826,184원 | BC15: 2013: 23,250백만원; 2014: 34,944백만원 (합병 전 예측 45,918·58,767백만원); 최근 2025(대리지표): CJ ENM 미디어플랫폼 부문 영업이익 1,332,256천원 | BD15: 인수 전은 OCN 별도 K-IFRS 감사보고서(2011: 20120328000227, 2012: 20130326000223; 12월 결산). 인수 후 2013·2014는 CJ E&M 2014 사업보고서(20150331004213) '합병등 전후의 재무사항 비교표' 실적(1차연도 2013·2차연도 2014로 판단; 합병 후 내부 사업 기준), 2013 1~11월은 CJ E&M 2013 연결 주석 35. 2025는 CJ ENM 2025 사업보고서(20260318001469) 미디어플랫폼사업 부문으로 tvN·티빙 등이 섞인 대리지표 | BE15: CJ E&M 2014 사업보고서 합병 사후 비교표: OCN 2014 매출 224,274백만원(예측 293,483, 괴리 24%)·영업이익 34,944백만원(예측 58,767, 41%), 설명 "방송 광고시장의 업황 부진으로 인해 매출 괴리율이 발생 … 킬러 콘텐츠 확보 및 제작역량 강화를 위해 제작투자를 계획대로 진행함에 따라 예측치와의 큰 괴리율". 이 합병을 다룬 IR·어닝콜 언급은 찾지 못함 | BF15: 완료 | BG15: 2026-10-26
A16: C013 | B16: CJ ENM | C16: 2014-05-07 | D16: CJ Educations Corporation | E16: 150 | F16: False | H16: MA② | I16: MA② | J16: 같음 | K16: 있음 | L16: 일치 | M16: 편입 후 | N16: Closed | O16: 1.64 | P16: CJ ENM CO., Ltd. (KOSDAQ:A035760) | Q16: - | R16: CJ O Shopping Co., Ltd. (KOSDAQ:A035760) acquired the remaining 5.21% stake in CJ Educations Corporation for KRW 1.7 billion in cash on April 30, 2014. CJ O Shopping acquired 1.5 million shares of CJ Educations Corporation at a price of KRW 1120 per share. | S16: Education | T16: Education / Childcare | U16: MA-1 그룹이 매수자 | V16: 기존 자회사 잔여지분 | W16: MA② 기존 지분 확대 | Y16: False | Z16: MA② 기존 지분 확대 | AA16: 편입 후 (매수자 ㈜씨제이오쇼핑은 현 CJ ENM 법인 자신: DART 고유번호 00265324, 2018-07-01 CJ E&M을 흡수합병하고 CJ ENM으로 사명 변경. 대상 CJ에듀케이션즈는 2011-11-16 CJ오쇼핑의 유상증자 참여로 종속회사가 됐고 2013-12-31 현재 지분 94.79%의 연결 종속회사 — CJ오쇼핑 2013 사업보고서 20140331003236) | AB16: 완료 (2014-04-30 주식 취득, 지분율 94.79%→100.00%) | AC16: 1,680,000,000원 (보통주 1,500,000주 × 1,120원, 현금; 공정위 공시 '금액(천원) 1,680,000') | AD16: 원자료와 일치 (1,680백만원 ÷ 1,029.44원/달러 = USD 1.63백만; Yahoo Finance KRW=X 2014-04-30 종가 적용, 계산) | AE16: 2014-05-07 | AF16: 기준 분류 유지(MA②): CJ오쇼핑은 2011-11부터 CJ에듀케이션즈의 지배주주였다(2012말 70.00%, 2013-02-15 주주배정 증자에 단독 참여해 94.79%). 이 거래로 비지배주주 지분 5.21%를 사들여 100% 자회사로 만들었다. CJ오쇼핑 2014 사업보고서 연결주석은 이 거래를 '지배력을 상실하지 않으면서 소유지분율이 증가한 거래'로 처리했다(지분취득대가 1,680,000천원, 비지배지분 증감 18,183천원, 기타불입자본 감소 1,698,183천원). 원자료 설명란의 지분·주식수·단가·일자(5.21%, 150만주, 1,120원, 2014-04-30)는 공시와 일치하고, 'KRW 1.7 billion'은 1,680백만원을 반올림한 값이다. 원자료 sellers '-'에 해당하는 매도자는 공시에 '기타 소계(C)'(동일인 측이 아닌 주주)로만 표시돼 이름을 알 수 없다 | AG16: 단독 행(묶음 안 다른 거래와 무관). 대상회사 계보: ㈜올엠인터랙티브(2011-01-04 설립) → 2011-11-16 CJ오쇼핑이 유상증자로 인수 → 씨제이에듀케이션즈㈜로 사명 변경(변경일 미확인) → 이 거래로 100% → 2014-12-31 CJ오쇼핑에 1:0 무증자 흡수합병(이사회 2014-10-27, CJ오쇼핑 쪽은 소규모합병). 사업: 합병 주요사항보고서는 '교육서비스업(영유아)', CJ오쇼핑 연결주석은 '소프트웨어 개발 및 공급'으로 적었다. 언론은 '영유아 교육 콘텐츠 전문 기업'이며 태블릿 기반 학습 프로그램 '나는생각 한글' 등을 낸다고 소개했고(아주경제 2013-11-25), 이 상품은 CJ오쇼핑 TV홈쇼핑에서 팔렸다(뉴스토마토 2013-03-21). 대상회사는 이 거래 전후 모두 큰 영업손실을 냈고(2013 영업손실 104억원), 2014-09-30 자본총계가 -4,322백만원으로 완전자본잠식이었다(합병종료보고서). CJ오쇼핑의 누적 출자는 2011년 약 5,999백만원(계산: 2013말 장부금액 17,899,000천원 − 2013 증자 11,900,000천원) + 2013년 11,900백만원 + 이 거래 1,680백만원 = 19,579,000천원으로, 2014 사업보고서 종속기업투자 '대체' 금액과 일치한다. 이 거래는 그중 마지막 약 8.6%에 불과해, 독립된 '인수'라기보다는 정리 수순(100% 확보 → 8개월 뒤 흡수합병 → 이듬해 영업권 전액 손상)의 한 단계로 보는 것이 맞다. 별도 인수 발표나 보도자료는 없고, 대상회사 명의의 공정거래법 대규모기업집단 공시가 유일한 공식 공시다. 조사 한계: 매도한 비지배주주의 신원, 사명 변경일, 합병 후 교육사업이 언제까지 이어졌는지는 DART와 한국어 웹 검색 4회로 찾지 못했다. 참고: CJ에듀케이션즈는 이재현 CJ그룹 회장의 장녀 이경후가 2011-12~2013-09 근무한 회사로 보도됐다(아이뉴스24 2013-10-11) | AH16: ㈜씨제이오쇼핑 (CJ O Shopping, 코스닥 035760; CJ㈜ 40.06% 자회사; 현 CJ ENM 법인. TV홈쇼핑 사업자이자 CJ헬로비전 53.92% 등을 보유한 연결 지배회사) | AI16: 미확인 — 이 지분 취득의 목적을 밝힌 공시·보도자료가 없다(공정위 공시는 변동 내역만 적는다). 참고: 8개월 뒤 같은 회사를 흡수합병하며 밝힌 합병목적 "조직 효율화, 중복비용 제거 등을 통한 사업 및 운영 효율화 도모" (CJ에듀케이션즈 회사합병결정 공시, 2014-10-27) | AJ16: TV홈쇼핑 중심의 신유통(TV·카탈로그·인터넷·모바일 커머스): 2013 연결 매출 2,513,496백만원 중 신유통 1,389,514백만원, 유선방송업(CJ헬로비전) 1,180,680백만원, 엔터테인먼트 94,382백만원, 기타 17,083백만원(부문 금액은 연결조정 전, CJ오쇼핑 2013 사업보고서 영업부문). 별도 매출 1,260,652백만원 중 대행매출이 65.88% | AK16: 인접 | AL16: 대상 CJ에듀케이션즈는 영유아 교육 콘텐츠·학습 프로그램 개발사라 CJ오쇼핑의 사업(상품 판매 중개)과는 다르다. 그러나 대표 상품 '나는생각 한글'을 CJ오쇼핑 TV홈쇼핑에서 팔았고 주 고객이 20~30대 부모로 홈쇼핑 고객군과 겹친다. 플랫폼에 공급되는 상품·콘텐츠 회사이므로 '인접'으로 본다. 그룹 정점 CJ ENM(현재 미디어·커머스) 기준으로도 커머스 부문에 붙은 인접 영역이고, 미디어 부문과는 관련이 없다 | AM16: 1,136,934,506천원 (㈜씨제이오쇼핑 별도, 2013-12-31; 2013 사업보고서 요약재무정보. CJ에듀케이션즈 회사합병결정 공시의 CJ오쇼핑 2013년 별도 자산총계 1,136,934백만원과 일치) | AN16: acq_total_assets와 같음 (인수 주체가 상장 지배회사 자신). 연결 기준 총자산 3,030,942,895천원 (CJ오쇼핑 연결, 2013-12-31; 2013 사업보고서 요약 연결재무정보) | AO16: 계산: 0.15 (1,680백만원 ÷ CJ오쇼핑 별도 총자산 1,136,935백만원, 2013-12-31). 연결 총자산(3,030,943백만원) 대비 0.06. 주요사항보고서 없음 | AP16: 계산: 0.30 (1,680백만원 ÷ CJ오쇼핑 별도 자본총계 567,185백만원, 2013-12-31) | AQ16: 계산: 2,292,751,655,400원 (발표 직전 거래일 2014-05-02 종가 369,400원 × 발행주식 6,206,691주). 주식수 = 2013-12-31 6,205,272주 + 2014-02-28 스톡옵션 행사 187주 + 2014-04-10 행사 1,232주(2014 사업보고서 자본금 변동표). 참고: 취득일 직전 거래일 2014-04-29 종가 356,700원 | AR16: 총자산·자본: CJ오쇼핑 2013-12-31 별도·연결(2013 사업보고서 20140331003236). 거래 직전 분기말(2014-03-31) 값 대신 감사받은 직전 연도말 값을 썼다. 시가총액: Yahoo Finance 035760.KQ 일별 close. 분할 이벤트가 2010-09 인적분할(0.55:1) 하나뿐이라 2014년 close는 당시 실제 종가로 본다(adjclose는 배당 조정값이라 쓰지 않음). 거래금액은 공정위 공시 20140507000681 | AS16: KRX:035760 | AT16: 인수 주체 ㈜씨제이오쇼핑(코스닥, 현 CJ ENM과 같은 종목코드). 대상 CJ에듀케이션즈는 비상장. 거래 금액이 시가총액의 0.07%라 주가 반응 분석에는 맞지 않는다 | AU16: 2014-05-07: DART 공정거래법 공시 '최대주주등의주식보유변동'(제출인 씨제이에듀케이션즈, 변동일 2014-04-30). 그 전의 보도·조회공시는 찾지 못함(CJ오쇼핑 2014-01~06 공시 목록에 관련 공시 없음) | AV16: 2011-01: ㈜올엠인터랙티브 설립(2011-01-04); 2011-11: CJ오쇼핑 이사회 '타법인 출자 승인의 건'(2011-11-03) 뒤 유상증자(2011-11-16)로 인수, 연결 신규 편입(2011말 자산 6,608백만원); 2011: 매출 254백만원·영업손실 916백만원(검토받은 재무제표); 2012-12: CJ오쇼핑 지분 70.00%; 2012: 매출 155백만원·영업손실 5,187백만원; 2013-02: 주주배정 유상증자 3,400만주 중 CJ오쇼핑만 2,380만주(11,900백만원, 주당 500원) 인수, 지분 70.00%→94.79%; 2013-03: 태블릿 기반 '나는생각 한글'을 CJ오쇼핑 TV홈쇼핑에서 처음 판매(약 6억원); 2013-11: 국제유아교육박람회 참가('나는생각' 한글·사고력·영어); 2013: 매출 9,074백만원·영업손실 10,417백만원·당기순손실 10,574백만원, 2013말 자본총계 1,830백만원 | AW16: 2014-04: 잔여 5.21%(150만주)를 1,680백만원에 취득해 100% 자회사; 2014-10: 양사 이사회 흡수합병 결정(2014-10-27, 1:0 무증자, 목적 '조직 효율화, 중복비용 제거'), 2014-09-30 CJ에듀케이션즈 자본총계 -4,322백만원; 2014-12: 합병기일 2014-12-31, 법인 소멸(합병종료보고서); 2014: 매출 1,321백만원·영업손실 7,730백만원; 2015: CJ오쇼핑 별도 재무제표에서 합병으로 생긴 'CJ에듀케이션즈' 영업권 1,675,555천원 전액 손상; 2018-07: CJ오쇼핑이 CJ E&M을 흡수합병해 CJ ENM 출범. 합병 후 교육사업의 존속·종료 시점은 미확인 | AX16: 있음 (2015, CJ오쇼핑 별도 재무제표의 영업권 'CJ에듀케이션즈(주)' 1,675,555천원 전액 손상차손 — CJ오쇼핑 2015 사업보고서 20160330003245 별도 주석 15 '당사는 당기 중 영업권 1,675,555천원에 대하여 전액 손상차손을 인식'). 이 영업권은 2014-12-31 합병 때 별도 장부에 생긴 것이다(2014 사업보고서 별도 주석 15: 당기말 1,675,555천원, 전기말 '-'). 별도 종속기업투자주식(취득원가 합계 19,579,000천원)은 합병일까지 손상 없이 '대체' 처리됐다. 연결 영업권 표(2014 사업보고서)는 CJ에듀케이션즈를 따로 표시하지 않는다('기타' 3,126,311천원에 들어 있는지는 확인 못함) | AY16: 수집·검토 기록에 인수 뒤 손상이 적혀 있음 | AZ16: 2012: 155백만원; 2013: 9,074백만원 (CJ에듀케이션즈 별도, K-IFRS; 2013은 천원 단위 9,074,337천원) | BA16: 2014: 1,321,089천원 (합병 직전 마지막 사업연도, 2014-01-01~12-31); 2015 이후: 2014-12-31 CJ오쇼핑에 흡수합병돼 법인 소멸, 이어받은 사업의 별도 매출 공시 없음(미확인) | BB16: 2012: -5,187백만원; 2013: -10,417백만원 (CJ에듀케이션즈 별도, K-IFRS; 2013 영업손실은 천원 단위 10,416,851천원) | BC16: 2014: -7,729,732천원 (당기순손실 -9,053,174천원); 2015 이후: 합병으로 소멸, 별도 손익 공시 없음(미확인) | BD16: CJ에듀케이션즈 별도·K-IFRS·12월 결산. 2011~2013: CJ오쇼핑 합병 주요사항보고서(20141027000722)의 최근 3년 요약재무(제1기 2011은 올엠인터랙티브 재무제표로 일반기업회계기준, 안진 검토, 비감사; 2012·2013은 삼일 감사 적정). 2013·2014 천원 단위 값: CJ오쇼핑 2014 사업보고서(20150331003468) 연결주석 '종속기업 요약 경영성과'(내부거래 제거 전, 공정가치 조정 반영 후). 대상회사 자체 감사보고서는 DART 공시 목록(2008~2018 조회)에 없다 | BE16: 미확인 — CJ오쇼핑 2014년 IR 자료·실적발표에서 CJ에듀케이션즈 언급을 찾지 못함(DART의 '기업설명회(IR)개최' 공시는 일정만 있고 자료가 없음, 웹 검색 2회). 참고: 2015 사업보고서 회사의 개요는 합병 효과를 '조직 효율화, 중복비용 제거 등으로 사업 및 운영 효율화를 기대'라고만 적음 | BF16: 부분 | BG16: 2026-10-26
A17: C014 | B17: CJ ENM | C17: 2015-11-02 | D17: CJ Hellovision Co., Ltd., N Screen Service tving Business | E17: 141 | F17: False | H17: MA① | I17: MA① | J17: 같음 | K17: 식별 불가 | L17: 일치 | M17: 편입 후 | N17: Closed | O17: 2.3 | P17: CJ E&M Corporation | Q17: LG HelloVision Corp. (KOSE:A037560) | R17: CJ E&M Corporation (KOSDAQ:A130960) agreed to acquire the N Screen Service tving business from CJ Hellovision Co., Ltd. (KOSE:A037560) for KRW 2.6 billion on November 2, 2015. As per amendment report, CJ E&M Corporation (KOSDAQ:A130960) agreed to acquire the N Screen Service tving business from CJ Hellovision Co., Ltd. (KOSE:A037560) for KRW 2.6 billion on November 2, 2015. Under the revised amendment, CJ E&M Corporation paid KRW 2.61 billion. The Board of Directors of CJ E&M Corporation resolved the transaction on November 2, 2015. | S17: Media Platforms | T17: OTT / Streaming Platform | U17: MA-1 그룹이 매수자 | V17: 지분율 미기재(대개 100%·사업양수) | W17: MA① 경영권 인수 | Y17: False | Z17: MA① 경영권 인수 | AA17: 편입 후 (CJ ENM 전신 계보: 씨제이이앤엠㈜(CJ E&M), 2018-07-01 CJ ENM(옛 CJ오쇼핑)에 흡수합병돼 CJ ENM 계보로 합병. 매도자 ㈜씨제이헬로비전도 당시 최대주주가 ㈜씨제이오쇼핑(현 CJ ENM 법인)인 CJ 계열회사였음 — CJ헬로비전 2015 사업보고서 20160330003207) | AB17: 조건 변경 후 완료 (2016-01-31 거래일자; 최종 양수가액 3,228,000,000원으로 정산 — CJ E&M 2016 사업보고서 20170331004920) | AC17: 계약 체결 시 양수가액 2,612,000,000원(2015-11-02 자율공시; CJ헬로비전 최초 공시 2,600,000,000원은 같은 날 2,612,000,000원으로 기재정정) / 최종 양수가액 3,228,000,000원(2016-01-31 거래, CJ E&M 2016 사업보고서) | AD17: 원자료와 일치 (체결가 2,612백만원 ÷ 1,139.16원/달러 = USD 2.29백만; Yahoo Finance KRW=X 2015-11-02 종가, 계산). 최종 정산가 3,228백만원 ÷ 1,205.63원/달러(KRW=X 2016-01-29 종가, 거래일자 2016-01-31 직전 거래일) = USD 2.68백만으로 원자료 2.3 대비 +16.4%(계산) | AE17: 2015-11-02 | AF17: 분류: 기준 분류 MA① 경영권 인수 유지(수집 단계의 MA④ 변경을 검토에서 되돌림). 근거: subtype_chk는 매수자·매도자가 추출 시점(2024-05) 그룹 계보(그때 그룹에 속한 회사와 그 전신)에 드는지로 판정한다. 매수자 CJ E&M은 2018-07-01 CJ ENM에 합병된 전신이라 계보 안이지만, 매도자 ㈜씨제이헬로비전은 추출 시점에 LG HelloVision Corp.(원자료 sellers 표기, LG유플러스 계열)로 CJ ENM 계보 밖이다. 따라서 계보 밖 회사로부터 사업(티빙)을 양수한 구조 = MA①이며 원자료 분류와 같다. 다만 거래 당시에는 양수법인 CJ E&M과 양도법인 CJ헬로비전이 서로를 '회사와 관계 : 계열회사'로 공시했고(20151102900267, 20151102800059), CJ헬로비전의 최대주주는 ㈜씨제이오쇼핑(현 CJ ENM 법인 자신)이었다(수집 기록 기준 53.92%). 즉 경제적으로는 당시 CJ그룹 계열사 간 사업 양수도였다. 추출 시점 뒤 그룹을 떠난 매도자를 계보 밖으로 볼지(MA①) 거래 당시 기준으로 MA④로 볼지는 사용자 확인 필요. 금액: 원자료 KRW 2.6bn·2.61bn은 계약 체결가(2,612,000,000원)이고, 공시는 '실사결과와 ... 자산, 부채 변동을 감안하여 정산하므로 최종양수도 가액은 변동될 수 있습니다'라고 밝혔으며, 실제 최종 거래금액은 3,228,000,000원(거래일자 2016.01.31)이다(조건 변경 후 완료). 원자료 설명란의 '이사회 결의(2015-11-02)'와 달리 자율공시는 이 양수계약이 이사회 개최 대상에 해당되지 않는다고 적었다. | AG17: 사업양수(자산거래: 티빙의 무형자산·영업권 등 영업부문 일부). 2015-11-02 같은 날 CJ오쇼핑이 CJ헬로비전 지분 30%를 SK텔레콤에 양도하기로 결의하고 CJ헬로비전이 SK브로드밴드와 합병을 결정했다(CJ헬로비전 2015 사업보고서). 추정: 티빙은 이 매각 직전에 CJ헬로비전에서 CJ E&M으로 떼어낸 것으로 보인다(근거: 같은 날 이사회 결의, 양도목적 '티빙스틱을 통한 TV OTT 사업 집중'). SKT 합병은 2016-07-25 SK브로드밴드의 합병계약 해제 통보로 무산(CJ헬로비전 자율공시 20160725800494). 묶음 내 C019(Tving Co.,Ltd)는 이 사업이 2020-10-01 물적분할돼 생긴 법인 관련 거래로 같은 사업 계보다. 이 거래는 주요사항보고서 제출 대상이 아닌 자율공시이며, CJ E&M 측은 이사회개최 대상이 아니라고 적었다(원자료 comment의 '이사회 결의'는 CJ헬로비전 측 이사회 결의 2015-11-02와 맞음). 대상 사업의 인수 전 매출·이익은 CJ헬로비전 '부가서비스'(헬로폰·tving·헬로모바일 합산)에 묶여 분리 공시가 없어 미확인. 인수 후 2016~2020-09 티빙 실적도 CJ E&M/CJ ENM 방송부문 안에 있어 별도 공시 미확인. CJ E&M은 2018-07 합병으로 상장폐지돼 Yahoo Finance 일별 종가가 없어(조회 결과 'symbol may be delisted') 시가총액은 월평균 주가로 추정. 동일지배하 사업결합이므로 회계처리(장부금액법 여부)와 영업권 인식액은 미확인. 2017년 이후 CJ ENM 사업보고서·IR 자료, ㈜티빙 감사보고서는 예산 한도로 미조사. | AH17: 씨제이이앤엠㈜ (CJ E&M Corporation, 코스닥 130960; CJ㈜ 계열 상장사, 현 CJ ENM의 전신으로 2018-07-01 CJ오쇼핑에 흡수합병) | AI17: "자체 OTT(Over The Top) 플랫폼 강화" (CJ E&M 기타주요경영사항 자율공시, 양수목적) / "티빙스틱을 통한 TV OTT(Over The Top) 사업 집중" (CJ헬로비전 자율공시, 양도목적) | AJ17: 방송·영화·음악·공연 콘텐츠 사업. 2015년 연결 매출 1,347,314백만원 중 방송부문 909,478백만원(67.5%), 영화 238,346백만원(17.7%), 음악 184,112백만원(13.7%), 공연 15,378백만원(1.1%) (CJ E&M 2015 사업보고서 사업부문별 요약). 방송부문 전략에 '모바일 OTT 기반의 디지털 유통 강화'가 포함 | AK17: 인접 | AL17: CJ E&M은 tvN·Mnet 등 채널(PP)과 콘텐츠 제작사였고, 티빙은 그 채널·VOD를 소비자에게 직접 유통하는 OTT 플랫폼으로 같은 가치사슬의 하류(유통) 영역이다. 인수 주체가 당시 상장 CJ 계열사 자신이고, 현 CJ ENM 정점 기준으로도 콘텐츠 기업의 자체 플랫폼 확보이므로 인접. | AM17: 연결 총자산 2,357,385백만원, 연결 자본총계 1,505,703백만원 (2014-12-31, CJ E&M 2015 사업보고서 요약 연결재무정보 전기 수치). 참고: 2015-12-31 연결 총자산 2,364,855백만원 | AN17: acq_total_assets와 같음 (인수 주체 CJ E&M이 상장사 자신) | AO17: 계산: 0.11 (체결가 2,612백만원 / 2014-12-31 연결 총자산 2,357,385백만원); 최종가 기준 0.14 (3,228 / 2,357,385) | AP17: 계산: 0.17 (2,612백만원 / 2014-12-31 연결 자본총계 1,505,703백만원); 최종가 기준 0.21 (3,228 / 1,505,703) | AQ17: 추정: 약 3조 3,105억원 (2015년 10월 일평균 주가 85,471원 × 발행주식총수 38,732,089주; 10월 최저 81,300원~최고 91,000원 기준 범위 약 3조 1,489억~3조 5,246억원). 2015-10-30 실제 종가는 미확인 | AR17: 총자산·자본: 2014-12-31 연결(직전 회계연도말), CJ E&M 2015 사업보고서(20160330003711). 주가: 같은 보고서 주가 및 주식거래실적의 2015년 10월 월간 통계(월최고 91,000·월최저 81,300·일평균 85,471원). 발행주식수 38,732,089주는 2015-12-31 기준(10월 말과 같다고 가정). 거래 비율은 공시에 없어 직접 계산. | AS17: KRX:130960 | AT17: 인수 주체 CJ E&M이 코스닥 상장사(2018-07 합병으로 상장폐지). 양도법인 CJ헬로비전은 유가증권시장 상장사 KRX:037560(현 LG헬로비전). 주의: 2015-11-02 같은 날 SKT의 CJ헬로비전 지분 인수·SK브로드밴드 합병 결정이 함께 나와 이 날짜의 주가 반응을 티빙 양수만으로 해석하기 어렵다(교란). 거래 규모도 시총 대비 약 0.08%로 매우 작다. | AU17: 2015-11-02 DART 자율공시: CJ E&M 기타주요경영사항(자율공시)(영업양수체결)(20151102900267), CJ헬로비전 기타경영사항(자율공시)(20151102800021, 같은 날 기재정정 20151102800059). 사전 보도는 확인하지 못함 | AV17: 2010-06: CJ헬로비전이 국내 최초 웹TV '티빙(tving)' 개시; 2010-12: 티빙 가입자 100만 돌파; 2011-07: 가입자 200만 돌파; 2012-02: 오픈플랫폼 '티빙에어' 출시; 2014-08: CJ헬로비전 동글형 OTT '티빙스틱' 출시; 2015: 티빙스틱 전용 리모컨 제공(TV OTT 집중); 2015-11-02: CJ오쇼핑 이사회가 CJ헬로비전 지분 30%의 SK텔레콤 양도를 결의하고 CJ헬로비전이 SK브로드밴드와의 합병을 결정, 같은 날 CJ헬로비전 이사회가 티빙 영업일부 양도 가결 | AW17: 2016-01-31: 영업양수 거래 완료, 최종가 3,228백만원; 2016-07-25: SK브로드밴드가 CJ헬로비전에 합병계약 해제 통보(SKT 인수 무산); 2016-12-21: CJ E&M이 2017-01-03부터 티빙 실시간 153개 채널 전면 무료화, VOD는 유료 유지 발표(아시아경제); 2018-07-01: CJ E&M이 CJ오쇼핑에 흡수합병돼 CJ ENM 출범(티빙은 CJ ENM 사업부로); 2019-09-17: CJ ENM·JTBC 합작 OTT 법인 설립 MOU(위키백과); 2020-10-01: 티빙 사업부 물적분할로 ㈜티빙 출범(위키백과; 묶음 C019 관련); 2021-06-30: 네이버 ㈜티빙에 400억원 투자 발표(위키백과); 2022-07: KT 시즌과 티빙 합병 발표, 2022-10 공정위 승인(위키백과); 2023-12: 티빙–웨이브 합병 논의 시작; 2025-06: 공정위 조건부 승인; 2026-05: 2대 주주 KT스튜디오지니의 미동의로 합병 지연(딜사이트 2026-05-21) | AX17: 확인 안 됨 (CJ E&M 2016 사업보고서 연결주석 '영업권 등의 손상검사': 손상검사 대상 현금창출단위는 방송사업부문·음악사업부문·㈜메조미디어·에이오엠지㈜로 티빙 별도 단위 없음, 손상 인식 기재 확인 못 함. 2017년 이후 CJ E&M·CJ ENM 보고서는 미조사) | AY17: 티빙이 별도 현금창출단위가 아니라 방송사업부문에 묶여 개별 손상을 알 수 없음 | AZ17: 미확인 (CJ헬로비전 2015 사업보고서에서 tving 매출은 '부가서비스'(헬로폰·tving·헬로모바일·SO 경영지원) 2015년 315,767,160천원에 합산돼 분리되지 않음) | BA17: 2016: 미확인; 2017: 미확인 (CJ E&M 방송부문 안 사업으로 별도 공시 없음); 2024: 4,355억원; 2025: 4,060억원 (㈜티빙, 딜사이트 2026-05-21 보도, 별도/연결 미기재) | BB17: 미확인 (사업부문별 영업이익 분리 공시 없음) | BC17: 2016: 미확인; 2017: 미확인; 2025: 영업손실 698억원, 순손실 893억원 (㈜티빙, 딜사이트 2026-05-21 보도). 같은 기사는 2020년 분할 설립 뒤 '매년 적자'라고 씀 | BD17: 인수 전: CJ헬로비전 2015 사업보고서(K-IFRS, 12월 결산) 매출 구성표 — tving 단독 수치 없음. 인수 후: 2016~2020-09 티빙은 CJ E&M·CJ ENM 내부 사업부여서 법인 실적 없음; 2020-10 물적분할 뒤 ㈜티빙 실적은 언론 보도(딜사이트) 재인용, ㈜티빙 감사보고서 원문은 미조사 | BE17: 2016-12-21: CJ E&M 티빙 2차 개편 발표 — 무료 실시간 채널로 소비자가 콘텐츠를 '더 쉽고, 편하게' 접하도록 하겠다는 회사 설명(아시아경제 보도, 실적·가입자 수치 미공개). CJ E&M·CJ ENM IR 자료와 어닝콜에서 티빙 언급은 미조사 | BF17: 부분 | BG17: 2026-10-26
A18: C015 | B18: CJ ENM | C18: 2018-08-29 | D18: Highup Entertainment Co., Ltd. | E18: 174 | F18: False | H18: MA⑦ | I18: MA⑤ | J18: 변경 | K18: 해당 없음 | L18: 일치 | M18: 편입 후 | N18: Closed | O18: 0.23 | P18: - | Q18: CJ ENM CO., Ltd. (KOSDAQ:A035760) | R18: Jooyoung Song and Kyusung Choi acquired 51% stake in Highup Entertainment Co., Ltd. from CJ ENM CO., Ltd. (KOSDAQ:A035760) for approximately KRW 260 million on August 27, 2018. Under the transaction, Jooyoung Song and Kyusung Choi acquired 0.026 million shares at KRW 5,000 per share respectively. | S18: Music & Fan Entertainment | T18: Music / Artist Management | U18: MA-5 매수자 미기재 | W18: MA⑦ 매수자 미기재 | Y18: False | Z18: MA⑤ 그룹의 지분 매각 | AA18: 편입 후 (매도자 ㈜씨제이이엔엠 = CJ ENM 본체. 지분은 CJ E&M이 2017-06-30 설립 출자로 취득했고 2018-07-01 CJ E&M→CJ ENM 합병으로 승계(2018-07-06 공정거래법 공시). 대상회사는 2017-08-01 CJ 기업집단 계열편입, CJ E&M 연결 종속기업) | AB18: 완료 (2018-08-27 주식 변동일) | AC18: 255,000,000원 (51,000주 × 주당 5,000원 = 액면가. 2018-08-29 공정거래법 공시 '255,000천원') | AD18: 원자료와 일치 (원자료 설명란 KRW 약 260백만원 대비 확인값 255백만원, 차이 약 2%) | AE18: 2018-08-29 | AF18: MA⑦ 매수자 미기재 → MA⑤ 그룹의 지분 매각. 근거: 하이업 2018-08-29 '최대주주등의주식보유변동'(20180829000249)에 ㈜씨제이이엔엠 51,000주(51.00%) 전량 처분, 송주영·최규성(하이업 임원)이 각 25,500주 취득해 각 50.00%가 됨. 매수자는 그룹 밖 개인 2명(하이업 공동대표이사)이므로 MA⑤. 원자료 설명란의 '0.026 million shares respectively'는 각 25,500주의 반올림이고, 금액 KRW 260백만원은 실제 255,000천원의 근사치. | AG18: CJ ENM이 2017년 블랙아이드필승 측과 설립한 음악 레이블(51%)을 1년여 만에 액면가에 공동대표 2인에게 전량 넘긴 엑시트 거래. 매각 직후 2018-08-30 이사회에서 하이업이 ㈜카카오엠을 대상으로 사모 전환사채 20억원(납입 2018-09-19)을 발행해 카카오 계보 자금이 들어왔고, 하이업은 2021-05-01 카카오 기업집단에 계열편입(㈜카카오엔터테인먼트 93,333주, 40%). 이 카카오엠 CB 인수·카카오엔터 지분 취득은 카카오 계보 쪽 별도 거래로, 다른 묶음에 있을 수 있다(이중 집계 확인 필요). 카카오엔터 40%가 2018 CB 전환에서 나왔는지는 문서로 확인하지 못함(전환가액 미공시). CJ ENM은 2018년 중 하이업 채무증권 1,000백만원도 처분(2018 사업보고서 별도주석 *2; 연결 채무증권 발행실적표에는 하이업 조건부자본증권 1,000백만원 '상환'으로 표기). 2018-08-27 CJ ENM 측 이사 3명(정형진 상무·공종윤 부장·상승현 과장)과 감사가 해임됨. 상승현(당시 CJ ENM 음악사업국 투자팀 과장)은 2023·2024년 말 하이업 주주(8.4%)로 기재. CJ 기업집단 공시는 2018-09-06 이후 없고 정확한 CJ 계열제외일은 미확인. 조사 한계: 2018·2019 회계연도 하이업 실적은 대규모기업집단 공시·감사보고서가 없어 미확인(2019~2020년 공시 공백). 매각 목적을 밝힌 공시·보도는 찾지 못함(CJ ENM 측 공시 없음, 금액이 공시 기준 미달로 보임). 웹 검색(한국어) 1회로 매각 보도는 찾지 못함. | AH18: 송주영·최규성 (개인 2인, ㈜하이업엔터테인먼트 공동대표이사·설립자, 그룹 밖). CJ E&M 2017 사업보고서는 하이업을 '하이업뮤직(블랙아이드필승 등)'으로 기술. 매도자는 ㈜씨제이이엔엠(CJ ENM, 그룹 지배회사, KOSDAQ 상장) | AI18: 미확인 (매각 목적을 밝힌 공시·보도 없음). 참고로 설립 당시 맥락: "앞으로도 지속적으로 음악 콘텐츠 및 아티스트IP 확보하여 음악사업 확대에 주력할 예정입니다" (CJ E&M 2017 사업보고서, 하이업뮤직 설립을 언급한 음악사업 현황) | AJ18: 매수자는 개인(대상회사 경영진·프로듀서). 매도자 CJ ENM(2018-07 CJ오쇼핑+CJ E&M 합병 법인)의 핵심 사업은 미디어·커머스·영화·음악 부문 | AK18: 해당 없음 | AL18: 그룹이 파는 쪽인 매각 거래라 인수 주체 기준 판단은 해당 없음. 그룹(CJ ENM) 기준 대상회사는 음악사업부문의 서브레이블(작곡·음반기획)로 음악 부문 안의 소규모 레이블이었다. CJ E&M은 2017년 젤리피쉬·아메바컬쳐 인수, 하이어뮤직·하이업 설립으로 레이블을 늘렸고 하이업은 그중 하나. | AM18: 해당 없음 (매수자 개인). 참고 매도자 기준: 아래 apex_total_assets | AN18: 매도자 CJ ENM 2017-12-31 연결 총자산 2,801,818백만원(합병 전 CJ오쇼핑 기준, CJ ENM 2018 사업보고서 비교수치). 참고: 지분 원보유자 CJ E&M 2017-12-31 연결 총자산 3,758,919,984,666원; 합병 후 CJ ENM 2018-12-31 연결 총자산 6,754,948백만원 | AO18: 계산: 255백만원 / 2,801,818백만원(CJ ENM 2017-12-31 연결 총자산) = 0.0091% (매도자 기준; 2018-12-31 합병 후 6,754,948백만원 기준 0.0038%) | AP18: 계산: 255백만원 / 1,484,104백만원(CJ ENM 2017-12-31 연결 자본총계) = 0.0172% (매도자 기준) | AQ18: 계산: 259,200원(2018-08-24 종가, Yahoo Finance 035760.KQ) × 21,926,384주(2018-12-31 발행주식총수, CJ ENM 2018 사업보고서; 추정: 2018-07 합병신주 발행 후 8월에도 동일) = 5,683,318,732,800원 (매도자 CJ ENM, 매수자는 개인) | AR18: 거래 금액은 2018-08-29 하이업 공정거래법 공시. 총자산·자본은 CJ ENM 2018 사업보고서(정정, 20190404001725) 연결 요약재무정보, CJ E&M 2017 사업보고서(20180330004046) 연결재무상태표. 시가총액은 매각 변동일(2018-08-27, 월) 직전 거래일 2018-08-24 종가 기준. 매수자가 개인이라 인수 주체 규모 지표는 매도자 기준 참고값. | AS18: KOSDAQ:035760 | AT18: 매수자가 개인이라 상장 종목 없음. 매도자 CJ ENM(KOSDAQ 035760)을 참고 종목으로 둔다. 대상회사 하이업은 비상장. 거래 규모가 CJ ENM 총자산의 0.01% 미만이라 주가 반응 분석의 의미는 거의 없음. | AU18: 2018-08-29 DART 공정거래법 공시(하이업 '최대주주등의주식보유변동'). 이보다 이른 보도는 찾지 못함 | AV18: 2017-06-14: ㈜하이업엔터테인먼트 설립(음반기획·제작·매니지먼트, 서울 마포구 연남동); 2017-06-30: CJ E&M이 51,000주(51%)를 255백만원에 출자 취득(경영참여), 송주영·최규성 각 24,500주(24.5%) 보유, CJ E&M 연결 종속기업 '신규 설립' 편입; 2017-08-01: CJ 기업집단 계열편입; 2017: CJ E&M 사업보고서가 '하이업뮤직(블랙아이드필승 등)을 설립'이라고 기술(같은 해 젤리피쉬·아메바컬쳐 인수, 하이어뮤직 설립); 2017 FY: 매출 52백만원, 영업손실 343백만원, 순손실 380백만원, 자산 1,177백만원, 자본 120백만원(자본금 500백만원), 하이업 조건부자본증권 1,000백만원(1%, 만기 2022-06-02)이 CJ E&M 연결 채무증권 발행실적표에 기재; 2018-07-01: CJ E&M이 CJ오쇼핑에 흡수합병돼 ㈜씨제이이엔엠이 51% 승계 | AW18: 2018-08-27: CJ ENM 51,000주 전량을 송주영·최규성에게 주당 5,000원(총 255백만원)에 매각, 두 사람 각 50%; 2018-08-27: CJ ENM 측 이사 3명·감사 해임(2018-08-31 등기); 2018-08-30: 이사회에서 ㈜카카오엠 대상 사모 전환사채 2,000백만원 발행 결정(표면 1%, 만기 2023-09-19, 납입 2018-09-19); 2018: CJ ENM이 하이업 채무증권 1,000백만원 처분, 연결범위에서 '매각'으로 제외, 별도 기준 종속기업투자주식처분이익 255백만원 인식; 2020-11-12: 걸그룹 STAYC 데뷔; 2020 FY: 매출 253백만원, 영업손실 2,292백만원, 자본총계 -4,291백만원(자본잠식); 2021-05-01: 카카오 기업집단 계열편입, ㈜카카오엔터테인먼트 93,333주(40%), 최규성 30%; 2021 FY: 매출 4,627백만원, 영업손실 1,363백만원; 2023 FY: 영업수익 14,262백만원, 영업이익 1,247백만원; 2024 FY: 영업수익 7,960백만원, 영업손실 3,028백만원, 주주 최규성·송주영 각 21.6%·최진우·상승현 각 8.4%·카카오엔터 40%, 카카오엔터 관련 전환사채 액면 4,000백만원; 2025-01-09: '특수관계인에대한전환사채발행' 공시(제목만 확인) | AX18: 확인 안 됨 (CJ E&M 2017 사업보고서 타법인출자현황에서 하이업 장부가 255백만원 유지, 손상 기재 없음. CJ ENM 2018 사업보고서 별도주석: 사업결합으로 장부금액 승계 후 지분매각으로 처분이익 255백만원 인식 → 추정: 매각가 255백만원과 같은 처분이익이므로 승계 장부금액은 0으로 보이나 손상차손 계상 문구는 찾지 못함) | AY18: 그룹의 지분 매각(MA⑤)이라 매수자 쪽 손상을 따지지 않음 | AZ18: 2016: 해당 없음 (2017-06-14 설립); 2017: 52백만원 | BA18: 2018: 미확인; 2019: 미확인; (참고 2020: 253백만원; 2021: 4,627백만원; 2023: 14,262백만원); 2024: 7,960백만원 (영업수익 7,959,572,978원) | BB18: 2016: 해당 없음 (설립 전); 2017: -343백만원 | BC18: 2018: 미확인; 2019: 미확인; (참고 2020: -2,292백만원; 2021: -1,363백만원; 2023: 1,247백만원); 2024: -3,028백만원 (영업손실 3,028,128,139원) | BD18: 하이업 별도 기준, 12월 결산. 2017: 2018-05-31 CJ 대규모기업집단현황공시(단위 백만원). 2020: 2021-05-28 카카오 대규모기업집단현황공시. 2021: 2022-05-31 같은 공시. 2023·2024: 하이업 2024 감사보고서(현대회계법인, 2025-04-01 제출, 영업수익·영업이익(손실), 단위 원). 2018·2019는 하이업이 어느 대규모기업집단에도 속하지 않고 감사보고서 공시도 없어 미확인. 매각 거래라 '인수 후'는 그룹 이탈 후 대상회사 실적이다. | BE18: 미확인 (CJ ENM IR 자료·어닝콜은 검토하지 않음. 거래 금액 255백만원으로 매도자 연결 총자산의 0.01% 미만이라 IR 언급 가능성은 낮음) | BF18: 부분 | BG18: 2026-10-26
A19: C016 | B19: CJ ENM | C19: 2019-03-25 | D19: GTIST | E19: 66 | F19: False | H19: MA① | I19: MA① | J19: 같음 | K19: 있음 | L19: 일치 | M19: 편입 후 | N19: Closed | O19: 22.08 | P19: Studio Dragon Corporation (KOSDAQ:A253450) | Q19: - | R19: Studio Dragon Corporation (KOSDAQ:A253450) agreed to acquire GTIST for KRW 25 billion on March 25, 2019. Studio Dragon Corporation will acquire 0.2 million. The transaction has been approved by the Board of Directors of Studio Dragon and is expected to be completed on April 8, 2019. | S19: Content Production & Investment | T19: Content Production Studio | U19: MA-1 그룹이 매수자 | V19: 지분율 미기재(대개 100%·사업양수) | W19: MA① 경영권 인수 | Y19: False | Z19: MA① 경영권 인수 | AA19: 편입 후 (매수자 스튜디오드래곤㈜는 거래 당시 CJ ENM의 연결 종속회사. 지티스트 2019 감사보고서 특수관계자 주석: 지배기업 스튜디오드래곤(주), 차상위지배기업 (주)씨제이이엔엠, 최상위지배기업 CJ(주)) | AB19: 완료 (2019-04-08) | AC19: 25,000,000,000원 (현금, 지티스트 보통주 200,000주 = 100%) | AD19: 원자료와 일치 (원자료 22.08 = 250억원/약 1,132원/달러, 2019-03 환율 수준) | AE19: 2019-03-25 | AF19: 기준 분류 유지: 스튜디오드래곤이 지티스트 발행주식 200,000주(100%)를 현금 250억원에 취득해 종속회사로 편입(취득 전 보유 지분 없음, 공시 '취득후 소유주식수 200,000주, 지분비율 100.0'). 금액·완료일(공시 취득예정일 2019-04-08, 연결주석 취득일 2019-04-08)도 원자료와 일치. | AG19: 원자료 sellers는 '-'. 공시 '상대방에 관한 사항'에는 상대방이 주식회사 지티스트 자신으로 적혀 있고 그 최대주주 (주)지티엔터테인먼트 38.0%, 대표이사 이동규 10.0%만 나온다(나머지 52% 보유자 미기재). 실제 구주 매도자 구성은 미확인. 같은 묶음 C013·C014·C015·C019와는 대상회사가 달라 직접 관계 없음(C019는 CJ ENM의 티빙 지분 확대). 연결주석상 이전대가 250억원 중 식별가능순자산 8,684,796천원(무형자산 전속계약금 10,515,404천원 포함), 영업권 16,315,204천원. 지티스트는 2020·2021년 감사보고서가 DART에 없어(외부감사 미대상 추정) 그 해 실적은 스튜디오드래곤 연결주석 '주요 종속기업 요약 재무정보'(매출·순이익만)로 채움. 2018 실적은 2019 감사보고서의 비교표시 전기(감사받지 않은 재무제표, K-IFRS 전환). | AH19: 스튜디오드래곤㈜(CJ ENM 자회사, 코스닥 상장) | AI19: "우수 크리에이터 및 제작 역량 확보" (거래소 공시 타법인주식및출자증권취득결정) / "크리에이터와 관계를 강화하고 장기적인 협업구조를 구축하여 국내외 드라마 시장 경쟁력 강화 및 수익성 극대화 추진을 위해" (2019 사업보고서 연결주석 사업결합) / "콘텐츠의 양보다 질이 중요해지는 미디어 환경변화 속에서 우수 크리에이터 확보는 스튜디오 경쟁력 강화의 핵심" (회사 관계자, 인사이트 2019-03-25 보도) | AJ19: 드라마 기획·제작·유통. 2018 연결매출 379,606백만원 중 드라마 편성 178,062(46.91%), 드라마 판매 162,054(42.69%), 기타 39,490(10.40%) (2019 사업보고서 II. 사업의 내용 매출 표의 전기) | AK19: 핵심 | AL19: 지티스트 주요사업 '방송 드라마 제작 및 공급'(공시)은 스튜디오드래곤 주력인 드라마 제작과 같은 영역. 그룹 정점 CJ ENM 기준으로도 미디어(방송·콘텐츠) 부문의 드라마 제작 역량 확대라 핵심. | AM19: 459,453,883,583원 (공시 '최근 사업연도말 자산총액', 2017년도말 연결재무제표 기준이라고 공시에 명기) | AN19: 6,754,948백만원 (CJ ENM 2018-12-31 연결 자산총계, 2018 사업보고서 [기재정정] 요약재무정보) | AO19: 5.4 | AP19: 6.2 | AQ19: 계산: 2,544,270,143,000원 (2019-03-22 종가 90,700원 × 발행주식총수 28,051,490주) | AR19: 총자산·비율은 2019-03-25 거래소 공시(자기자본 401,285,512,072원 = 2017 연결 자본총액에 2018 증감 반영 기준, 취득금액 250억원). 시가총액은 발표 직전 거래일 2019-03-22 Yahoo Finance 253450.KQ 종가(스튜디오드래곤은 그 뒤 액면분할·무상증자를 찾지 못해 조정 없이 사용)와 2018 사업보고서 발행주식총수 28,051,490주. 지배회사 총자산은 CJ ENM 2018 사업보고서. | AS19: KOSDAQ:253450 | AT19: 인수 주체 스튜디오드래곤이 코스닥 상장사. 상장 지배회사 CJ ENM(KOSDAQ:035760)도 보조로 쓸 수 있음. 대상회사 지티스트는 비상장. | AU19: 2019-03-25 (거래소 공시 '타법인주식및출자증권취득결정', 접수번호 20190325900541). 공식 발표 전 인수설 보도는 찾지 못함. 같은 날 2019-03-25 15:59 인사이트가 공시 내용과 회사 관계자 발언을 보도했고, 다음 날 2019-03-26 인사이트가 한국투자증권 리포트와 함께 재보도. | AV19: 2017-01: ㈜지티스트 설립(서울 마포구 상암동, 드라마 제작; 2019 감사보고서 주석 1); 2017: 매출 1,404백만원, 당기순손실 93백만원, 자본총계 107백만원(공시 요약재무, 별도·외감 대상 아님); 2018-03: tvN '라이브'(극본 노희경, 연출 김규태)를 지티스트와 스튜디오드래곤이 공동제작(아주경제 2018-03-06 제작발표회 보도 '제작 지티스트, 스튜디오드래곤') — 인수 주체와의 인수 전 제작 협업; 2018: 매출 11,535백만원, 영업이익 86백만원으로 급증(2019 감사보고서 비교표시); 2019-03 이전: 최대주주 ㈜지티엔터테인먼트 38.0%, 대표이사 이동규 10.0%(인수 공시 '상대방에 관한 사항'), 노희경 작가·김규태·홍종찬 연출 등 소속(언론); 배경: 스튜디오드래곤은 화앤담픽쳐스·문화창고·KPJ를 100% 자회사로 두고 크리에이터 확보형 인수를 해 왔고 지티스트는 그 연장(2019 연결주석 종속기업 목록, 인사이트 2019-03-26) | AW19: 2019-04-08: 100% 취득 완료, 연결 편입(영업권 16,315백만원), 이동규 대표이사 취임(2019-04-08, 대규모기업집단현황공시 임원현황); 2019: 매출 22,984백만원, 영업이익 484백만원(별도 감사); 2020: 매출 438백만원, 영업손실 491백만원, 순손실 534백만원(제작 공백); 2021: 매출 12,297백만원, 순이익 2,083백만원; 2022: 매출 46,590백만원, 순이익 3,280백만원(스튜디오드래곤 2023 사업보고서 연결주석), 영업이익 48억원('우리들의 블루스'·'소년심판' 참여, 딜사이트); 2023: 매출 18,080백만원, 순손실 2,502백만원, 영업권 16,315백만원 유지(손상 없음); 2024: 매출 14,567백만원, 영업손실 1,119백만원, 순손실 549백만원, 영업권 손상 약 5,854백만원(계산); 2025: 매출 65백만원, 영업손실 1,984백만원, 순손실 1,776백만원, 영업권 손상 약 532백만원(계산), 2025말 영업권 9,929백만원; 2026-03: 2025 감사보고서상 대표이사 이동규 유지, 스튜디오드래곤 지분 100% 유지; 2026-05: 대규모기업집단현황공시(2026-05-01 기준)상 이동규 대표이사 유지(임기 2028-04-08), 기타비상무이사 장경익(스튜디오드래곤 대표이사)·유상원; 2026-2분기: 지티스트가 제작한 넷플릭스 '맨 끝줄 소년'을 스튜디오드래곤이 공급(MTN 2026-09-30); 2026-08: 딜사이트가 지티스트 제작 공백과 실적 급감을 보도 | AX19: 있음 (2024: 지티스트 현금창출단위 영업권 16,315,205천원→10,461,224천원, 감소분 5,853,981천원 계산 — 그해 CGU별 감소 합계가 연결 영업권손상차손 15,869,556천원과 정확히 일치, 스튜디오드래곤 2024 사업보고서 연결주석; 2025: 10,461,224천원→9,929,142천원, 532,082천원 계산, 스튜디오드래곤 2025 사업보고서 연결주석. 2019~2023은 지티스트 영업권 16,315,205천원 그대로로 손상 없음, 2023 사업보고서 연결주석 CGU 표) | AY19: 수집·검토 기록에 인수 뒤 손상이 적혀 있음 | AZ19: 2017: 1,404백만원; 2018: 11,535백만원 | BA19: 2019: 22,984백만원; 2020: 438백만원; 2025: 65백만원 | BB19: 2017: 미확인 (공시에는 당기순손실 93백만원만 있음); 2018: 86백만원 | BC19: 2019: 484백만원; 2020: -491백만원; 2025: -1,984백만원 | BD19: 모두 지티스트 별도, 12월 결산. 2017은 인수 공시의 발행회사 요약 재무상황(2017 별도, 외부감사 없음, 일반기업회계기준). 2018·2019는 지티스트 2019 감사보고서(K-IFRS 최초 적용, 2018 비교표시는 감사받지 않은 재무제표, K-GAAP 기준 2018 영업이익은 89백만원 — 2019-05-31 대규모기업집단현황공시 손익현황도 2018 매출 11,535·영업이익 89백만원). 2020 매출·순이익은 스튜디오드래곤 2021 사업보고서 연결주석 종속기업 요약 재무정보(매출 438,005천원, 당기순손실 534,456천원), 2020 영업이익 -491백만원은 지티스트 대규모기업집단현황공시(2021-05-31, 접수번호 20210531001821) '회사 손익현황'(2020-12-31 기준, 백만원, 개별; 같은 표의 당기순이익은 -538백만원으로 연결주석 값과 4백만원 차이, 연결주석 값을 유지). 2025는 지티스트 2025 감사보고서(삼정회계법인)이며 2026-06-01 대규모기업집단현황공시 손익현황(매출 65, 영업이익 -1,984, 당기순이익 -1,776백만원)과 일치. 참고로 2019 연결 요약재무(지배력 획득 이후분)는 매출 12,914,985천원, 순이익 172,023천원. | BE19: 2019-03-26 한국투자증권 최민하 연구원(인사이트 재인용): "지티스트 인수를 통해 연간 3~4편의 추가 제작 역량을 확보할 것으로 예상된다"; 2020-02-13 엑스포츠뉴스(2019 실적 보도): 핵심 크리에이터 수가 노희경 작가가 속한 지티스트 인수 등에 힘입어 197명으로 39명 늘었다고 보도; 2026-08-26 딜사이트: 스튜디오드래곤 관계자 "제작 자회사 인수는 경쟁력 강화를 위해 크리에이터 풀을 확보한다는 개념이 가장 중요하다". 스튜디오드래곤 IR 원자료(실적발표 PDF)에서의 지티스트 직접 언급은 찾지 못함 | BF19: 완료 | BG19: 2026-10-26
A20: C017 | B20: CJ ENM | C20: 2021-02-04 | D20: Media Commerce Service Business and Assets of CJ ENM CO., Ltd. | E20: 123 | F20: False | H20: MA④ | I20: MA④ | J20: 같음 | K20: 있음 | L20: 일치 | M20: 편입 후 | N20: Closed | O20: 5.06 | P20: DADA MNC CO.,Ltd | Q20: CJ ENM CO., Ltd. (KOSDAQ:A035760) | R20: DADA MNC CO.,Ltd acquired Media Commerce Service Business and Assets of CJ ENM CO., Ltd. for approximately KRW 5.7 billion on February 4, 2021. The board of directors of CJ ENM CO., Ltd. resolved the deal on February 4, 2021. | S20: Commerce & Marketing | T20: E-commerce / Marketplace | U20: MA-2 그룹 내부 재편 | W20: MA④ 그룹 내부 재편 | Y20: False | Z20: MA④ 그룹 내부 재편 | AA20: 편입 후 (매도자는 CJ ENM 본체이고, 매수자 ㈜다다엠앤씨는 2020-12-01 CJ ENM이 100% 출자해 설립한 종속회사다. 다다엠앤씨 최대주주등의주식보유변동 공시(20210528001144)에서 거래 당시 CJ ENM 지분은 100%) | AB20: 완료 (2021-02-04 양도일자, 특수관계인에대한자산양도 공시) | AC20: 5,666,000,000원 (양도가액 5,666백만원, 부가가치세 별도, 감정평가액 근거). CJ ENM 2022 사업보고서 특수관계자 주석에는 양수도가액이 5,675백만원으로 기재돼 있다 | AD20: 원자료와 일치 (5,666백만원 ÷ 5.06 = 약 1,120원/달러로 2021-02 환율 수준) | AE20: 2021-02-04 | AF20: 기준 분류 유지: CJ ENM이 미디어커머스 사업(자산·인력·가입자)을 100% 자회사 다다엠앤씨에 넘긴 계열사 간 사업 양수도다. 금액과 상태도 원자료와 같다. 매수자 쪽에서 보면 신설 자회사가 사업을 넘겨받은 분사 성격의 거래다. | AG20: C029(2023-11 CJ ENM이 미래에셋 PEF로부터 다다엠앤씨 전환상환우선주 91만주를 약 260.6억원에 사들여 100% 자회사로 만든 거래)와 같은 계보다. 거래 구조는 2020-12 다다엠앤씨 설립(자본금 40억원) → 2021-02-04 사업 양수 → 2021-05 미래에셋자산운용 PEF가 RCPS 91만주(210억원, 주당 23,077원, 지분 41.18%)를 인수해 CJ ENM 지분이 58.82%로 희석된 순서다. 원자료의 매수자 'DADA MNC'는 정확하다. 양도 전 사업부 단독 매출과 영업이익은 공시에서 찾지 못했다(2020년 취급고 약 250억원은 언론 보도). 2024~2025년 다다엠앤씨 매출이 사실상 0으로 줄어 사업이 멈춘 것으로 보이지만, 사업 중단이나 청산 공시는 찾지 못했다(2025 사업보고서까지 지분 100% 종속회사로 존속). 다다엠앤씨는 DART에 감사보고서가 없어 영업이익을 확인하지 못했다. | AH20: ㈜다다엠앤씨(CJ ENM이 2020-12-01 설립한 100% 종속회사, 비상장, 미디어커머스 전문). 매도자는 ㈜씨제이이엔엠(그룹 지배회사, 커머스부문) | AI20: "미디어커머스 사업의 성장 가속화 추구" (특수관계인에대한자산양도·특수관계인으로부터자산양수 공시) | AJ20: 다다엠앤씨는 미디어커머스(영상 콘텐츠로 상품을 파는 사업)만 하는 신설법인이다. 운영 브랜드는 다다픽, 필라이저(두피관리기기), 트리플블랙(PB 소형가전)이다(전자신문 2021-03-10). 그룹 정점 CJ ENM의 2020년 매출은 커머스가 1조4,786억원(43.60%)이고 나머지는 미디어·음악·영화다(2021 사업보고서 요약재무정보) | AK20: 핵심 | AL20: 매수자 다다엠앤씨는 이 사업을 하려고 세운 회사이므로 대상 사업과 주력 사업이 같다. CJ ENM 기준으로도 2017년 CJ오쇼핑 신사업개발팀에서 시작한 커머스부문의 자체 사업을 자회사로 옮긴 것이어서 커머스부문 핵심 영역 안의 재편이다. | AM20: 40억원 (㈜다다엠앤씨 2020-12-31 총자산 4,000,000천원, CJ ENM 2021 사업보고서 종속기업 요약재무정보 전기말) | AN20: CJ ENM 2020-12-31 연결 총자산 6,279,917백만원 (별도 4,903,163백만원) | AO20: 계산: 매수자 기준 5,666 ÷ 4,000(다다엠앤씨 2020말 총자산, 백만원) = 141.65%. 참고로 매도자 CJ ENM 기준은 5,666 ÷ 4,903,163(별도) = 0.116%, 5,666 ÷ 6,279,917(연결) = 0.090% | AP20: 계산: 매수자 기준 5,666 ÷ 4,000(다다엠앤씨 2020말 자본) = 141.65%. 참고로 CJ ENM 기준은 5,666 ÷ 3,098,401(2020말 별도 자본) = 0.183%, 5,666 ÷ 3,785,178(연결 자본) = 0.150% | AQ20: 계산: CJ ENM 2021-02-03 종가 161,900원 × 발행주식총수 21,929,154주 = 약 3조5,503억원 | AR20: 총자산과 자본은 CJ ENM 2021 사업보고서(20220321001256)의 2020년말 수치와 종속기업 요약재무정보를 썼다. 시가총액은 Yahoo Finance 035760.KQ 종가(분할 없음)와 2021 사업보고서의 발행주식총수로 계산했다. 공시에 총자산 대비 비율이 없어 직접 계산했다. 양수 금액이 신설 매수자의 자본보다 커서 매수자 기준 비율이 100%를 넘는다. | AS20: KOSDAQ:035760 | AT20: 매수자 다다엠앤씨는 비상장이고 상장 지배회사는 CJ ENM(코스닥)이다. 대상은 사업부라서 별도 종목이 없다. 같은 날 CJ ENM 2020년 잠정실적 공시가 나와 이벤트 분석에 교란이 크다. | AU20: 2021-02-04 DART 특수관계인에대한자산양도(CJ ENM, 20210204000422)와 특수관계인으로부터자산양수(다다엠앤씨, 20210204000428). 같은 날 CJ ENM 2020년 잠정실적 공시 | AV20: 2017: CJ오쇼핑 신사업개발팀에서 미디어커머스 사업 시작; 2018-07: CJ오쇼핑이 CJ E&M을 흡수합병해 CJ ENM 커머스부문이 사업을 운영; 2020: 미디어커머스 취급고 약 250억원, 전년 대비 120% 증가(언론); 2020-12-01: CJ ENM이 미디어커머스 법인 ㈜다다엠앤씨 설립(자본금 40억원, 지분 100%) | AW20: 2021-02-04: 사업 양수도 이사회 결의와 양도; 2021-03-09: 미래에셋자산운용 PEF와 210억원 신주인수계약(기업가치 약 500억원, 2023년 취급고 1,000억원과 상장 목표); 2021-05-17: 임직원 주식선택권 93,000주 부여; 2021-05-18~24: RCPS 91만주 발행, CJ ENM 지분 100%→58.82%; 2021: 매출 234.5억원, 순손실 87.9억원; 2022: 매출 159.2억원, 순손실 160.6억원, 자본잠식(자본 -133.2억원), CJ ENM 별도재무제표에서 투자주식 65억원 전액 손상; 2023-11: CJ ENM이 RCPS 91만주를 약 260.6억원에 사들여 100% 자회사화(C029); 2023: 매출 75.0억원, 순손실 90.0억원; 2024: 매출 1.5억원, 순손실 11.4억원; 2025: 매출 7만원 수준, 순손실 11.9억원, 장부가 0인 종속회사로 존속 | AX20: 있음 (2022년, CJ ENM 별도재무제표에서 다다엠앤씨 투자주식 장부가 6,500백만원 전액 손상. 타법인출자 현황 평가손익 -6,500백만원, CJ ENM 2022 사업보고서 20230320000724). 그룹 내부 거래라 영업권은 생기지 않았다 | AY20: 수집·검토 기록에 인수 뒤 손상이 적혀 있음 | AZ20: 미확인 (양도 전 미디어커머스 사업부 단독 매출 공시 없음. 참고: 취급고 2020년 약 250억원(전자신문 2021-03-10)) | BA20: 2021: 234.5억원; 2022: 159.2억원; 2023: 75.0억원; 2024: 1.5억원; 2025: 7만원 수준 (모두 ㈜다다엠앤씨 단독, 천원 단위 원값 23,454,675 / 15,923,826 / 7,501,352 / 147,922 / 74) | BB20: 미확인 (사업부 단독 손익 공시 없음) | BC20: 미확인 (영업이익은 찾지 못했다). 대신 당기순손익: 2021: -87.9억원; 2022: -160.6억원; 2023: -90.0억원; 2024: -11.4억원; 2025: -11.9억원 | BD20: CJ ENM 사업보고서(2021: 20220321001256, 2022: 20230320000724, 2023: 20240318000857, 2025: 20260318001469) 연결재무제표 주석 '종속기업 요약 재무정보'의 다다엠앤씨 단독 수치(K-IFRS, 12월 결산, 천원). 2024 수치는 2025 사업보고서의 전기 비교 수치다. 양도 전 실적은 사업부 단위라 공시되지 않았다. | BE20: 2021-03-10 전자신문: 다다엠앤씨 210억원 투자 유치를 보도하며 "'분사→투자유치→육성→상장'이라는 신사업 육성 단계"를 밟는다고 전함(회사 설명 재인용); 2021-04-15 뉴데일리: "미디어커머스 시장은 콘탠츠 제작역량 뿐 아니라 수익성 강화와 외형 확대를 위한 독자적인 상품경쟁력 확보가 필수다"(회사 설명 재인용). CJ ENM IR 자료와 어닝콜에서 다다엠앤씨를 직접 다룬 발언은 찾지 못했다. | BF20: 부분 | BG20: 2026-10-31
A21: C018 | B21: CJ ENM | C21: 2021-06-18 | D21: Jk Film Co.Ltd. | E21: 186 | F21: False | H21: MA② | I21: MA② | J21: 같음 | K21: 없음 (확인) | L21: 기타 | M21: 편입 후 | N21: Closed | O21: 0.013 | P21: CJ ENM CO., Ltd. (KOSDAQ:A035760) | Q21: - | R21: CJ ENM CO., Ltd. (KOSDAQ:A035760) acquired additional 36.9% stake in Jk Film Co.Ltd. from Gil, Young Min and Yoon, Je-kyun for KRW 15 million on June 18, 2021. Under the terms of transaction, 8,671 shares were sold at KRW 1,730 per share and CJ ENM CO. currently hold 51% stake and post completion it holds 87.8% stake in company. | S21: Content Production & Investment | T21: Content Production Studio | U21: MA-1 그룹이 매수자 | V21: 추가지분 | W21: MA② 기존 지분 확대 | Y21: False | Z21: MA② 기존 지분 확대 | AA21: 편입 후 (매수자 ㈜씨제이이엔엠은 CJ ENM 본체. JK필름은 2016년 CJ E&M이 지분 36%를 추가 취득해 지배력 획득(51%), 2018-07-02 CJ E&M→CJ ENM 합병으로 51% 승계. CJ E&M 2016 사업보고서 20170331004920, JK필름 최대주주변동 20180706000379) | AB21: 완료 (2021-06-18 이사회 결의·주식매매계약 체결 예정일, JK필름 최대주주등의주식보유변동 공시상 변동일 2021-06-18. CJ ENM 2021 연결주석에 2021말 지분율 87.85%로 기재) | AC21: 15,000,830,000원 (8,671주 × 주당 1,730,000원; CJ ENM 공시상 취득금액 15,001백만원. 윤제균 8,436주 14,594,280천원 + 길영민 235주 406,550천원) | AD21: 13.23 (15,001백만원 ÷ 1,133.54원/USD, Yahoo Finance KRW=X 2021-06-17 종가). 원자료 0.013은 1,000배 과소 | AE21: 2021-06-18 | AF21: 기준 분류 유지: CJ ENM은 이미 51%를 보유한 지배주주였고(2016년 지배력 획득) 이 거래로 87.85%가 됐다. 금액 정정: 원자료 설명란의 'KRW 15 million', 'KRW 1,730 per share'는 JK필름 공정위 공시의 단위(천원)를 원으로 읽은 오류다. 실제 취득금액은 15,000,830천원(약 150억원), 주당 1,730,000원(CJ ENM '특수관계인으로부터주식의취득' 20210618000385: 취득금액 15,001백만원, 취득단가 1,730,000원). value를 0.013에서 약 13.23백만달러로 정정. 매도자 표기(Gil Young Min, Yoon Je-kyun)는 공시와 일치(윤제균·길영민, 계열회사 임원). | AG21: C024(2022-10-24 윤제균 잔여 2,388주 10.15% 5,074백만원 취득, 취득 후 100%)와 같은 대상의 후속 단계. 이 거래 후 남은 지분은 윤제균 2,388주(10.15%)·길영민 471주(2.00%)였는데, C024 공시는 취득 후 23,530주(100%)로 적고 있어 길영민 471주는 2022-01~2022-10 사이 별도 취득된 것으로 보인다(해당 공시 미확인). CJ ENM 2021 연결주석 각주: '연결회사는 계약된 전제조건 충족시 기존 주주의 잔여지분 매도를 요구할 수 있는 권리를 보유'. 주당가 비교: 2016 지배력 획득 때 총이전대가 20,398,800천원/12,000주=주당 약 1,700천원, 2021 주당 1,730천원으로 사실상 같은 평가. 이 거래는 이미 연결 종속기업의 비지배지분 매입이어서 연결상 영업권이 새로 생기지 않는 자본거래다. JK필름은 2016년 이후 감사보고서가 DART에 없어 실적은 공정위 대규모기업집단현황공시(별도, 백만원)와 CJ ENM 연결주석으로 확인했다. 2018년 수치는 두 출처가 다르다(공정위 공시 매출 4,652백만원·순이익 275백만원 vs CJ ENM 2018 연결주석 매출 922백만원·순손실 483백만원). 2022-12-13 씨제이이엔엠 스튜디오스에 흡수합병돼 법인 소멸. 2016년 지배력 획득의 정확한 일자는 미확인. | AH21: ㈜씨제이이엔엠(CJ ENM, 그룹 정점·코스닥 상장 035760) | AI21: "자회사 지분 추가 취득을 통한 제작 역량 강화" (DART 특수관계인으로부터주식의취득, 2021-06-18) | AJ21: 추정: 방송·디지털 미디어 콘텐츠, 커머스(옛 CJ오쇼핑), 영화, 음악 사업을 하는 미디어·커머스 기업(2021 연결 매출 3,552,397백만원, 2021 사업보고서 요약재무정보). 부문별 매출 비중은 이번 수집에서 직접 확인하지 못함 | AK21: 핵심 | AL21: JK필름은 영화 제작사(CJ ENM 연결주석 주요사업 '영화 제작 사업')이고 CJ ENM은 영화 사업 부문을 직접 운영하며 JK필름 작품(공조2 등)을 배급했다. 이미 지배하던 제작 자회사의 지분 확대이며, 인수 주체 자체가 그룹 정점이다. | AM21: 별도 4,903,163백만원 (2020-12-31, CJ ENM 2021 사업보고서 요약재무정보); 연결 6,279,917백만원 (2020-12-31) | AN21: acq_total_assets와 같음 (연결 6,279,917백만원, 2020-12-31) | AO21: 계산: 0.31 (15,001백만원 ÷ 별도 총자산 4,903,163백만원, 2020-12-31). 연결 기준 0.24 | AP21: 계산: 0.48 (15,001백만원 ÷ 별도 자본총계 3,098,401백만원, 2020-12-31). 연결 자본총계 3,785,178백만원 기준 0.40 | AQ21: 계산: 약 3조 8,946억원 (2021-06-17 종가 177,600원 × 발행주식총수 21,929,154주) | AR21: 총자산·자본: CJ ENM 2021 사업보고서(20220321001256) 요약재무정보의 2020-12-31 값. 공시에 총자산대비 비율이 없어 직접 계산. 시가총액: Yahoo Finance 035760.KQ 2021-06-17 종가(분할 없음) × 2021 사업보고서 발행주식총수(2021-12-31 기준; 2021년 중 변동 여부는 미확인) | AS21: KOSDAQ:035760 | AT21: 인수 주체 CJ ENM이 코스닥 상장사(2021-06 당시). 대상회사 JK필름은 비상장 | AU21: 2021-06-18 DART 공시(CJ ENM 특수관계인으로부터주식의취득, JK필름 최대주주등의주식보유변동). 이전 보도는 찾지 못함 | AV21: 2016 이전(일자 미확인): CJ E&M이 JK필름 지분 15%를 매도가능금융자산으로 보유; 2016: CJ E&M이 지분 36%를 14,398백만원에 추가 취득해 51%로 지배력 획득(총이전대가 20,398,800천원, 영업권 18,560,170천원, 기존 15% 재측정이익 5,001백만원); 2018-07: CJ E&M이 CJ오쇼핑에 합병돼 CJ ENM이 51% 승계; 2019: 매출 15,489백만원·영업이익 80백만원; 2020: 매출 5,497백만원·영업손실 447백만원, CJ ENM이 JK필름 영업권 1,543백만원 손상 인식; 2021-06-18: 이사회 결의·지분 36.85% 취득 결정 | AW21: 2021-06-18: 지분 87.85%로 확대; 2021: 매출 16,137백만원·영업이익 152백만원; 2021말: CJ ENM이 잔여지분 매도청구권 보유(연결주석); 2022-04: 씨제이이엔엠 스튜디오스(주) 설립; 2022-07: 윤제균 CJ ENM스튜디오스 대표이사 선임(비즈워치 보도); 2022-09-07: JK필름 제작 '공조2: 인터내셔날' 개봉, 일주일 만에 손익분기점 돌파; 2022-10-24: 윤제균 잔여 2,388주(10.15%)를 5,074백만원(주당 2,124,900원)에 취득해 100%(C024); 2022-12-13: 씨제이이엔엠 스튜디오스가 JK필름 등 8개 제작사 흡수합병, JK필름 법인 소멸; 2023: CJ ENM 영업권 1,143억 손상(스튜디오스 CGU 영업권 2023말 151,282백만원, CGU별 손상 배분 미확인) | AX21: 거래 후 JK필름 개별 손상 확인 안 됨 (CJ ENM 연결주석 2021·2022 손상 열거 목록에 JK필름 없음). 거래 전 2020년 JK필름 영업권 1,543백만원 손상 있음(CJ ENM 2020 연결주석 20210322000740). 합병 후 씨제이이엔엠 스튜디오스 CGU의 2023 손상 여부는 CGU별 배분 미확인(2023 사업보고서 20240318000857; 2024·2025 사업보고서 주석까지 검색) | AY21: 2021·2022 CJ ENM 손상 목록에 JK필름 없음, 합병 뒤 2022~2025 스튜디오스 현금창출단위 영업권 151,281,704천원 불변 | AZ21: 2019: 15,489백만원; 2020: 5,497백만원 | BA21: 2021: 16,137백만원; 2022: 미확인(2022-12 합병으로 개별 실적 공시 없음); 승계법인 씨제이이엔엠 스튜디오스 매출 2022: 29,374백만원, 2023: 143,370백만원, 2024: 199,229백만원, 2025: 226,702백만원 | BB21: 2019: 80백만원; 2020: -447백만원 | BC21: 2021: 152백만원; 2022: 미확인; 승계법인 씨제이이엔엠 스튜디오스는 영업이익 미확인, 당기순이익 2022: 2,185백만원, 2023: -9,296백만원, 2024: 7,106백만원, 2025: -3,143백만원 | BD21: JK필름 2018~2021: 공정위 대규모기업집단현황공시(연1회공시, 직전 사업연도 별도, 백만원; 20190531002020, 20200528000719, 20210531001396, 20220531000871). 2019·2020·2021 매출·순이익은 CJ ENM 연결주석 종속기업 요약재무정보(천원)와 일치. 2022 이후는 승계법인 씨제이이엔엠 스튜디오스(8개 제작사 합병, JK필름 몫 분리 불가)의 CJ ENM 연결주석 요약재무정보(매출·당기순이익, 천원; 2023·2024·2025 사업보고서). 12월 결산 | BE21: 2022-11-08 CJ ENM 3분기 실적(데일리안 보도, 회사 실적발표 재인용): "<공조2: 인터내셔날>의 박스오피스 실적이 호조를 보이며 극장 매출이 지난해 3분기 대비 376.8% 증가", 영화 부문 매출 1186억원·영업손실 1억원. JK필름을 직접 언급한 어닝콜 발언은 찾지 못함 | BF21: 완료 | BG21: 2026-10-31
A22: C019 | B22: CJ ENM | C22: 2021-10-13 | D22: Tving Co.,Ltd | E22: 37 | F22: True | H22: MA② | I22: MA② | J22: 같음 | K22: 없음 (확인) | L22: 일치 | M22: 편입 후 | N22: Announced | O22: 66.93 | P22: CJ ENM CO., Ltd. (KOSDAQ:A035760) | Q22: - | R22: CJ ENM CO., Ltd. (KOSDAQ:A035760) agreed to acquire additional 8.818696% stake in Tving Co.,Ltd for KRW 79.582 billion on October 13, 2021. CJ ENM CO., Ltd. will acquire 0.18 million shares of Tving Co.,Ltd. After the transaction CJ ENM will own 67.61% stake comprising of 1.38 million shares. The transaction is expected to close on October 15, 2021. | S22: Media Platforms | T22: OTT / Streaming Platform | U22: MA-1 그룹이 매수자 | V22: 추가지분 | W22: MA② 기존 지분 확대 | Y22: False | Z22: MA② 기존 지분 확대 | AA22: 편입 후 (매수자 ㈜씨제이이엔엠은 그룹 지배회사 자신. 대상 ㈜티빙은 2020-10-01 CJ ENM 티빙(OTT) 사업부문 물적분할로 설립된 종속회사, 공시 '회사와의관계: 종속회사') | AB22: 완료 (2021-10-15, 신주 납입일 2021-10-14) | AC22: 79,582,140,000원 (티빙 제3자배정 신주 180,000주 × 주당 442,123원, 현금) | AD22: 원자료와 일치 (원자료 66.93 = 79,582백만원/약 1,189원/달러, 2021-10 환율 수준) | AE22: 2021-10-13 | AF22: 기준 분류 유지(MA②): 이미 지배하던 종속회사 티빙의 신주를 CJ ENM이 추가 인수(구주 매입이 아니라 제3자배정 유상증자 참여, 대금은 티빙으로 유입. 같은 구조의 C002 선례와 동일 처리). 다만 같은 날 같은 증자(총 339,272주, 149,999,954,456원)에서 제이티비씨스튜디오㈜ 120,000주, 네이버㈜ 39,272주도 함께 배정돼 CJ ENM 지분율은 오히려 70.51%(1,200,000/1,701,817주)→67.61%(1,380,000/2,041,089주)로 2.90%p 낮아짐(티빙 '최대주주등의주식보유변동' 2021-10-15). 원자료 설명란의 'additional 8.818696% stake'는 CJ ENM 신주 180,000주가 증자 후 총주식 2,041,089주에서 차지하는 비중일 뿐 순증 지분이 아님. 상태 정정: 원자료 Announced → 완료(2021-10-15). | AG22: 같은 묶음 C014(2015-11, CJ E&M이 CJ헬로비전의 N스크린 tving 사업을 양수, 원자료 기록)가 이 사업 계보의 앞 단계이고, 2020-10 물적분할로 법인 ㈜티빙이 생긴 뒤 이 거래가 이어짐. 동시 배정된 JTBC스튜디오·네이버 몫(약 704억원)은 그룹 자회사가 외부자에게 신주를 발행한 MA⑤ 성격이지만 이 행의 금액(796억원)은 CJ ENM 몫만 담음. 발행가 442,123원은 3개월 전 네이버 배정가 152,778원(2021-06-30 공시)의 약 2.9배. 이후 외부 투자 유치(2022-02)와 KT시즌 흡수합병(2022-12-01)으로 CJ ENM 지분은 48.85%까지 내려갔으나 의결권 상대적 규모·약정을 근거로 실질 지배력이 있다고 보고 계속 연결(CJ ENM 2025 사업보고서 주석). 티빙은 분할 신설법인이라 인수 직전 2개 회계연도 실적이 법인 단위로 온전히 존재하지 않음(2019는 CJ ENM 별도 사업부문 매출, 2020은 3개월). 2021 감사보고서(하온회계법인)는 열지 않고 2022 감사보고서 비교표시로 2021 수치를 채움. | AH22: ㈜씨제이이엔엠(CJ ENM, 그룹 지배회사, 코스닥 상장) | AI22: "종속회사 티빙의 플랫폼 경쟁력 및 오리지널 콘텐츠 강화" (거래소 공시 타법인주식및출자증권취득결정(자율공시)) / "티빙의 플랫폼 경쟁력 및 오리지널 콘텐츠 강화" (유상증자결정(종속회사의주요경영사항) 제3자배정 증자의 목적) | AJ22: 방송·디지털 미디어와 홈쇼핑 커머스. 2020 연결매출 3,391,184백만원 중 미디어 1,590,692(46.9%), 커머스 1,478,647(43.6%), 음악 180,278(5.3%), 영화/공연 141,567(4.2%) (CJ ENM 2020 사업보고서 II. 사업의 내용 부문별 매출 표) | AK22: 핵심 | AL22: 티빙은 2020-10 분할 전까지 CJ ENM이 직접 운영하던 OTT 사업부문이고 CJ ENM 미디어 부문의 디지털 유통 창구라 주력 사업과 같은 영역. 인수 주체가 그룹 정점 CJ ENM 자신이므로 정점 기준도 같음. | AM22: 6,279,917,456,928원 (공시 '최근 사업연도말 자산총액', 2020말 연결) | AN22: acq_total_assets와 같음 | AO22: 1.27 | AP22: 1.97 | AQ22: 계산: 3,695,062,449,000원 (2021-10-12 종가 168,500원 × 발행주식총수 21,929,154주) | AR22: 총자산대비 1.27%는 2020말 연결 자산총액 기준, 자기자본대비 1.97%는 2021 반기말 자기자본 4,029,495,524,446원 기준(2021-10-13 공시). 시가총액은 발표 직전 거래일 2021-10-12 Yahoo Finance 035760.KQ 종가(CJ ENM은 이후 액면분할·무상증자를 찾지 못해 조정 없이 사용)와 CJ ENM 2020 사업보고서 발행주식총수 21,929,154주(자기주식 1,199,535주 포함, 2021 중 변동 여부는 확인 안 함). | AS22: KOSDAQ:035760 | AT22: 인수 주체 CJ ENM이 코스닥 상장 지배회사. 대상 티빙은 비상장. 같은 날 티빙 증자 공시가 함께 나와 이벤트는 CJ ENM 자금 투입과 JTBC스튜디오·네이버 동반 투자가 섞인 신호임에 유의. | AU22: 2021-10-13 (CJ ENM 거래소 공시 '타법인주식및출자증권취득결정(자율공시)'·'유상증자결정(자율공시)(종속회사의주요경영사항)'·'특수관계인에대한출자', 티빙 '유상증자결정'·'특수관계인의유상증자참여' 동시 공시). 공식 발표 전 보도는 찾지 못함. | AV22: 2015-11: CJ E&M이 CJ헬로비전의 N스크린 tving 사업 양수(같은 묶음 C014, 원자료 기록); 2019: 티빙 사업부문 매출 44,075백만원(CJ ENM 별도 내부결산 잠정, 분할 공시); 2020-10-01: CJ ENM이 티빙(OTT) 사업부문을 단순·물적분할해 ㈜티빙 설립(100%), 목적 '사업경쟁력을 강화하고 … 전문성 및 고도화를 추구'; 2020-10~12: 매출 15,491백만원, 영업손실 6,134백만원(첫 3개월); 2021-01-07: JTBC스튜디오가 유상증자 240,000주(60억원)+전환사채 140억원으로 16.67% 2대 주주, CJ ENM 83.33%, 티빙은 3년간 4,000억원 이상 콘텐츠 투자·2023년 유료가입자 500만명 목표 발표(뉴시스); 2021-06-30: 네이버㈜에 제3자배정 261,817주(주당 152,778원, 39,999,877,626원, 납입 2021-07-07, 네이버 멤버십 제휴), CJ ENM 지분 83.33%→70.51% | AW22: 2021-10-14: 제3자배정 339,272주(주당 442,123원, 총 149,999,954,456원) 납입, CJ ENM 180,000주·JTBC스튜디오 120,000주·네이버 39,272주; 2021-10-15: CJ ENM 1,380,000주 67.61%(증자 전 70.51%); 2021-11-04: CJ ENM 3분기 실적 보도에서 티빙 유료가입자 '직전 동기 대비' 37.8% 증가(기사 표현 그대로, 전분기·전년동기 구분 불명, CEO스코어데일리); 2021: 매출 131,525백만원, 영업손실 76,235백만원; 2022-02-18: 미디어그로쓰캐피탈제1호㈜에 제3자배정 382,513주(주당 653,572원, 249,999,786,436원, 납입 2022-02-25) 결의, CJ ENM 67.61%→56.94%(변동일 2022-02-28, 이후 56.50%), 이 투자자의 매수청구권 관련 파생상품부채를 CJ ENM이 인식(CJ ENM 2025 별도 주석); 2022-07-14: ㈜케이티시즌 흡수합병 결정(합병비율 티빙 1 : 케이티시즌 1.5737519, 합병기일 2022-12-01); 2022-12-01: 합병 완료, 합병신주 382,513주 발행으로 CJ ENM 48.85%(1,380,000/2,824,798주), KT 측 2대 주주(약 13.5%); 2022: 매출 247,570백만원, 영업손실 119,151백만원(최대 적자); 2023-06-29: CJ ENM이 티빙 대표이사를 양지을에서 최주희(전 트렌비 비즈니스 총괄 대표)로 교체 선임 발표; 2023: 웨이브와 합병 MOU; 2024: 매출 435,459백만원, 영업손실 71,048백만원; 2024-11: CJ ENM·티빙이 웨이브와 합의서(웨이브 이사 8명 중 5명 지명); 2025-06-10: 공정위가 티빙–웨이브 기업결합을 2026년 말까지 요금 유지 조건으로 승인; 2025-09: 웨이브가 CJ ENM 연결 종속회사로 편입; 2025: 매출 405,981백만원, 영업손실 69,819백만원, 순손실 89,338백만원, 건설중인무형자산 손상 5,736백만원, CJ ENM 지분 48.85%로 실질 지배력 근거 연결 유지; 2026-04: 형식적 합병은 KT 측 신중론으로 교착(MTN); 2026-09-03: 민관합동조사단 조사에서 티빙 계정 3,954만 개(활성·휴면·탈퇴·테스트 계정, 중복 포함) 유출 확인, 티빙 공식 사과·보상안 발표(MTN); 2026-2Q: 매출 1,407억원, 영업이익 60억원으로 독립법인 출범 후 첫 분기 흑자(MTN 2026-10-16 보도, 감사 전 분기 실적) | AX22: 확인 안 됨 (① CJ ENM 2025 사업보고서 별도재무제표 주석 종속기업투자 표: ㈜티빙 지분 48.9%, 취득원가 93,230,885천원 = 장부금액 93,230,885천원(2024말·2025말 모두) → 이 거래 대금 79,582백만원을 포함한 티빙 투자주식에 누적 손상 없음; ② 티빙 2025 감사보고서 무형자산 표: 영업권 213,089,914천원(2020 분할 때 이관분 + 2022-12 케이티시즌 합병분) 취득원가=장부금액, 상각 및 손상차손누계액 없음(2024말·2025말) → 2022~2025 영업권 손상 없음. 단 2025년 건설중인무형자산 손상차손 5,735,957천원 인식(인수 관련 영업권·투자주식 아님); ③ CJ ENM 연결에서는 티빙이 '미디어플랫폼사업부문' 현금창출단위에 묶여 CGU별 손상 귀속을 분리할 수 없음(2025 사업보고서 연결 주석). 이 거래는 지배력 유지 중의 추가 취득이라 CJ ENM 연결상 새 영업권이 생기지 않음) | AY22: CJ ENM 별도 티빙 투자주식 취득원가=장부금액(2024·2025), 티빙 영업권 손상누계 없음 | AZ22: 2019: 44,075백만원 (CJ ENM 티빙 사업부문); 2020: 15,491백만원 (㈜티빙 2020-10-01~12-31, 3개월) | BA22: 2021: 131,525백만원; 2022: 247,570백만원; 2025: 405,981백만원 | BB22: 2019: 미확인; 2020: -6,134백만원 (3개월) | BC22: 2021: -76,235백만원; 2022: -119,151백만원; 2025: -69,819백만원 | BD22: 2019는 CJ ENM 물적분할 주요사항보고서의 '신설사업부문 최근 사업연도 매출액' 44,074,834,289원(2019말 별도 기준, 내부결산 잠정). 2020은 ㈜티빙 제1기 감사보고서(2020-10-01~12-31, 3개월, K-IFRS 별도). 2021·2022는 티빙 2022 감사보고서(삼정회계법인, 별도 K-IFRS, 12월 결산; 2021은 비교표시), 2025는 티빙 2025 감사보고서(삼정회계법인). 손익 항목은 '영업수익'(매출)과 '영업이익(손실)'. 2022-12-01 KT시즌 합병 이후 수치는 합병 효과를 포함함. | BE22: 2021-01-07 뉴시스: CJ ENM·티빙 "향후 3년간 4000억 이상 콘텐츠 제작에 투자", "2023년까지 유료 가입자 500만명 확보 계획"; 2021-11-04 CEO스코어데일리(CJ ENM 3분기 실적 보도): "티빙은 <환승연애> 등의 인기에 힘입어 유료가입자가 직전 동기 대비 37.8% 급증했다"; 2026-04-01 MTN: 티빙–웨이브 형식적 합병이 2대 주주 KT의 신중론으로 교착. CJ ENM IR 원자료(실적발표 PDF·어닝콜 스크립트)는 열지 못해 기사 재인용임 | BF22: 완료 | BG22: 2026-10-26
A23: C020 | B23: CJ ENM | C23: 2021-11-18 | D23: Scripted Business of IMG Worldwide, LLC | E23: 7 | F23: True | H23: MA① | I23: MA① | J23: 같음 | K23: 있음 | L23: 일치 | M23: 편입 후 | N23: Closed | O23: 775.28 | P23: CJ ENM CO., Ltd. (KOSDAQ:A035760) | Q23: IMG Worldwide, LLC | R23: CJ ENM CO., Ltd. (KOSDAQ:A035760) entered into a purchase agreement to acquire 80% stake in scripted business of IMG Worldwide, LLC for approximately $780 million on November 18, 2021. CJ ENM CO., Ltd. will subscribe for and accept from Endeavor Content, a number of newly issued equity interests in Endeavor Content equal to 80% of the total issued and outstanding equity interests of Endeavor Content, on a fully-diluted basis (excluding equity interests related to any post-closing employee incentive plans) in exchange for proceeds equal to $775.3 million (subject to certain adjustments) at an enterprise value of $850 million, including $655.3 million in proceeds to be paid to IMG Worldwide (subject to certain adjustments) and $120 million paid to Endeavor Content (subject to certain adjustments). The transaction implies an approximately $970 million post-money equity valuation for Endeavor Content and will include the assets and liabilities associated therewith, including Endeavor Content’s related production financing facilities, and of which Endeavor is entitled to sweep up to an additional $55 million of Endeavor Content’s cash (subject to certain adjustments) as part of the transaction. Post-closing, IMG Worldwide will retain 20% of the total issued and outstanding equity interests of Endeavor Content, on a fully-diluted basis (excluding equity interests related to any post-closing employee incentive plans) along with the scripted portion of the business, in addition to retaining the non-scripted portion of the business, as well as certain documentary and film sales and financing consulting services. Endeavor Content’s Graham Taylor and Chris Rice will continue to lead the studio as co-Chief Executive Officers. The transaction is subject to certain customary conditions, expiration of the waiting period under the Hart-Scott-Rodino Antitrust Improvements Act of 1976, as amended, obtaining other applicable regulatory approvals and consummation of an internal reorganization to be affected by Endeavor Content and IMG Worldwide, LLC in advance of consummating the transaction. The transaction has been approved by CJ ENM’s Board of Directors on November 19, 2021. The consummation of the transaction is not subject to a financing condition. The deal will close early in the first quarter of 2022. As of December 29, 2021, the transaction is expected to close within January 2022. J.P. Morgan acted as exclusive financial advisor and O’Melveny & Myers acted as legal advisor to CJ ENM in the transaction. The Raine Group acted as exclusive financial advisor and Justin Hamill, Rick Offsay, Michael Anastasio, Matthew Dewitz, Nancy Bruington, Joshua Tinkelman, Seniz Yakut, Austin Ozawa, Ghaith Mahmood, Robert Blamires, Nineveh Alkas, Robert Gilbert, Amanda Reeves, Peter Todaro, Michelle Kelban, Christopher Norton, Benjamin Naftalis Stephanie Fontanes, Benjamin Cohen, Ellen Smiley and Robert McGuire of Latham & Watkins LLP, Sarah Gadd of Latham & Watkins (London) LLP acted as legal advisors and Tomas Nilsson of Latham & Watkins Belgium acted as legal advisor to Endeavor, parent of IMG Worldwide, LLC. | S23: Content Production & Investment | T23: Content Production Studio | U23: MA-1 그룹이 매수자 | V23: 과반 인수(≥50%) | W23: MA① 경영권 인수 | Y23: False | Z23: MA① 경영권 인수 | AA23: 편입 후 (인수 주체 CJ ENM USA Holdings LLC는 CJ ENM이 CJ ENM USA INC.를 거쳐 본 거래용으로 신설한 100% 종속 SPC. 대상회사 Endeavor Content Parent, LLC는 본 거래 종결로 2022-01-19(KST; 현지 2022-01-18) CJ ENM 연결 종속회사로 편입 — CJ ENM 2022 사업보고서 연결범위 변동표에 'CJ ENM FIFTH SEASON, LLC (구, Endeavor Content Parent, LLC) | 인수'로 기재, 비지배지분율 20%(연결주석 41), 접수번호 20230320000724) | AB23: 완료 (2022-01-19 KST, 현지 2022-01-18 거래종결; 취득예정일 2021-12-31 → 2022-01-31로 연기 정정(2021-12-29) 후 2022-01-19 종결 확정 정정) | AC23: USD 785,381,728.77 = 933,740,337,335원 (거래종결 시 확정 인수대금, 1,188.9원/USD; 2022-01-19 정정공시. 연결 사업결합 이전대가 933,740,337천원). 계약 시 기준금액 USD 775,279,046.03 = 915,216,913,838원(1,180.5원/USD). 계약 구성(Endeavor 8-K): 매도인 IMG Worldwide 몫 USD 655.3M + Endeavor Content 신규 출자 USD 120.0M, EV USD 850M, post-money equity USD 970M. CJ ENM의 SPC 출자 총액은 운영비 포함 USD 793,850,000 = 944,602,115,000원 | AD23: 원자료와 일치 (원자료 775.28 = 계약 기준금액 USD 775.3M; 종결 확정 USD 785.38M은 +1.3%) | AE23: 2021-11-18 (미국 현지: Endeavor 8-K·공동 보도자료. 한국 시간 2021-11-19 CJ ENM 이사회 결의·거래소 공시) | AF23: 기준 분류 유지: CJ ENM이 SPC(CJ ENM USA Holdings LLC)를 통해 Endeavor Content Parent, LLC 의결권부 지분 80%를 처음 취득해 경영권 확보(주주간계약상 우선매수권·동반매도요구권·위반 시 콜옵션 보유, 풋옵션 없음). 원자료 보정: (1) 대상회사 법인은 'Scripted Business of IMG Worldwide, LLC'가 아니라 Endeavor Content Parent, LLC(IMG Worldwide 100% 자회사; 2022-09 CJ ENM FIFTH SEASON, LLC로 사명 변경). 종결 전 내부 재편으로 비각본(non-scripted)·일부 다큐·영화판매·금융자문 사업은 매도인 측으로 이관. (2) 매수인은 CJ ENM 본체가 아니라 CJ ENM→CJ ENM USA INC.→CJ ENM USA Holdings LLC이고 CJ ENM은 인수대금 지급보증. (3) 구조: DART는 '매도인 보유 지분 일부 매수 + 대상회사 신규 발행 지분 인수'를 동시에 해 80:20이 된다고 기재, Endeavor 8-K는 '신규 발행 지분 80%' 인수로 서술(대금 중 USD 655.3M은 매도인, USD 120M은 회사 유입) — 금액·지분은 일치. (4) 확정 대금은 종결 조정 후 USD 785.38M(Endeavor 보도자료 'approximately $785 million in total proceeds'); 이 중 Endeavor가 받은 현금은 USD 666.3M(Endeavor 2022 10-K). | AG23: 같은 묶음의 C030(2023-12)과 연결: Toho International이 Fifth Season에 USD 225M을 넣어 25%를 받으면서(제3자 배정 신규 발행) CJ ENM 지분이 80%→60%, Endeavor 지분이 20%→15%로 희석됐다. 매각 배경: Endeavor가 2021-02 미국작가조합(WGA)과 맺은 프랜차이즈 계약으로 제작사 지분을 20% 이하로 낮춰야 했다(Endeavor 10-K). 입찰: CJ ENM은 2020년 말 'Eagle' TF를 꾸렸고 2021-07 초청 입찰에 국내 유일하게 참여해 Apollo 등과 경쟁(한국경제 KED 2021-11-23). 자금: 2021-11-19 단기차입금 9,000억원 증가 결정(CP 5,000억 + 금융기관 4,000억, 목적 '글로벌향 콘텐츠 제작 역량 강화 및 멀티 스튜디오 구축을 위한 자금 마련') — 2021-12-21 정정공시(20211221900378)로 8,000억원으로 축소(차입 후 CP 4,000억·금융기관 4,850억, 합계 8,850억원)과 SPC 의무 지급보증(915,216,913,838원, 자기자본대비 21.9%; 종결로 종료). 회계: 식별가능 순자산 680,238,114천원(무형자산 505,594,369천원 포함, 인수 차입금 287,712,103천원 승계), 비지배지분 136,132,317천원, 영업권 389,634,540천원(이전대가의 41.7%; 영업권 CGU 표에는 389,765,558천원). 가치 변화(계산): 인수 시 100% 환산 약 USD 982M(785.38/0.8) → 2023-12 Toho 출자 기준 post-money USD 900M·pre-money USD 675M. 이벤트 분석 주의: 발표일(2021-11-19)에 '물적분할을 통한 스튜디오 신설 추진' 공정공시가 함께 나갔고(2022-02-09·03-08 해명공시로 재검토 표명), 2021-11-25 SM엔터 인수설 조회공시 답변이 이어져 교란이 크다. 출처 한계: Fifth Season 단독 영업손익은 CJ ENM 공시·IR에 연간 단위로 공개되지 않아 당기순손익과 증권사 인용 분기 영업이익으로 대신했다. Deadline·Hollywood Reporter 기사는 유료(402/tollbit)라 원문을 못 열었고, WSJ 선행 보도 여부는 검색 요약으로만 확인. Endeavor 10-K는 Endeavor의 USD 30M 대여 시점을 2023-09(2023 10-K)와 2023-06(2024 10-K)으로 다르게 적었다. 2023 작가·배우 파업 기간의 정확한 날짜는 이 기록에서 출처로 확인하지 않았다. 검토 보완: 손상은 연결 영업권 외에 CJ ENM 별도 재무제표의 CJ ENM USA INC. 투자주식 손상(2022 약 582억·2023 약 1,957억 계산, 2025 832억 공시)도 있음 — impairment 참조. FS 연간 영업손익은 DS투자증권 법인별 표(자료: CJ ENM)로 보완했고 2023 -655억원이 영업손실임이 확인됨. 2023-04·08 두 차례 감원. | AH23: CJ ENM USA Holdings LLC (CJ ENM→CJ ENM USA INC.(100%)→Holdings(100%), 본 거래용 신설 미국 캘리포니아주 SPC, 비상장). 최종 지배회사 ㈜씨제이이엔엠(코스닥 상장)이 출자·지급보증 | AI23: "글로벌향 콘텐츠 제작 역량 강화 및 멀티 스튜디오 구축" (거래소 공시 취득목적, 2021-11-19) / "Acquisition will serve as a new growth engine towards CJ ENM's vision as a 'global total entertainment company'" (CJ ENM·Endeavor 보도자료, Endeavor 8-K EX-99.1) / "The library and portfolio ... will support CJ ENM's plan to launch its OTT platform, TVING, globally" (같은 보도자료) | AJ23: CJ ENM 그룹: 방송(채널 tvN·OCN·Mnet 등 운영, 드라마·예능 제작, 스튜디오드래곤 드라마 제작·유통)과 커머스(TV·온라인 홈쇼핑)가 양대 축. 2020 연결 순매출 3,391,184,002천원 중 방송 1,590,692,492천원(46.9%), 커머스 1,478,646,956천원(43.6%), 음악 180,277,650천원(5.3%), 영화 124,014,922천원(3.7%), 공연 17,551,982천원(0.5%) (2021 사업보고서 연결주석 38, 전기). 인수 주체 SPC 자체는 사업 없음 | AK23: 핵심 | AL23: 대상 사업(미국 기반 TV 시리즈·영화 기획·제작·자금조달·해외 판매)은 CJ ENM 주력인 방송부문의 드라마 제작·유통(스튜디오드래곤)과 영화부문 제작·배급과 같은 영역이다. 새로운 것은 지역(미국·글로벌 OTT 납품)과 규모. 인수 주체가 SPC라 그룹 정점 CJ ENM 기준으로 판단했고, 결론도 같다. | AM23: 938,984,303,250원 (CJ ENM USA Holdings LLC의 '종속회사의 자산총액', 2022-01-19 최종 정정공시 20220119900349; CJ ENM USA INC.의 출자(2022-01-14 결정, 938,428,478,000원) 이후 값으로 기준일 명시는 없음. 최초 공시(2021-11-19)에서는 '발행주식 없이 신규 설립' 상태라 자산 기재 생략) | AN23: 6,279,917,456,928원 (CJ ENM 연결, 2020-12-31; 2021-11-19 공시 기재값). 참고: 2021-12-31 연결 총자산 7조 9,406억원(2022 사업보고서 경영진단) | AO23: 14.9 | AP23: 계산: 22.3 (933,740,337,335원 / 4,185,358,693,668원). 참고: CJ ENM 본체 공시(CJ ENM USA INC. 출자 944,602,115,000원) 기준은 총자산대비 15.0, 자기자본대비 22.6(최초 공시 14.9·22.3) | AQ23: 계산: 3,734,534,926,200원 (발표 직전 거래일 2021-11-18 종가 170,300원 × 발행주식총수 21,929,154주, 자기주식 1,199,535주 포함). 종가는 Yahoo Finance(035760.KQ), 2015년 이후 분할 이벤트 없음 | AR23: 총자산대비 14.9%는 종속회사 주요경영사항 최종 정정공시(2022-01-19, 20220119900349)의 '지배회사의 연결자산총액대비'(분모 2020-12-31 연결 총자산). 자기자본 4,185,358,693,668원은 2021년 3분기말 연결 기준(2022-01-13 정정공시 20220113900426 명시; 최초 공시는 '2020년말 연결 자기자본에 자본금·자본잉여금 변동 반영'). 시가총액 주식수는 2021년 3분기보고서(20211115001194) 발행주식총수. | AS23: KRX:035760 | AT23: 인수 주체 SPC가 비상장이라 상장 지배회사 CJ ENM(코스닥)을 쓴다. 대상회사는 비상장. 매도측 모회사 Endeavor Group Holdings는 당시 NYSE:EDR 상장. 참고 주가(Yahoo Finance 일별): 2021-11-18 종가 170,300원 → 발표일 2021-11-19 종가 180,400원(+5.9%, 장중 고가 183,600원) → 11-22 170,400원 → 11-25 149,700원(SM엔터 조회공시 답변일). 같은 날 물적분할 공정공시가 있어 인수 효과만 분리하기 어렵다. | AU23: 2021-11-18(미국 현지): Endeavor 8-K(Item 7.01·8.01)와 공동 보도자료(BusinessWire)로 공식 공개. Hollywood Reporter가 WSJ의 같은 날 선행 보도를 언급했다는 검색 요약이 있으나 유료 차단으로 원문 미확인. 2021-11-19(KST) CJ ENM 거래소 공시(타법인주식및출자증권취득결정 2건·타인에대한채무보증결정·단기차입금증가결정·물적분할 공정공시) 동시 제출. 2021-11 CJ ENM 공시 목록에 본건 인수설 조회공시는 없음(같은 시기 조회공시는 SM엔터 인수설 건). | AV23: 2010: Graham Taylor·Chris Rice가 WME 글로벌 TV 부문을 이끌기 시작(이후 Endeavor Content로 분사, Broadcast 2025-09-26); 2017: Endeavor 산하 독립 스튜디오 Endeavor Content 출범(Endeavor 8-K EX-99.1 'launched in 2017', Toho 공시 '2017年に設立'); 2020: 인수대상 사업부 매출 63,463백만원·당기순손실 35,654백만원(감사 전, DART), 코로나로 납품 위축; 2020 말: CJ ENM 매각 가능성 파악 후 'Eagle' TF 구성(KED); 2021-01: CJ ENM 계열 본팩토리가 Endeavor Content와 제휴(KED); 2021-02: Endeavor가 WGA와 프랜차이즈 계약 — 제작사 지분 20% 초과 보유 금지(Endeavor 10-K); 2021-07: 소수 초청 입찰에 CJ ENM 참여, Apollo 등과 경쟁(KED); 2021 3분기: Endeavor가 매각 마케팅 개시, 2021-12-31 매각예정자산 분류(자산 USD 885.6M·부채 USD 507.3M, Endeavor 2022 10-K); 2021: Endeavor Content(제한 사업) 매출 USD 737M(전년 대비 콘텐츠 납품 USD 716M 증가, Endeavor 10-K); 2021-10 말: CJ ENM TF가 LA 방문해 협상(KED); 2021-11-18/19: 계약 체결·발표 | AW23: 2022-01-18(현지)/01-19(KST): 거래종결, 확정대금 USD 785.38M, 대상회사 49개 종속회사 포함 편입(2022 사업보고서 주석40); 2022-09-07(현지, TheWrap 'effective Wednesday')/09-08: 사명 Endeavor Content → FIFTH SEASON(CJ ENM FIFTH SEASON, LLC; CJ 뉴스룸 2022-09-20); 2022 회계연도: FS 매출 699,601,932천원·순손실 69,235,740천원, FS 영업권 손상 51,837백만원, 별도 CJ ENM USA INC. 투자주식 손상 약 582억원(계산); 2023-01: FS 경영진 대상 주식선택권 949,057주 부여(2023 사업보고서 주석25); 2023-04-27: 직원 8명(인력의 2%) 감원(Variety·TheWrap); 2023-08-24: 파업 여파로 임원·관리직 30명(12%) 추가 감원(TheWrap); 2023: 미국 작가·배우 파업으로 FS 납품·매출 급감(2023 사업보고서 경영진단), 2023-06 또는 09 Endeavor가 FS에 USD 30M 대여(만기 2026, Endeavor 10-K); 2023-08-24: FS 지분 매각설 보도에 CJ ENM '매각은 사실무근' 부인(MTN); 2023-12-11/12: Toho International이 FS에 USD 225M 출자(25%, 제3자 배정) — CJ ENM 60%·Endeavor 15%로 희석(C030); 2023 회계연도: FS 매출 347,619,868천원·순손실 117,915,270천원, FS 영업권 손상 약 950억원(Toho 출자가 기준 순공정가치), 별도 CJ ENM USA INC. 투자주식 손상 약 1,957억원(계산), 영화드라마 부문 영업손실 975억원; 2024 회계연도: <Severance S2> 등 납품 증가로 FS 매출 1,038,782,865천원·순손실 91,812,320천원, 4Q24 FS 영업이익 80억원(증권사 인용); 2025-07: <Severance> 에미상 27개 부문 후보, FS 관련 작품 총 36개 부문(한국경제 2025-07-17), 2025-09 에미상 8관왕(MTN 2026-07-24); 2025-09-26: 공동CEO Chris Rice 연말 퇴임 발표, Graham Taylor 단독 CEO(Broadcast); 2025 회계연도: FS 매출 789,711,200천원·순손실 42,163,187천원, 회사 발표로 2분기·4분기 흑자, 별도 CJ ENM USA INC. 투자주식 손상 832억원(2025 사업보고서); 2026-02-12 보도: Apple이 <Severance> IP·전체 권리를 약 USD 70M(TechCrunch 'just under $70 million')에 인수, 계약은 2025년 말 체결(Broadcast) — 제작비가 FS 감당 범위를 넘었다는 보도, FS는 총괄제작으로만 남음(TechCrunch·Broadcast); 2026-02-18: Peter Traugott TV 사장 선임 등 TV 조직 개편(Broadcast); 2026-03: J.P. Morgan 주관 5년 USD 500M 신용한도 갱신(SFNet 2026-03-18); 2026 상반기: FS 매출 284,057,366천원·순손실 33,590,641천원, CJ ENM 지분 60% 유지, 종속기업 94개(2026 반기보고서), 1Q26 FS 영업손실 29억원(하나증권 2026-05-08), FS 제작 <His & Hers>가 2026 상반기 넷플릭스 최다 시청 시리즈(MTN 2026-07-24) | AX23: 있음 — [연결 영업권] 2022년 51,836,961천원(약 518억원; CJ ENM 2022 사업보고서 20230320000724 연결주석 19(4) CGU별 영업권 변동표 '손상' 열과 (*1) 'CJ ENM FIFTH SEASON, LLC 에 대한 51,837백만원의 영업권에 대하여 무형자산손상차손을 인식', 사용가치 기준, 할인율 9.4%·영구성장률 1%; 그해 감사인 핵심감사사항 '방송부문 현금창출단위 및 CJ ENM FIFTH SEASON, LLC 영업권 손상'); 2023년 약 950억원(금액은 CJ ENM 관계자 발언 '지난해 약 950억원의 손상차손을 반영했다', 딜사이트 2024-02-08. DART 2023 사업보고서 20240318000857 연결주석 17은 전사 영업권 손상 114,292,880천원만 공시하고 CGU별 금액은 없음 — 계산: FS CGU 영업권 363,613,494→273,896,082천원 감소분 89,717,412천원에 FS 몫 환율효과(전사 영업권 환율효과 6,405,566천원 이내)를 더하면 약 897억~961억원으로 보도 금액과 부합. 2023 검사는 'CJ ENM FIFTH SEASON, LLC 현금창출단위 영업권의 경우 제3자 배정 유상증자 금액을 공정가치로 판단하여 순공정가치를 기초로' 수행 — C030의 Toho 출자가); 2024년 FS 영업권 손상 없음(계산: 전사 손상 38,388,927천원 = 스튜디오드래곤 CGU 감소 15,869,681 + 기타 CGU 감소 22,519,246천원과 정확히 일치, FS CGU 273,896,082→312,228,416천원 증가 38,332,334천원은 전사 환율효과 38,992,232천원의 일부; 20250319000884); 2025년 FS 영업권 손상 없음으로 추정(FS CGU 312,228,416→304,870,195천원 감소 7,358,221천원 ≈ 전사 환율효과 -7,491,517천원; 전사 손상 19,940,683천원은 연결범위변동 +17,796,115천원과 함께 미디어플랫폼·스튜디오드래곤 CGU 변동으로 설명됨; 20260318001469). 연결 누적 약 1,470억원(최초 영업권 389,634,540천원의 약 38%). [별도 종속기업투자주식] CJ ENM 본체가 보유한 CJ ENM USA INC.(FS 지분을 보유한 중간지주) 주식 손상: 2022년 계산 58,224,058천원(취득원가 952,620,000천원 vs 기말 장부 894,395,942천원, 2022 사업보고서 별도주석 15; 그해 종속기업투자 손상차손 총 79,243,853천원); 2023년 계산 약 195,698,793천원(기초 장부 894,395,943천원 + CJ ENM Investments America 이관분 92,823,880천원 → 기말 791,521,030천원; 2023 별도주석 15 '당기말 현재 투자주식 CJ ENM USA INC. 등에 대해 장부금액이 회수가능액에 미달하여 손상차손을 인식', 총 207,090,188천원; 2023년부터 CJ ENM USA INC.는 CJ ENM America 흡수합병·CJ ENM Investments America 편입으로 FS 외 자산도 포함); 2024년 없음(장부 791,521,030천원 유지, 20250319000884 별도주석 15); 2025년 832억원(20260318001469 별도주석 14 '(*1) ... CJ ENM USA Inc 832억원 등', 장부 791,521,030→708,311,978천원 = 83,209,052천원); 2026 상반기 없음(장부 708,311,978천원 유지, 20260814002422 별도주석 11). 별도 누적 337,131,902천원(취득원가 1,045,443,880천원의 32.2%). 2025년에는 연결 영업권 손상 없이 별도 투자주식만 손상된 점에 주의. 그 밖에 DS투자증권(2025-02-13)은 4Q24 'FS 손상차손 인식으로 이익 기여는 아쉬웠다'고 썼으나 계정·금액 미확인(연결 영업권 손상은 아님 — 위 계산). 2026 반기보고서까지 확인. | AY23: 수집·검토 기록에 인수 뒤 손상이 적혀 있음 | AZ23: 2020: 63,463백만원 (인수대상 사업부만, 감사 전, 1,088원/USD 환산 — 약 USD 58.3M; DART 20211119900185); 2021: USD 737 million (Endeavor 2022 10-K의 '제한 Endeavor Content 사업' 2021년 매출, US GAAP) | BA23: 2022: 699,601,932천원; 2023: 347,619,868천원; 2024: 1,038,782,865천원; 2025: 789,711,200천원 (최근 회계연도); 참고 2026 상반기: 284,057,366천원 | BB23: 미확인 (2020·2021 대상 사업 영업손익은 DART 공시·Endeavor 10-K 어디에도 별도 공개되지 않음). 대체 지표: 2020 당기순손실 35,654백만원(인수대상 사업부, 감사 전, DART 20211119900185) | BC23: 증권사 집계(공시 아님, 십억원): 2022: -44.0; 2023: -65.5; 2024: -52.0; 2025(잠정): -5.6 (DS투자증권 2026-02-06 표6 'CJ ENM 법인별 실적 추이', '자료: CJ ENM', 주 'CJ ENM과 별도 법인으로 구분된 이후의 실적'; 같은 표의 FS 매출 699.6·347.6·1,038.8·789.7십억원은 DART 종속기업 요약재무정보와 일치). 교차 확인: 2022는 IB토마토(2023-04-28) '418억원의 영업적자'로 약간 다름(-418억 vs -440억), 2023은 대신증권 '655억원의 적자'(아시아경제 2024-06-05)와 일치. 분기(언론·증권사 인용): 2Q23 -326억원(MTN 2023-08-24), 4Q24 +80억원(메리츠 2025-02-13), 2Q25 +32억원(메리츠 2025-08-08), 2025년 2분기·4분기 흑자(CJ ENM 보도자료 2026-02-05), 참고 1Q26 -29억원(하나증권 2026-05-08). CJ ENM 공시·IR 자료에는 FS 단독 연간 영업손익이 없음. 공시 대체 지표 당기순손익(CJ ENM 사업보고서 종속기업 요약재무정보, 천원): 2022: -69,235,740(주석1.2; 주석41.2는 -69,128,652); 2023: -117,915,270; 2024: -91,812,320; 2025: -42,163,187; 2026 상반기: -33,590,641. 상위 부문 영업손익(경영진단): 2022 미디어 부문 -46억원(당시 부문 구분), 영화드라마 부문 2023 -975억원, 2024 -413억원, 2025 -10억원. Endeavor 10-K: FS 2022 세전손실 USD 48.3M | BD23: 인수 후: CJ ENM FIFTH SEASON, LLC(56~94개 종속기업 포함) 연결, K-IFRS, 12월 결산, CJ ENM 연결조정 제거 전 금액, 원화 환산(CJ ENM 2022~2025 사업보고서 연결주석 '주요 종속기업 요약재무정보'·'비지배지분' 표, 2026 반기보고서). 인수 전: 2020은 CJ ENM 공시의 인수대상 사업부 감사 전 수치(원화), 2021은 Endeavor 10-K(US GAAP, USD)라 기준이 다르다. 상위 부문 실적은 CJ ENM이 2023년 사업부문을 재구분해(미디어 → 미디어플랫폼·영화드라마) 연도 간 범위가 다르다. | BE23: 2021-11-18 공동 보도자료: 강호성 CJ ENM 대표 "We are confident that this deal will create synergy between both companies" (Endeavor 8-K EX-99.1); 2024-02-07 4Q23 실적발표 자료: 엔터 부문 'FIFTH SEASON 턴어라운드', 영화드라마 '[FY2024] ... FIFTH SEASON 턴어라운드 목표'(4Q23 영화드라마 영업손실 53억원); 2023-08-24 MTN: CJ ENM 관계자 '피프스시즌은 SI 관점에서 인수했다. 보통 M&A 후 2~3년을 PMI(기업 인수·합병 후 통합 관리) 기간으로 본다', '외부 환경으로 지난해 딜리버리가 지연되면서 매출 인식 역시 지연됐을 뿐'(기사 재인용); 2024-02-08 딜사이트: CJ ENM 관계자 'CJ ENM이 피프스시즌을 인수할 당시 콘텐츠 제작사가 호황이였지만, 현재는 20~25% 정도 가격이 낮아졌다', '이에 지난해 약 950억원의 손상차손을 반영했다'(기사 재인용; '피프스시즌 투자유치 과정에서 지분가치 하락으로 손상차손을 950억원 반영'은 기자 서술); 2024-11-07 3Q24 실적발표 자료: 'FIFTH SEASON 부진 지속', '<베테랑2> 극장 매출 1위 흥행 불구, FIFTH SEASON 딜리버리 지연'; 2025-02-13 메리츠증권(4Q24 실적 리뷰): '피프스시즌은 80억원 영업이익 기록'; 2025-08-08 메리츠증권: '영화드라마는 피프스시즌의 흑자전환(OP 32억원) 성공으로 -12억원의 영업적자'; 2026-02-05 4Q25 실적발표 자료: 'FIFTH SEASON 턴어라운드 따른 수익성 강화', '전년 동기 대형 IP <Severance S2> 공급 따른 high-base 부담 불구, 유통 매출 호조 및 비용 효율화로 수익성 개선'; 같은 날 CJ ENM 보도자료: '피프스시즌은 ... 2분기에 이어 4분기에도 흑자를 달성했다'; 2026-05-08 하나증권(1Q26 리뷰): '피프스시즌이 3개의 드라마 타이틀이 반영되며 영업적자 29억원(+144억원)으로 크게 개선', '2분기 이후 ... 분기 200억원 내외의 적자가 예상된다'. (어닝콜 녹취록은 찾지 못해 IR 자료·보도자료·증권사 보고서로 대신함) | BF23: 완료 | BG23: 2026-10-26
A24: C021 | B24: CJ ENM | C24: 2022-07-01 | D24: Artworks Korea Co, Ltd. | E24: 152 | F24: False | H24: MA② | I24: MA② | J24: 같음 | K24: 있음 | L24: 일치 | M24: 편입 후 | N24: Closed | O24: 1.39 | P24: CJ ENM CO., Ltd. (KOSDAQ:A035760) | Q24: - | R24: CJ ENM CO., Ltd. (KOSDAQ:A035760) acquired the remaining 29.98% stake in Artworks Korea Co, Ltd. for KRW 1.8 billion on June 29, 2022. | S24: Commerce & Marketing | T24: E-commerce / Marketplace | U24: MA-1 그룹이 매수자 | V24: 기존 자회사 잔여지분 | W24: MA② 기존 지분 확대 | Y24: False | Z24: MA② 기존 지분 확대 | AA24: 편입 후 (매수자 CJ ENM은 그룹 지배회사이고, 대상 ㈜아트웍스코리아는 2017년 CJ오쇼핑(현 CJ ENM 법인)이 70.02%를 취득한 뒤 연결 종속회사였다. CJ오쇼핑 2017 사업보고서 20180330003559 연결대상 변동 '인수') | AB24: 완료 (2022-06-29 주식 취득일) | AC24: 1,803,967,000원 (보통주 151,200주, 29.98%, 주당 약 11,931원) | AD24: 원자료와 일치 (1,803.967백만원 ÷ 1.39 = 약 1,298원/달러로 2022-06 말 환율 수준) | AE24: 2022-07-01 | AF24: 기준 분류 유지: CJ ENM이 이미 70.02%를 보유해 연결하던 종속회사의 잔여 29.98%를 사들여 100%로 만든 거래다. 원자료에 매도자가 '-'로 비어 있으나, 아트웍스코리아 주요주주의주식보유변동 공시(20220701000088)에서 매도자는 개인 주요주주 김성헌(151,200주 전량 처분)으로 확인된다. | AG24: 같은 묶음의 C027(2022-12 CJ ENM 커머스부문의 리빙·남성패션 사업을 브랜드웍스코리아로 양도하고 유상증자)과 C028(2023-11 브랜드웍스코리아의 락포트컴퍼니코리아 브랜드 사업 양수)이 이 거래 뒤에 이어진다. 100% 자회사로 만든 뒤 브랜드 사업 집결 법인으로 쓰는 흐름이다. 2022-11-07 임시주주총회에서 사명을 아트웍스코리아에서 브랜드웍스코리아로 바꿨다. 지분 가치가 크게 떨어졌다. 2017년에는 70.02%(353,148주)를 20,306백만원(주당 약 57,500원)에 샀는데, 이번 29.98%는 주당 약 11,931원이다(100% 환산 약 60억원). 인수 목적을 밝힌 공시나 보도는 찾지 못했다(CJ ENM은 소액이라 별도 공시를 내지 않았다). 2018~2020년 CJ ENM 사업보고서의 손상 주석은 확인하지 않았다. 검토 추가: CJ ENM 2021 사업보고서 연결 주석은 "2022년 7월 3일 이후" 잔여 주식 전부를 과거 최대주주로부터 매입할 수 있는 콜옵션(CJ ENM 보유)과 매각할 수 있는 풋옵션(과거 최대주주 보유)이 있고 행사가액은 행사 시점 공정가치라고 적었다(20220321001256). 따라서 이 잔여 지분 취득은 2017년 최초 인수 계약에 들어 있던 콜·풋옵션 구조에 따른 것으로 보이며(옵션 행사인지 별도 합의인지는 미확인), 주당 가격이 2017년보다 크게 낮은 것은 공정가치 기준 가격 산정의 결과로 해석할 수 있다. | AH24: ㈜씨제이이엔엠(그룹 지배회사, 커머스부문이 옛 CJ오쇼핑) | AI24: 미확인 (CJ ENM은 이 취득을 따로 공시하지 않았고, 아트웍스코리아의 공정거래법 공시에는 목적 기재란이 없다. 딜사이트 2022-12-22 기사도 추가 취득 이유를 밝히지 않았다. 참고로 2017년 최초 인수 때 목적은 "상대적으로 취약한 남성 고객층을 확보해 경쟁력을 갖춘 상품·브랜드 사업자로 거듭나기 위해" (한경비즈니스 2017-05)) | AJ24: CJ ENM의 2021년 매출 중 커머스(TV홈쇼핑·T커머스·CJ온스타일 모바일)가 1조3,785억원(38.81%)이고, 나머지는 미디어·음악·영화다(2021 사업보고서 요약). 커머스는 2021년 영업이익의 40.45%를 차지했다 | AK24: 인접 | AL24: 아트웍스코리아는 '남심 취향저격' 큐레이션 온라인몰 펀샵과 PB 상품을 운영하는 전자상거래 회사다. CJ ENM 커머스부문과 같은 유통 가치사슬에 있지만 독립 온라인 전문몰·자체 브랜드 사업이라 인접으로 본다. 기존 종속회사의 잔여 지분이라 새 영역 진입은 아니다. | AM24: CJ ENM 2021-12-31 연결 총자산 7,940,625백만원 (별도 6,032,346백만원) | AN24: acq_total_assets와 같음 | AO24: 계산: 1,804 ÷ 6,032,346(2021말 별도 총자산, 백만원) = 0.030%. 연결 기준 1,804 ÷ 7,940,625 = 0.023% | AP24: 계산: 1,804 ÷ 3,327,171(2021말 별도 자본) = 0.054%. 연결 기준 1,804 ÷ 4,203,306 = 0.043% | AQ24: 계산: CJ ENM 2022-06-28 종가 97,300원 × 발행주식총수 21,929,154주 = 약 2조1,337억원 | AR24: 총자산과 자본은 CJ ENM 2021 사업보고서(20220321001256) 요약재무정보의 2021년말 값이다. 시가총액은 거래일(2022-06-29) 직전 거래일 종가(Yahoo Finance 035760.KQ, 분할 없음)와 2022 사업보고서 발행주식총수로 계산했다. 거래 공시에 비율이 없어 직접 계산했다. | AS24: KOSDAQ:035760 | AT24: 매수자 CJ ENM이 코스닥 상장사다. 대상 아트웍스코리아는 비상장이다. 거래가 공시 없이 이루어졌고 규모가 시가총액의 0.1% 미만이라 주가 반응을 기대하기 어렵다. | AU24: 2022-07-01 DART 최대주주등의주식보유변동·주요주주의주식보유변동(아트웍스코리아, 공정거래법 공시). 그 전의 보도나 CJ ENM 공시는 찾지 못했다 | AV24: 2000-11: ㈜아트웍스코리아 설립(전자상거래·인터넷쇼핑몰, 펀샵 운영); 2017-05: CJ오쇼핑이 지분 70.02%를 20,306백만원에 취득하는 주식매매계약(영업권 16,148백만원 인식, 비지배지분 29.98%는 개인주주 보유); 2017: 취득 후 매출 145.8억원·순이익 7.1억원 연결 반영; 2018-07: CJ오쇼핑이 CJ E&M을 흡수합병해 CJ ENM이 됨; 2020: 인수 뒤 처음 흑자를 냈다는 보도(뉴데일리 2021-04-15), 매출 323.5억원, 순손실 0.5억원; 2021: 매출 436.6억원, 영업손실 2.2억원, CJ ENM 연결 영업권 3,276백만원 손상; 2021-08·11: CJ ENM에서 단기차입 각 45억원 | AW24: 2022-06-29: CJ ENM이 잔여 29.98%를 1,804백만원에 취득해 100% 자회사화; 2022-11-07: 사명을 브랜드웍스코리아로 변경; 2022: 영업권 1,699백만원 추가 손상, 별도재무제표 투자주식 3,312백만원 손상; 2022-12-21: CJ ENM 커머스부문의 리빙·남성패션 사업 양수와 CJ ENM 대상 유상증자 결정(C027); 2023-11-01: 락포트컴퍼니코리아 브랜드 사업 영업양수 결정(C028), 2023-11-23 유상증자; 2023: 매출 1,074.2억원, 영업손실 48.0억원; 2024: 매출 1,378.8억원, 영업손실 73.8억원; 2025: 매출 1,261.8억원, 영업손실 13.1억원; 2024~2026: CJ ENM에서 자금 차입 반복 | AX24: 있음 (영업권: 2021년 3,276백만원(CJ ENM 2021 사업보고서 20220321001256), 2022년 1,699백만원(2022 사업보고서 20230320000724). 별도재무제표 투자주식: 2022년 3,312백만원 손상, 2022년초 장부가가 이미 7,525백만원으로 취득원가 20,306백만원보다 12,781백만원 낮아 2018~2021년 사이 추가 손상이 있었음(연도별 금액은 미확인). 2023·2025 사업보고서 손상 주석에서는 브랜드웍스코리아 언급을 찾지 못했다) | AY24: 수집·검토 기록에 인수 뒤 손상이 적혀 있음 | AZ24: 2020: 323.5억원; 2021: 436.6억원 | BA24: 2022: 335.6억원; 2023: 1,074.2억원; 2024: 1,378.8억원; 2025: 1,261.8억원 (2023년부터 C027·C028로 양수한 브랜드 사업 포함) | BB24: 2020: 미확인 (당기순손실 0.5억원, 언론은 '흑자' 보도); 2021: -2.2억원 (영업손실 218,610,619원) | BC24: 2022: -5.8억원; 2023: -48.0억원; 2024: -73.8억원; 2025: -13.1억원 | BD24: 2020·2021 매출은 CJ ENM 2021 사업보고서 연결 주석 '종속기업 요약 재무정보'(K-IFRS, 천원)이다. 2021 영업손익과 2022~2025 값은 브랜드웍스코리아 자체 감사보고서(별도, K-IFRS, 12월 결산: 2022 20230331002494, 2023 20240402002799, 2025 20260402002612의 당기·전기)다. 2022년 매출원가가 전년 322억원에서 142억원으로 줄어 매출 인식 방식이나 사업 구성이 바뀌었을 수 있다(확인 안 됨). 2023년 이후 매출 급증은 사업 양수 효과라 원래 펀샵 사업의 성과로 읽으면 안 된다. | BE24: 2021-04-15 뉴데일리(CJ오쇼핑 설명 재인용): "재미 큐레이션 쇼핑몰 '펀샵'을 운영하고 있는 아트웍스코리아는 작년에 2017년 CJ오쇼핑에 인수된 이후 처음으로 흑자를 기록했다"; 2025-01-17 뉴스토마토: CJ ENM 관계자 "사업 초기인 만큼 투자에 집중해 손실이 발생했지만 대표 브랜드를 육성함에 따라 매출 볼륨은 커지고 있다". CJ ENM IR 자료와 어닝콜에서 아트웍스코리아·브랜드웍스코리아를 직접 다룬 발언은 찾지 못했다. | BF24: 부분 | BG24: 2026-10-31
A25: C022 | B25: CJ ENM | C25: 2022-10-25 | D25: Blaad Studios Co. Ltd | E25: 80 | F25: False | G25: C022 | H25: MA② | I25: MA② | J25: 같음 | K25: 없음 (확인) | L25: 일치 | M25: 편입 후 | N25: Closed | O25: 15.89 | P25: CJ ENM CO., Ltd. (KOSDAQ:A035760) | Q25: - | R25: CJ ENM CO., Ltd. (KOSDAQ:A035760) acquired remaining 29.84% stake in Blaad Studios Co. Ltd from Yong Hwa Kim and others for KRW 22.6 billion on October 24, 2022. As per the terms of the deal, CJ ENM CO., Ltd. will acquire 1232 shares of Blaad Studios Co. Ltd each for KRW 18.375 million. Post-completion, CJ ENM CO., Ltd. will own 100% stake in Blaad Studios Co. Ltd. The Board of Directors of CJ ENM CO., Ltd has resolved the deal on October 24, 2022, and the expected date of signing the stock purchase contract is October 24, 2022. | S25: Content Production & Investment | T25: Content Production Studio | U25: MA-1 그룹이 매수자 | V25: 기존 자회사 잔여지분 | W25: MA② 기존 지분 확대 | Y25: False | Z25: MA② 기존 지분 확대 | AA25: 편입 후 (매수자 ㈜씨제이이엔엠 본체. 블라드스튜디오는 2020년 70.16% 인수로 이미 CJ ENM 연결 종속회사 — 2020 사업보고서 연결주석 '인수 70.16') | AB25: 완료 (2022-10-24 취득; 블라드스튜디오 최대주주등의주식보유변동 공시 변동일 2022-10-24, 취득 후 4,128주 100%) | AC25: 22,638,000,000원 (1,232주 × 18,375,000원; 이 중 김용화 960주 17,640백만원, 나머지 272주 4,998백만원은 기타 주주) | AD25: 원자료와 일치 (15.89; 22,638백만원 기준 암묵 환율 약 1,425원/USD) | AE25: 2022-10-24 (CJ ENM 이사회 결의일; 공개 공시는 2022-10-25) | AF25: 기준 분류 유지: CJ ENM이 2020년부터 70.16%를 보유해 연결하던 종속회사의 잔여 29.84% 매입. 금액·지분은 DART 공시와 원자료 설명란이 일치 | AG25: C023(본팩토리), C024(제이케이필름), C025(만화가족), C026(용필름)과 같은 날(2022-10-24 이사회) 결의된 '잔여지분 100% 확보 → CJ ENM 스튜디오스 흡수합병' 패키지의 일부(원자료 event_group은 C022/C023만 묶음). 김용화 몫(960주)만 공정거래법상 '특수관계인으로부터 주식의 취득' 공시 대상이라 그 공시는 176.4억원만 기재; 전체 1,232주·226.38억원은 블라드스튜디오의 최대주주등의주식보유변동 공시로 확인. 대상회사는 2022-12-13 씨제이이엔엠스튜디오스에 흡수합병돼 소멸했으므로 인수 후 실적은 합병법인(8개 제작사 통합) 실적으로 대신해 블라드 단독 성과 분리 불가. 2020년 최초 인수 대가 53,214백만원에는 신주 인수 대금이 섞인 것으로 보이나(취득 시 현금 37,665백만원 계상) 구주·신주 구분은 확인 안 함. 2022-12 스튜디오스 유상증자 배정대상 24명은 공시에 'OOO'로 가려져 있으나, 스튜디오스 2023 감사보고서 주석20.2가 '피합병법인의 기존 주주 24인'이라고 밝혀 옛 제작사 주주의 재투자임이 확인됨(김용화 등 개인별 참여 여부와 금액은 미확인). 이 유상증자에는 그룹이 하방을 보전하는 차액결제약정이 붙어 있음. 어닝콜 언급 미확인 | AH25: ㈜씨제이이엔엠(CJ ENM, 그룹 지배회사, 코스닥 상장) | AI25: "자회사 지분 추가 취득을 통한 제작 역량 강화" (DART 특수관계인으로부터 주식의 취득) / "콘텐츠 제작역량 통합을 통한 시너지효과 창출 및 경영의 효율성 달성" (씨제이이엔엠스튜디오스 회사합병결정) | AJ25: 방송·디지털 콘텐츠 제작·유통(미디어), 영화 제작·투자·배급, 음악, 공연, 홈쇼핑 커머스(CJ ENM 2020 사업보고서 연결주석 영업부문 구분: 방송·영화·음악·공연·커머스). 2022년 4월 OTT·멀티장르 제작 자회사 CJ ENM 스튜디오스 설립 | AK25: 핵심 | AL25: 블라드스튜디오는 '영상콘텐츠 제작, 배급 및 투자'(합병결정 공시) 회사로 CJ ENM 영화·방송 콘텐츠 제작 부문과 같은 영역. 인수 주체가 그룹 정점 CJ ENM 자신 | AM25: 7,940,625백만원 (CJ ENM 연결 자산총계, 2021-12-31; 2022 사업보고서 요약재무정보). 참고: 연결 자본총계 4,203,306백만원(2021-12-31) | AN25: acq_total_assets와 같음 | AO25: 계산: 0.29 (22,638백만원 / 2021-12-31 연결 자산총계 7,940,625백만원) | AP25: 계산: 0.54 (22,638백만원 / 2021-12-31 연결 자본총계 4,203,306백만원, 비지배지분 포함) | AQ25: 계산: 1,728,017,335,200원 (발표 직전 거래일 2022-10-21 종가 78,800원 × 발행주식총수 21,929,154주, 자기주식 1,199,535주 포함). 참고: 공시 전날 2022-10-24 종가 80,400원 기준 1,763,103,981,600원 | AR25: 거래 규모가 작아 주요사항보고서·거래소 취득결정 공시가 없어 총자산·자기자본 대비는 직접 계산. 분모는 CJ ENM 2022 사업보고서 요약재무정보의 2021-12-31 연결 값. 시가총액은 Yahoo Finance 035760.KQ 종가(2015년 이후 분할 없음, C019·C020 기록과 같은 처리) × 2022 사업보고서 발행주식총수 | AS25: KRX:035760 | AT25: 인수 주체 CJ ENM 본체가 코스닥 상장사(035760.KQ). 대상회사는 비상장. 같은 날(2022-10-24 이사회) 블라드스튜디오·본팩토리·제이케이필름·만화가족·용필름 잔여지분 취득과 2022-10-25 CJ ENM 스튜디오스 8개사 흡수합병 결정이 함께 공시돼 이벤트 창이 겹친다 | AU25: 2022-10-25 DART 공시(㈜씨제이이엔엠 '특수관계인으로부터주식의취득' 5건, 씨제이이엔엠스튜디오스 '회사합병결정'). 같은 날 딜사이트, 2022-10-26 비즈워치 보도. 공식 발표 전 인수설 보도는 찾지 못함 | AV25: 2019-11: 김용화 감독이 블라드스튜디오 설립(2019-11-04, 감사보고서 주석); 2020-02: CJ ENM이 '김용화 감독이 설립한 신생 제작사 블라드스튜디오에도 지분 투자' 보도(뉴데일리 2020-02-12); 2020-01~03(1분기): CJ ENM 70.16% 인수(2020 1분기보고서 사업결합 주석에 당기 발생으로 기재, 정확한 일자 미확인), 이전대가 현금 등 53,214,000천원, 영업권 23,104,525천원, 비지배지분 12,809,003천원(2020 사업보고서 주석39); 2020: 매출 111.6억원·영업손실 9.0억원; 2021: 매출 305.8억원·영업손실 11.9억원(자산 407.6억원 중 대부분 현금성 자산); 2022-04: CJ ENM 스튜디오스 현금출자 설립; 2022-07: 스튜디오스 대표에 윤제균 선임 | AW25: 2022-10-24: CJ ENM이 김용화 등으로부터 1,232주(29.84%) 22,638백만원에 취득, 100%; 2022-10-25: 씨제이이엔엠스튜디오스(주)가 본팩토리·제이케이필름·블라드스튜디오·엠메이커스·모호필름·용필름·만화가족·에그이즈커밍 8개사 흡수합병 결정(무증자, 합병비율 1:0, 합병기일 2022-12-13, 목적 '콘텐츠 제작역량 통합을 통한 시너지효과 창출 및 경영의 효율성 달성'); 2022-12-13: 합병 완료, 8개사 소멸·CJ ENM 연결범위에서 '합병'으로 제외(2022 사업보고서 주석); 2022-12-16: 스튜디오스 제3자배정 유상증자 350,083주×350,000원=122,529,050,000원(배정 대상 'OOO 등 24명'), CJ ENM 지분 100%→85.10%. 스튜디오스 2023 감사보고서 주석20.2에 따르면 배정 대상은 '피합병법인의 기존 주주 24인'이며, 스튜디오스는 이들과 '기초자산이 기준금액 이하로 매각될 경우 해당 차액을 지급'하는 차액결제약정을 맺음(2023 평가손실 5,277백만원, 2023말 파생상품부채 34,716백만원). 스튜디오스 재무제표상 유상증자 자본 증가는 92,644,090천원으로 공시 납입액보다 약 299억원 적음(차이가 약정의 최초 인식분인지는 확인 안 됨). CJ ENM은 이 주식과 관련한 '씨제이이엔엠 스튜디오스(주) 차액결제약정'을 파생상품 금융부채로 계상(2023 사업보고서 공정가치 주석); 2023: 스튜디오스 별도 영업손실 57.1억원; 2024~2025: 영업이익 92.5억원·103.6억원으로 흑자; 2025-12-30: 옛 본팩토리 공동대표 오광희가 스튜디오스 주식 38,758주(1.65%) 취득, CJ ENM 측 지분 86.75%(2026-02-04 공시); 2026-04-15: 스튜디오스 이사회, 만화 사업부문을 물적분할해 (주)만화가족 신설 결정(분할기일 2026-06-02); 2026-06-18: 스튜디오스 이사회, 보통주 81,167주(3.45%) 무상소각 감자 결정(감자기준일 2026-08-05, 사유 '경영 효율화'); 2026-08-05: 무상소각으로 CJ ENM 지분 85.10%→88.15%, 오광희 포함 동일인측 89.86%(2026-08-10 최대주주등의주식보유변동); 2026-08-06: 스튜디오스 이사회, 보통주 7,905주(0.35%) 유상소각 결정, 1주당 매수가격 350,000원, 감자기준일 2026-09-23(완료 여부 미확인) | AX25: 확인 안 됨 (CJ ENM 2022 사업보고서 연결주석: 2022년 영업권 손상은 제이에스픽쳐스·문화창고·밀리언볼트·브랜드웍스코리아·텔레닉스·CJ ENM FIFTH SEASON에만 인식. 2023·2025 사업보고서 연결주석: 씨제이이엔엠 스튜디오스(주) 현금창출단위 영업권이 2022·2023·2024·2025년말 모두 151,281,704천원으로 변동 없음. 2023년 영업권 손상 1,143억원은 CGU별 배분이 표에 없으나 스튜디오스 CGU 장부금액은 그대로임. 2024 사업보고서 본문은 따로 열지 않았고 2025 보고서 비교표로 대신함) | AY25: CJ ENM 2022 손상 대상 목록에 없음, 2022~2025 스튜디오스 현금창출단위 영업권 151,281,704천원 불변 | AZ25: 2020: 11,156,948,603원; 2021: 30,579,384,204원 | BA25: CJ ENM 스튜디오스 별도(K-IFRS): 2022(2022-04-05~12-31): 29,429,441,022원; 2023: 143,370,372,598원; 2024: 199,229,118,946원; 2025: 226,701,916,902원 | BB25: 2020: -895,481,106원; 2021: -1,189,591,202원 | BC25: CJ ENM 스튜디오스 별도(K-IFRS): 2022(2022-04-05~12-31): 1,539,118,903원; 2023: -5,710,635,594원; 2024: 9,245,240,627원; 2025: 10,358,886,351원 (참고: 당기순이익 2023 -9,348,907,073원, 2025 -2,950,231,356원; 2025 기타영업외비용 12,820,041,795원의 내역은 확인 안 함) | BD25: 인수 전: 블라드스튜디오 별도 K-IFRS, 12월 결산, 2021 감사보고서(제3기, 전기 2020 비교표시; 2020 기초는 미감사). 인수 후: 블라드가 2022-12-13 씨제이이엔엠스튜디오스에 흡수합병돼 소멸했으므로 합병법인 스튜디오스 별도 K-IFRS 실적(8개 제작사+스튜디오스 자체 사업 합산)으로 대신함. 동일지배 합병이라 2022년 스튜디오스 실적에는 합병 전 제작사 실적이 들어가지 않음 | BE25: 미확인 (2022-11-08 CJ ENM 3분기 실적 컨퍼런스콜 녹취는 gurufocus에 있으나 HTTP 403으로 열지 못함). 언론 재인용: 2022-10-26 비즈워치 'CJ ENM측은 이번 합병이 각 제작사들의 보유 지식재산(IP)을 자유롭게 활용해 콘텐츠 제작 역량을 강화하기 위한 차원이라고 설명했다' | BF25: 부분 | BG25: 2026-10-31
A26: C023 | B26: CJ ENM | C26: 2022-10-25 | D26: Bon Factory Co.,Ltd | E26: 59 | F26: False | G26: C022 | H26: MA② | I26: MA② | J26: 같음 | K26: 없음 (확인) | L26: 일치 | M26: 편입 후 | N26: Announced | O26: 26.39 | P26: CJ ENM CO., Ltd. (KOSDAQ:A035760) | Q26: - | R26: CJ ENM CO., Ltd. (KOSDAQ:A035760) agreed to acquire remaining 47% stake in Bon Factory Co.,Ltd from Kwang Hee Oh and Seok Hwan Moon for KRW 37.6 billion on October 24, 2022. As per the terms of the deal, CJ ENM CO will acquire 56,959 shares from Kwang Hee Oh and 56,960 shares from Seok Hwan Moon each for KRW 330,058. Post-completion, CJ ENM CO., Ltd. will own 100% stake in Bon Factory Co.,Ltd. The Board of Directors of CJ ENM CO., Ltd has resolved the deal on October 24, 2022, and the expected date of signing the stock purchase contract is October 24, 2022. | S26: Content Production & Investment | T26: Content Production Studio | U26: MA-1 그룹이 매수자 | V26: 기존 자회사 잔여지분 | W26: MA② 기존 지분 확대 | Y26: False | Z26: MA② 기존 지분 확대 | AA26: 편입 후 (매수자 ㈜씨제이이엔엠 본체. 본팩토리는 2019년 53% 인수로 이미 CJ ENM 연결 종속회사 — 2019 사업보고서 연결주석 '㈜본팩토리 인수 53.00%') | AB26: 완료 (2022-10-24 취득; 본팩토리 [기재정정]최대주주등의주식보유변동 공시 변동일 2022-10-24, 취득 후 242,382주 100%) | AC26: 37,599,877,302원 (113,919주 × 330,058원 계산값; 보유변동 공시 금액 37,599,877천원; 오광희 56,959주 18,799,773천원, 문석환 56,960주 18,800,104천원. 특수관계인 거래 공시에는 37,600백만원) | AD26: 원자료와 일치 (26.39; 37,600백만원 기준 암묵 환율 약 1,425원/USD) | AE26: 2022-10-24 (CJ ENM 이사회 결의일; 공개 공시는 2022-10-25) | AF26: 분류 유지, 상태 정정: 원자료 status=Announced → 완료. 근거: 본팩토리 최대주주등의주식보유변동(정정) 공시상 2022-10-24 CJ ENM 100% 보유, 씨제이이엔엠스튜디오스 합병결정 공시에 '소멸회사의 주식을 (주)씨제이이엔엠이 100%소유', 2022-12-13 합병 완료(2022 사업보고서). 기존 53%는 2019년부터 연결 종속회사 지분이므로 MA② 유지 | AG26: C022(블라드스튜디오)와 원자료 event_group이 같고, C024(제이케이필름)·C025(만화가족)·C026(용필름)도 같은 날 이사회에서 결의된 '잔여지분 100% 확보 → CJ ENM 스튜디오스 흡수합병' 패키지의 일부. 매도자 오광희·문석환은 본팩토리 공동대표(공시상 '계열회사 임원'). 본팩토리 최초 공시는 정정 전 변동일을 2022-10-14·단가 500원으로 잘못 적었다가 같은 날 정정. 2019 사업보고서 종속기업 요약재무의 본팩토리 2019 매출 1,238,937천원은 감사보고서 2019 매출 22,587,639,995원과 크게 달라 편입 후 기간분만 반영된 것으로 보임(추정). 본팩토리는 2022-12-13 스튜디오스에 흡수합병돼 소멸했으므로 인수 후 실적은 합병법인 실적으로 대신해 본팩토리 단독 성과 분리 불가. 매도자 오광희가 2025-12-30 스튜디오스 주식 1.65%를 취득한 것은 확인했으나 2022-12 스튜디오스 유상증자 배정대상 24명은 스튜디오스 2023 감사보고서 주석20.2에 '피합병법인의 기존 주주 24인'으로 적혀 있어 옛 제작사 주주의 재투자임이 확인됨(오광희·문석환 개인별 참여 여부와 금액은 미확인). 이 유상증자에는 그룹이 하방을 보전하는 차액결제약정이 붙어 있음. 2019년 최초 인수의 취득일은 2019-11-07(CJ ENM 2019 3분기보고서 보고기간 후 사건 주석)이며, 별도 발표 공시는 찾지 못함. 2019 연결 요약재무의 본팩토리 매출 1,238,937천원은 2019-11-07 이후 편입 기간분이라는 해석과 맞음. 어닝콜 언급 미확인 | AH26: ㈜씨제이이엔엠(CJ ENM, 그룹 지배회사, 코스닥 상장) | AI26: "자회사 지분 추가 취득을 통한 제작 역량 강화" (DART 특수관계인으로부터 주식의 취득) / "콘텐츠 제작역량 통합을 통한 시너지효과 창출 및 경영의 효율성 달성" (씨제이이엔엠스튜디오스 회사합병결정) | AJ26: 방송·디지털 콘텐츠 제작·유통(미디어), 영화 제작·투자·배급, 음악, 공연, 홈쇼핑 커머스(CJ ENM 2020 사업보고서 연결주석 영업부문 구분: 방송·영화·음악·공연·커머스). 2022년 4월 OTT·멀티장르 제작 자회사 CJ ENM 스튜디오스 설립 | AK26: 핵심 | AL26: 본팩토리는 '방송프로그램제작'(합병결정 공시; 2021 매출 중 방송제작매출 341.4억원) 드라마 제작사로 CJ ENM 방송(미디어) 콘텐츠 제작 부문과 같은 영역. 인수 주체가 그룹 정점 CJ ENM 자신 | AM26: 7,940,625백만원 (CJ ENM 연결 자산총계, 2021-12-31; 2022 사업보고서 요약재무정보). 참고: 연결 자본총계 4,203,306백만원(2021-12-31) | AN26: acq_total_assets와 같음 | AO26: 계산: 0.47 (37,600백만원 / 2021-12-31 연결 자산총계 7,940,625백만원) | AP26: 계산: 0.89 (37,600백만원 / 2021-12-31 연결 자본총계 4,203,306백만원, 비지배지분 포함) | AQ26: 계산: 1,728,017,335,200원 (발표 직전 거래일 2022-10-21 종가 78,800원 × 발행주식총수 21,929,154주, 자기주식 1,199,535주 포함). 참고: 공시 전날 2022-10-24 종가 80,400원 기준 1,763,103,981,600원 | AR26: 거래 규모가 작아 주요사항보고서·거래소 취득결정 공시가 없어 총자산·자기자본 대비는 직접 계산. 분모는 CJ ENM 2022 사업보고서 요약재무정보의 2021-12-31 연결 값. 시가총액은 Yahoo Finance 035760.KQ 종가(2015년 이후 분할 없음, C019·C020 기록과 같은 처리) × 2022 사업보고서 발행주식총수 | AS26: KRX:035760 | AT26: 인수 주체 CJ ENM 본체가 코스닥 상장사(035760.KQ). 대상회사는 비상장. 같은 날(2022-10-24 이사회) 블라드스튜디오·본팩토리·제이케이필름·만화가족·용필름 잔여지분 취득과 2022-10-25 CJ ENM 스튜디오스 8개사 흡수합병 결정이 함께 공시돼 이벤트 창이 겹친다 | AU26: 2022-10-25 DART 공시(㈜씨제이이엔엠 '특수관계인으로부터주식의취득' 5건, 씨제이이엔엠스튜디오스 '회사합병결정'). 같은 날 딜사이트, 2022-10-26 비즈워치 보도. 공식 발표 전 인수설 보도는 찾지 못함 | AV26: 2008-08: 본팩토리 설립(2008-08-18, 감사보고서 주석); 2019: 매출 225.9억원·영업이익 18.3억원; 2019-11-07: CJ ENM이 본팩토리 지분 53%를 15,900백만원에 취득(2019 3분기보고서 보고기간 후 사건 주석), 영업권 13,138,600천원(2019 사업보고서 주석40); 2020: 매출 312.2억원·영업이익 3.1억원; 2021: 매출 346.9억원·영업이익 30.0억원, 주주 CJ ENM 53.0%·문석환 23.5%·오광희 23.5%; 2022-04: CJ ENM 스튜디오스 현금출자 설립; 2022-07: 스튜디오스 대표에 윤제균 선임 | AW26: 2022-10-24: CJ ENM이 오광희·문석환으로부터 113,919주(47%) 37,600백만원에 취득, 100%; 2022-10-25: 씨제이이엔엠스튜디오스(주)가 본팩토리·제이케이필름·블라드스튜디오·엠메이커스·모호필름·용필름·만화가족·에그이즈커밍 8개사 흡수합병 결정(무증자, 합병비율 1:0, 합병기일 2022-12-13, 목적 '콘텐츠 제작역량 통합을 통한 시너지효과 창출 및 경영의 효율성 달성'); 2022-12-13: 합병 완료, 8개사 소멸·CJ ENM 연결범위에서 '합병'으로 제외(2022 사업보고서 주석); 2022-12-16: 스튜디오스 제3자배정 유상증자 350,083주×350,000원=122,529,050,000원(배정 대상 'OOO 등 24명'), CJ ENM 지분 100%→85.10%. 스튜디오스 2023 감사보고서 주석20.2에 따르면 배정 대상은 '피합병법인의 기존 주주 24인'이며, 스튜디오스는 이들과 '기초자산이 기준금액 이하로 매각될 경우 해당 차액을 지급'하는 차액결제약정을 맺음(2023 평가손실 5,277백만원, 2023말 파생상품부채 34,716백만원). 스튜디오스 재무제표상 유상증자 자본 증가는 92,644,090천원으로 공시 납입액보다 약 299억원 적음(차이가 약정의 최초 인식분인지는 확인 안 됨). CJ ENM은 이 주식과 관련한 '씨제이이엔엠 스튜디오스(주) 차액결제약정'을 파생상품 금융부채로 계상(2023 사업보고서 공정가치 주석); 2023: 스튜디오스 별도 영업손실 57.1억원; 2024~2025: 영업이익 92.5억원·103.6억원으로 흑자; 2025-12-30: 옛 본팩토리 공동대표 오광희가 스튜디오스 주식 38,758주(1.65%) 취득, CJ ENM 측 지분 86.75%(2026-02-04 공시); 2026-04-15: 스튜디오스 이사회, 만화 사업부문을 물적분할해 (주)만화가족 신설 결정(분할기일 2026-06-02); 2026-06-18: 스튜디오스 이사회, 보통주 81,167주(3.45%) 무상소각 감자 결정(감자기준일 2026-08-05, 사유 '경영 효율화'); 2026-08-05: 무상소각으로 CJ ENM 지분 85.10%→88.15%, 오광희 포함 동일인측 89.86%(2026-08-10 최대주주등의주식보유변동); 2026-08-06: 스튜디오스 이사회, 보통주 7,905주(0.35%) 유상소각 결정, 1주당 매수가격 350,000원, 감자기준일 2026-09-23(완료 여부 미확인) | AX26: 확인 안 됨 (CJ ENM 2022 사업보고서 연결주석: 2022년 영업권 손상은 제이에스픽쳐스·문화창고·밀리언볼트·브랜드웍스코리아·텔레닉스·CJ ENM FIFTH SEASON에만 인식. 2023·2025 사업보고서 연결주석: 씨제이이엔엠 스튜디오스(주) 현금창출단위 영업권이 2022·2023·2024·2025년말 모두 151,281,704천원으로 변동 없음. 2023년 영업권 손상 1,143억원은 CGU별 배분이 표에 없으나 스튜디오스 CGU 장부금액은 그대로임. 2024 사업보고서 본문은 따로 열지 않았고 2025 보고서 비교표로 대신함) | AY26: CJ ENM 2022 손상 대상 목록에 없음, 2022~2025 스튜디오스 현금창출단위 영업권 151,281,704천원 불변 | AZ26: 2020: 31,216,744,576원; 2021: 34,690,384,962원 | BA26: CJ ENM 스튜디오스 별도(K-IFRS): 2022(2022-04-05~12-31): 29,429,441,022원; 2023: 143,370,372,598원; 2024: 199,229,118,946원; 2025: 226,701,916,902원 | BB26: 2020: 312,885,711원; 2021: 2,996,584,157원 | BC26: CJ ENM 스튜디오스 별도(K-IFRS): 2022(2022-04-05~12-31): 1,539,118,903원; 2023: -5,710,635,594원; 2024: 9,245,240,627원; 2025: 10,358,886,351원 (참고: 당기순이익 2023 -9,348,907,073원, 2025 -2,950,231,356원; 2025 기타영업외비용 12,820,041,795원의 내역은 확인 안 함) | BD26: 인수 전: 본팩토리 별도 K-IFRS, 12월 결산, 2020·2021 감사보고서. 인수 후: 본팩토리가 2022-12-13 씨제이이엔엠스튜디오스에 흡수합병돼 소멸했으므로 합병법인 스튜디오스 별도 K-IFRS 실적(8개 제작사+스튜디오스 자체 사업 합산)으로 대신함. 동일지배 합병이라 2022년 스튜디오스 실적에는 합병 전 제작사 실적이 들어가지 않음 | BE26: 미확인 (2022-11-08 CJ ENM 3분기 실적 컨퍼런스콜 녹취는 gurufocus에 있으나 HTTP 403으로 열지 못함). 언론 재인용: 2022-10-26 비즈워치 'CJ ENM측은 이번 합병이 각 제작사들의 보유 지식재산(IP)을 자유롭게 활용해 콘텐츠 제작 역량을 강화하기 위한 차원이라고 설명했다' | BF26: 부분 | BG26: 2026-10-31
